Workbook

Sheet IMPORT_DATA
A1: COUNTRY | B1: Qty(KGS) | C1: Units | D1: Product Name | E1: PRICE PER KGS | F1: Currency | G1: IMPORTER NAME | H1: SUPPLIER NAME | I1: MONTH | J1: PRICE FOR KGS(USD) | K1: PRICE(USD) | L1: QTY(MTS) | M1: TOTAL PRICE(USD) | N1: PRODUCT_CATEGORY | O1: PRICE FOR TONN(USD) | P1: TOTAL PRICE(USD-TONN) | Q1: Year | R1: IMPORTER NAME_FINAL | S1: SUPPLIER NAME_FINAL
A2: AUSTRALIA | B2: 18648 | C2: KGS | D2: MCCP ACECEL 102 (90M) USP | E2: 2.352 | F2: AUD | G2: SIGACHI INDUSTRIES | H2: RAVENSWOOD | I2: Jan | J2: =IF(F2="USD", E2, E2 * IFERROR(VLOOKUP(F2, EXCHANGE_RATE!A:B, 2, FALSE), "Currency not found")) -> 1.50528 | K2: =ROUNDUP(J2,2) -> 1.51 | L2: =IF(C2="MTS", B2, B2 * IFERROR(VLOOKUP(C2, 'QTY_CONVERSIONS '!A:B, 2, FALSE), "Units not found")) -> 18.648 | M2: =B2*K2 -> 28158.48 | N2: =IFERROR(VLOOKUP(D2, Product_Category!A:B, 2, FALSE), "Uncategorized") -> MCC | O2: =K2 -> 1.51 | P2: =L2*O2 -> 28.15848 | Q2: 2023 | R2: =IFERROR(VLOOKUP(G2,'Importer Name'!A:B, 2, FALSE), "") -> SIGACHI INDUSTRIES | S2: =IFERROR(VLOOKUP(H2,'Supplier name '!A:B, 2, FALSE), "") -> RAVENSWOOD
A3: BRAZIL | B3: 20000 | C3: KGS | D3: MICROCEL MCC-101 | E3: 2.6 | F3: EUR | G3: AZELIS (INDIA) | H3: ITACEL FARMO | I3: =I2 -> Jan | J3: =IF(F3="USD", E3, E3 * IFERROR(VLOOKUP(F3, EXCHANGE_RATE!A:B, 2, FALSE), "Currency not found")) -> 2.782 | K3: =ROUNDUP(J3,2) -> 2.79 | L3: =IF(C3="MTS", B3, B3 * IFERROR(VLOOKUP(C3, 'QTY_CONVERSIONS '!A:B, 2, FALSE), "Units not found")) -> 20 | M3: =B3*K3 -> 55800 | N3: =IFERROR(VLOOKUP(D3, Product_Category!A:B, 2, FALSE), "Uncategorized") -> MCC | O3: =K3 -> 2.79 | P3: =L3*O3 -> 55.8 | Q3: =Q2 -> 2023 | R3: =IFERROR(VLOOKUP(G3,'Importer Name'!A:B, 2, FALSE), "") -> AZELIS (INDIA) | S3: =IFERROR(VLOOKUP(H3,'Supplier name '!A:B, 2, FALSE), "") -> ITACEL FARMO
A4: BRAZIL | B4: 10000 | C4: KGS | D4: MICROCEL MCC-101 | E4: 2.6 | F4: EUR | G4: AZELIS (INDIA) | H4: ITACEL FARMO | I4: =I3 -> Jan | J4: =IF(F4="USD", E4, E4 * IFERROR(VLOOKUP(F4, EXCHANGE_RATE!A:B, 2, FALSE), "Currency not found")) -> 2.782 | K4: =ROUNDUP(J4,2) -> 2.79 | L4: =IF(C4="MTS", B4, B4 * IFERROR(VLOOKUP(C4, 'QTY_CONVERSIONS '!A:B, 2, FALSE), "Units not found")) -> 10 | M4: =B4*K4 -> 27900 | N4: =IFERROR(VLOOKUP(D4, Product_Category!A:B, 2, FALSE), "Uncategorized") -> MCC | O4: =K4 -> 2.79 | P4: =L4*O4 -> 27.9 | Q4: =Q3 -> 2023 | R4: =IFERROR(VLOOKUP(G4,'Importer Name'!A:B, 2, FALSE), "") -> AZELIS (INDIA) | S4: =IFERROR(VLOOKUP(H4,'Supplier name '!A:B, 2, FALSE), "") -> ITACEL FARMO
A5: BRAZIL | B5: 5000 | C5: KGS | D5: MICROCEL MCC-101 | E5: 2.6 | F5: EUR | G5: AZELIS (INDIA) | H5: ITACEL FARMO | I5: =I4 -> Jan | J5: =IF(F5="USD", E5, E5 * IFERROR(VLOOKUP(F5, EXCHANGE_RATE!A:B, 2, FALSE), "Currency not found")) -> 2.782 | K5: =ROUNDUP(J5,2) -> 2.79 | L5: =IF(C5="MTS", B5, B5 * IFERROR(VLOOKUP(C5, 'QTY_CONVERSIONS '!A:B, 2, FALSE), "Units not found")) -> 5 | M5: =B5*K5 -> 13950 | N5: =IFERROR(VLOOKUP(D5, Product_Category!A:B, 2, FALSE), "Uncategorized") -> MCC | O5: =K5 -> 2.79 | P5: =L5*O5 -> 13.95 | Q5: =Q4 -> 2023 | R5: =IFERROR(VLOOKUP(G5,'Importer Name'!A:B, 2, FALSE), "") -> AZELIS (INDIA) | S5: =IFERROR(VLOOKUP(H5,'Supplier name '!A:B, 2, FALSE), "") -> ITACEL FARMO
A6: BRAZIL | B6: 20000 | C6: KGS | D6: MICROCEL MCC-102 | E6: 2.6 | F6: EUR | G6: AZELIS (INDIA) | H6: ITACEL FARMO | I6: =I5 -> Jan | J6: =IF(F6="USD", E6, E6 * IFERROR(VLOOKUP(F6, EXCHANGE_RATE!A:B, 2, FALSE), "Currency not found")) -> 2.782 | K6: =ROUNDUP(J6,2) -> 2.79 | L6: =IF(C6="MTS", B6, B6 * IFERROR(VLOOKUP(C6, 'QTY_CONVERSIONS '!A:B, 2, FALSE), "Units not found")) -> 20 | M6: =B6*K6 -> 55800 | N6: =IFERROR(VLOOKUP(D6, Product_Category!A:B, 2, FALSE), "Uncategorized") -> MCC | O6: =K6 -> 2.79 | P6: =L6*O6 -> 55.8 | Q6: =Q5 -> 2023 | R6: =IFERROR(VLOOKUP(G6,'Importer Name'!A:B, 2, FALSE), "") -> AZELIS (INDIA) | S6: =IFERROR(VLOOKUP(H6,'Supplier name '!A:B, 2, FALSE), "") -> ITACEL FARMO
A7: BRAZIL | B7: 20000 | C7: KGS | D7: MICROCEL MCC-101 | E7: 2.6 | F7: EUR | G7: AZELIS (INDIA) | H7: ITACEL FARMO | I7: =I6 -> Jan | J7: =IF(F7="USD", E7, E7 * IFERROR(VLOOKUP(F7, EXCHANGE_RATE!A:B, 2, FALSE), "Currency not found")) -> 2.782 | K7: =ROUNDUP(J7,2) -> 2.79 | L7: =IF(C7="MTS", B7, B7 * IFERROR(VLOOKUP(C7, 'QTY_CONVERSIONS '!A:B, 2, FALSE), "Units not found")) -> 20 | M7: =B7*K7 -> 55800 | N7: =IFERROR(VLOOKUP(D7, Product_Category!A:B, 2, FALSE), "Uncategorized") -> MCC | O7: =K7 -> 2.79 | P7: =L7*O7 -> 55.8 | Q7: =Q6 -> 2023 | R7: =IFERROR(VLOOKUP(G7,'Importer Name'!A:B, 2, FALSE), "") -> AZELIS (INDIA) | S7: =IFERROR(VLOOKUP(H7,'Supplier name '!A:B, 2, FALSE), "") -> ITACEL FARMO
A8: BRAZIL | B8: 10000 | C8: KGS | D8: MICROCEL MCC-102 | E8: 2.6 | F8: EUR | G8: AZELIS (INDIA) | H8: ITACEL FARMO | I8: =I7 -> Jan | J8: =IF(F8="USD", E8, E8 * IFERROR(VLOOKUP(F8, EXCHANGE_RATE!A:B, 2, FALSE), "Currency not found")) -> 2.782 | K8: =ROUNDUP(J8,2) -> 2.79 | L8: =IF(C8="MTS", B8, B8 * IFERROR(VLOOKUP(C8, 'QTY_CONVERSIONS '!A:B, 2, FALSE), "Units not found")) -> 10 | M8: =B8*K8 -> 27900 | N8: =IFERROR(VLOOKUP(D8, Product_Category!A:B, 2, FALSE), "Uncategorized") -> MCC | O8: =K8 -> 2.79 | P8: =L8*O8 -> 27.9 | Q8: =Q7 -> 2023 | R8: =IFERROR(VLOOKUP(G8,'Importer Name'!A:B, 2, FALSE), "") -> AZELIS (INDIA) | S8: =IFERROR(VLOOKUP(H8,'Supplier name '!A:B, 2, FALSE), "") -> ITACEL FARMO
A9: BRAZIL | B9: 2900 | C9: KGS | D9: MICROCEL MCC-200 | E9: 6.6 | F9: EUR | G9: AZELIS (INDIA) | H9: ITACEL FARMO | I9: =I8 -> Jan | J9: =IF(F9="USD", E9, E9 * IFERROR(VLOOKUP(F9, EXCHANGE_RATE!A:B, 2, FALSE), "Currency not found")) -> 7.062 | K9: =ROUNDUP(J9,2) -> 7.07 | L9: =IF(C9="MTS", B9, B9 * IFERROR(VLOOKUP(C9, 'QTY_CONVERSIONS '!A:B, 2, FALSE), "Units not found")) -> 2.9 | M9: =B9*K9 -> 20503 | N9: =IFERROR(VLOOKUP(D9, Product_Category!A:B, 2, FALSE), "Uncategorized") -> MCC | O9: =K9 -> 7.07 | P9: =L9*O9 -> 20.503 | Q9: =Q8 -> 2023 | R9: =IFERROR(VLOOKUP(G9,'Importer Name'!A:B, 2, FALSE), "") -> AZELIS (INDIA) | S9: =IFERROR(VLOOKUP(H9,'Supplier name '!A:B, 2, FALSE), "") -> ITACEL FARMO
A10: CHINA | B10: 18000 | C10: KGS | D10: SODIUM CMC | E10: 3.275 | F10: USD | G10: Nipra Hydro | H10: ANQIU EAGLE | I10: =I9 -> Jan | J10: =IF(F10="USD", E10, E10 * IFERROR(VLOOKUP(F10, EXCHANGE_RATE!A:B, 2, FALSE), "Currency not found")) -> 3.275 | K10: =ROUNDUP(J10,2) -> 3.28 | L10: =IF(C10="MTS", B10, B10 * IFERROR(VLOOKUP(C10, 'QTY_CONVERSIONS '!A:B, 2, FALSE), "Units not found")) -> 18 | M10: =B10*K10 -> 59040 | N10: =IFERROR(VLOOKUP(D10, Product_Category!A:B, 2, FALSE), "Uncategorized") -> CMC | O10: =K10 -> 3.28 | P10: =L10*O10 -> 59.04 | Q10: =Q9 -> 2023 | R10: =IFERROR(VLOOKUP(G10,'Importer Name'!A:B, 2, FALSE), "") -> Nipra Hydro | S10: =IFERROR(VLOOKUP(H10,'Supplier name '!A:B, 2, FALSE), "") -> ANQIU EAGLE
A11: CHINA | B11: 18000 | C11: KGS | D11: SODIUM CMC | E11: 3.42 | F11: USD | G11: BENTEC ORGANO | H11: ANQIU EAGLE | I11: =I10 -> Jan | J11: =IF(F11="USD", E11, E11 * IFERROR(VLOOKUP(F11, EXCHANGE_RATE!A:B, 2, FALSE), "Currency not found")) -> 3.42 | K11: =ROUNDUP(J11,2) -> 3.42 | L11: =IF(C11="MTS", B11, B11 * IFERROR(VLOOKUP(C11, 'QTY_CONVERSIONS '!A:B, 2, FALSE), "Units not found")) -> 18 | M11: =B11*K11 -> 61560 | N11: =IFERROR(VLOOKUP(D11, Product_Category!A:B, 2, FALSE), "Uncategorized") -> CMC | O11: =K11 -> 3.42 | P11: =L11*O11 -> 61.56 | Q11: =Q10 -> 2023 | R11: =IFERROR(VLOOKUP(G11,'Importer Name'!A:B, 2, FALSE), "") -> BENTEC ORGANO | S11: =IFERROR(VLOOKUP(H11,'Supplier name '!A:B, 2, FALSE), "") -> ANQIU EAGLE
A12: CHINA | B12: 18000 | C12: KGS | D12: CELLULOSE ETHER-SODIUM CMC | E12: 3.04 | F12: USD | G12: PERRY TRADING | H12: ANQIU EAGLE | I12: =I11 -> Jan | J12: =IF(F12="USD", E12, E12 * IFERROR(VLOOKUP(F12, EXCHANGE_RATE!A:B, 2, FALSE), "Currency not found")) -> 3.04 | K12: =ROUNDUP(J12,2) -> 3.04 | L12: =IF(C12="MTS", B12, B12 * IFERROR(VLOOKUP(C12, 'QTY_CONVERSIONS '!A:B, 2, FALSE), "Units not found")) -> 18 | M12: =B12*K12 -> 54720 | N12: =IFERROR(VLOOKUP(D12, Product_Category!A:B, 2, FALSE), "Uncategorized") -> CMC | O12: =K12 -> 3.04 | P12: =L12*O12 -> 54.72 | Q12: =Q11 -> 2023 | R12: =IFERROR(VLOOKUP(G12,'Importer Name'!A:B, 2, FALSE), "") -> PERRY TRADING | S12: =IFERROR(VLOOKUP(H12,'Supplier name '!A:B, 2, FALSE), "") -> ANQIU EAGLE
A13: CHINA | B13: 9000 | C13: KGS | D13: SODIUM CMC | E13: 2.57 | F13: USD | G13: PRACHIN CHEMICAL | H13: ANQIU EAGLE | I13: =I12 -> Jan | J13: =IF(F13="USD", E13, E13 * IFERROR(VLOOKUP(F13, EXCHANGE_RATE!A:B, 2, FALSE), "Currency not found")) -> 2.57 | K13: =ROUNDUP(J13,2) -> 2.57 | L13: =IF(C13="MTS", B13, B13 * IFERROR(VLOOKUP(C13, 'QTY_CONVERSIONS '!A:B, 2, FALSE), "Units not found")) -> 9 | M13: =B13*K13 -> 23130 | N13: =IFERROR(VLOOKUP(D13, Product_Category!A:B, 2, FALSE), "Uncategorized") -> CMC | O13: =K13 -> 2.57 | P13: =L13*O13 -> 23.13 | Q13: =Q12 -> 2023 | R13: =IFERROR(VLOOKUP(G13,'Importer Name'!A:B, 2, FALSE), "") -> PRACHIN CHEMICAL | S13: =IFERROR(VLOOKUP(H13,'Supplier name '!A:B, 2, FALSE), "") -> ANQIU EAGLE
A14: CHINA | B14: 300 | C14: KGS | D14: SODIUM CMC | E14: 3.15 | F14: USD | G14: INGREDION INDIA | H14: CHANGSHU WEALTHY | I14: =I13 -> Jan | J14: =IF(F14="USD", E14, E14 * IFERROR(VLOOKUP(F14, EXCHANGE_RATE!A:B, 2, FALSE), "Currency not found")) -> 3.15 | K14: =ROUNDUP(J14,2) -> 3.15 | L14: =IF(C14="MTS", B14, B14 * IFERROR(VLOOKUP(C14, 'QTY_CONVERSIONS '!A:B, 2, FALSE), "Units not found")) -> 0.3 | M14: =B14*K14 -> 945 | N14: =IFERROR(VLOOKUP(D14, Product_Category!A:B, 2, FALSE), "Uncategorized") -> CMC | O14: =K14 -> 3.15 | P14: =L14*O14 -> 0.945 | Q14: =Q13 -> 2023 | R14: =IFERROR(VLOOKUP(G14,'Importer Name'!A:B, 2, FALSE), "") -> INGREDION INDIA | S14: =IFERROR(VLOOKUP(H14,'Supplier name '!A:B, 2, FALSE), "") -> CHANGSHU WEALTHY
... A23: CHINA | B23: 20 | C23: MTS | D23: SODIUM CMC | E23: 2.66 | F23: USD | G23: MERIDIAN POLYMERS | H23: CHONGQING LIHONG | I23: =I22 -> Jan | J23: =IF(F23="USD", E23, E23 * IFERROR(VLOOKUP(F23, EXCHANGE_RATE!A:B, 2, FALSE), "Currency not found")) -> 2.66 | K23: =ROUNDUP(J23,2) -> 2.66 | L23: =IF(C23="MTS", B23, B23 * IFERROR(VLOOKUP(C23, 'QTY_CONVERSIONS '!A:B, 2, FALSE), "Units not found")) -> 20 | M23: =B23*K23 -> 53.2 | N23: =IFERROR(VLOOKUP(D23, Product_Category!A:B, 2, FALSE), "Uncategorized") -> CMC | O23: =K23 -> 2.66 | P23: =L23*O23 -> 53.2 | Q23: =Q22 -> 2023 | R23: =IFERROR(VLOOKUP(G23,'Importer Name'!A:B, 2, FALSE), "") -> MERIDIAN POLYMERS | S23: =IFERROR(VLOOKUP(H23,'Supplier name '!A:B, 2, FALSE), "") -> CHONGQING LIHONG
A24: CHINA | B24: 1000 | C24: KGS | D24: SODIUM CMC USP | E24: 41.7 | F24: CNY | G24: COLGATE-PALMOLIVE | H24: CHONGQING LIHONG | I24: =I23 -> Jan | J24: =IF(F24="USD", E24, E24 * IFERROR(VLOOKUP(F24, EXCHANGE_RATE!A:B, 2, FALSE), "Currency not found")) -> 5.838 | K24: =ROUNDUP(J24,2) -> 5.84 | L24: =IF(C24="MTS", B24, B24 * IFERROR(VLOOKUP(C24, 'QTY_CONVERSIONS '!A:B, 2, FALSE), "Units not found")) -> 1 | M24: =B24*K24 -> 5840 | N24: =IFERROR(VLOOKUP(D24, Product_Category!A:B, 2, FALSE), "Uncategorized") -> CMC | O24: =K24*1000 -> 5840 | P24: =L24*O24 -> 5840 | Q24: =Q23 -> 2023 | R24: =IFERROR(VLOOKUP(G24,'Importer Name'!A:B, 2, FALSE), "") -> COLGATE-PALMOLIVE | S24: =IFERROR(VLOOKUP(H24,'Supplier name '!A:B, 2, FALSE), "") -> CHONGQING LIHONG
A25: CHINA | B25: 18000 | C25: KGS | D25: SODIUM CMC | E25: 23.6 | F25: CNY | G25: COLGATE-PALMOLIVE | H25: CHONGQING LIHONG | I25: =I24 -> Jan | J25: =IF(F25="USD", E25, E25 * IFERROR(VLOOKUP(F25, EXCHANGE_RATE!A:B, 2, FALSE), "Currency not found")) -> 3.304 | K25: =ROUNDUP(J25,2) -> 3.31 | L25: =IF(C25="MTS", B25, B25 * IFERROR(VLOOKUP(C25, 'QTY_CONVERSIONS '!A:B, 2, FALSE), "Units not found")) -> 18 | M25: =B25*K25 -> 59580 | N25: =IFERROR(VLOOKUP(D25, Product_Category!A:B, 2, FALSE), "Uncategorized") -> CMC | O25: =K25 -> 3.31 | P25: =L25*O25 -> 59.58 | Q25: =Q24 -> 2023 | R25: =IFERROR(VLOOKUP(G25,'Importer Name'!A:B, 2, FALSE), "") -> COLGATE-PALMOLIVE | S25: =IFERROR(VLOOKUP(H25,'Supplier name '!A:B, 2, FALSE), "") -> CHONGQING LIHONG
A26: CHINA | B26: 18000 | C26: KGS | D26: SODIUM CMC | E26: 28 | F26: CNY | G26: COLGATE-PALMOLIVE | H26: CHONGQING LIHONG | I26: =I25 -> Jan | J26: =IF(F26="USD", E26, E26 * IFERROR(VLOOKUP(F26, EXCHANGE_RATE!A:B, 2, FALSE), "Currency not found")) -> 3.92 | K26: =ROUNDUP(J26,2) -> 3.92 | L26: =IF(C26="MTS", B26, B26 * IFERROR(VLOOKUP(C26, 'QTY_CONVERSIONS '!A:B, 2, FALSE), "Units not found")) -> 18 | M26: =B26*K26 -> 70560 | N26: =IFERROR(VLOOKUP(D26, Product_Category!A:B, 2, FALSE), "Uncategorized") -> CMC | O26: =K26 -> 3.92 | P26: =L26*O26 -> 70.56 | Q26: =Q25 -> 2023 | R26: =IFERROR(VLOOKUP(G26,'Importer Name'!A:B, 2, FALSE), "") -> COLGATE-PALMOLIVE | S26: =IFERROR(VLOOKUP(H26,'Supplier name '!A:B, 2, FALSE), "") -> CHONGQING LIHONG
A27: CHINA | B27: 20000 | C27: KGS | D27: SODIUM CMC | E27: 2.63 | F27: USD | G27: DHARIYAL POLYMERS | H27: CHONGQING LIHONG | I27: =I26 -> Jan | J27: =IF(F27="USD", E27, E27 * IFERROR(VLOOKUP(F27, EXCHANGE_RATE!A:B, 2, FALSE), "Currency not found")) -> 2.63 | K27: =ROUNDUP(J27,2) -> 2.63 | L27: =IF(C27="MTS", B27, B27 * IFERROR(VLOOKUP(C27, 'QTY_CONVERSIONS '!A:B, 2, FALSE), "Units not found")) -> 20 | M27: =B27*K27 -> 52600 | N27: =IFERROR(VLOOKUP(D27, Product_Category!A:B, 2, FALSE), "Uncategorized") -> CMC | O27: =K27 -> 2.63 | P27: =L27*O27 -> 52.6 | Q27: =Q26 -> 2023 | R27: =IFERROR(VLOOKUP(G27,'Importer Name'!A:B, 2, FALSE), "") -> DHARIYAL POLYMERS | S27: =IFERROR(VLOOKUP(H27,'Supplier name '!A:B, 2, FALSE), "") -> CHONGQING LIHONG
A28: CHINA | B28: 20000 | C28: KGS | D28: SODIUM CMC | E28: 2.63 | F28: USD | G28: DHARIYAL POLYMERS | H28: CHONGQING LIHONG | I28: =I27 -> Jan | J28: =IF(F28="USD", E28, E28 * IFERROR(VLOOKUP(F28, EXCHANGE_RATE!A:B, 2, FALSE), "Currency not found")) -> 2.63 | K28: =ROUNDUP(J28,2) -> 2.63 | L28: =IF(C28="MTS", B28, B28 * IFERROR(VLOOKUP(C28, 'QTY_CONVERSIONS '!A:B, 2, FALSE), "Units not found")) -> 20 | M28: =B28*K28 -> 52600 | N28: =IFERROR(VLOOKUP(D28, Product_Category!A:B, 2, FALSE), "Uncategorized") -> CMC | O28: =K28 -> 2.63 | P28: =L28*O28 -> 52.6 | Q28: =Q27 -> 2023 | R28: =IFERROR(VLOOKUP(G28,'Importer Name'!A:B, 2, FALSE), "") -> DHARIYAL POLYMERS | S28: =IFERROR(VLOOKUP(H28,'Supplier name '!A:B, 2, FALSE), "") -> CHONGQING LIHONG
A29: CHINA | B29: 18000 | C29: KGS | D29: SODIUM CMC | E29: 2.96 | F29: USD | G29: KAKKAT DRUGS | H29: JIANGSU GUOTAI | I29: =I28 -> Jan | J29: =IF(F29="USD", E29, E29 * IFERROR(VLOOKUP(F29, EXCHANGE_RATE!A:B, 2, FALSE), "Currency not found")) -> 2.96 | K29: =ROUNDUP(J29,2) -> 2.96 | L29: =IF(C29="MTS", B29, B29 * IFERROR(VLOOKUP(C29, 'QTY_CONVERSIONS '!A:B, 2, FALSE), "Units not found")) -> 18 | M29: =B29*K29 -> 53280 | N29: =IFERROR(VLOOKUP(D29, Product_Category!A:B, 2, FALSE), "Uncategorized") -> CMC | O29: =K29 -> 2.96 | P29: =L29*O29 -> 53.28 | Q29: =Q28 -> 2023 | R29: =IFERROR(VLOOKUP(G29,'Importer Name'!A:B, 2, FALSE), "") -> KAKKAT DRUGS | S29: =IFERROR(VLOOKUP(H29,'Supplier name '!A:B, 2, FALSE), "") -> JIANGSU GUOTAI
A30: CHINA | B30: 1000 | C30: KGS | D30: SODIUM CMC | E30: 3.8 | F30: USD | G30: BABA ENTERPRISES | H30: JIANGSU WEIKEM | I30: =I29 -> Jan | J30: =IF(F30="USD", E30, E30 * IFERROR(VLOOKUP(F30, EXCHANGE_RATE!A:B, 2, FALSE), "Currency not found")) -> 3.8 | K30: =ROUNDUP(J30,2) -> 3.8 | L30: =IF(C30="MTS", B30, B30 * IFERROR(VLOOKUP(C30, 'QTY_CONVERSIONS '!A:B, 2, FALSE), "Units not found")) -> 1 | M30: =B30*K30 -> 3800 | N30: =IFERROR(VLOOKUP(D30, Product_Category!A:B, 2, FALSE), "Uncategorized") -> CMC | O30: =K30 -> 3.8 | P30: =L30*O30 -> 3.8 | Q30: =Q29 -> 2023 | R30: =IFERROR(VLOOKUP(G30,'Importer Name'!A:B, 2, FALSE), "") -> BABA ENTERPRISES | S30: =IFERROR(VLOOKUP(H30,'Supplier name '!A:B, 2, FALSE), "") -> JIANGSU WEIKEM
A31: CHINA | B31: 1000 | C31: KGS | D31: SODIUM CMC | E31: 3.8 | F31: USD | G31: BABA ENTERPRISES | H31: JIANGSU WEIKEM | I31: =I30 -> Jan | J31: =IF(F31="USD", E31, E31 * IFERROR(VLOOKUP(F31, EXCHANGE_RATE!A:B, 2, FALSE), "Currency not found")) -> 3.8 | K31: =ROUNDUP(J31,2) -> 3.8 | L31: =IF(C31="MTS", B31, B31 * IFERROR(VLOOKUP(C31, 'QTY_CONVERSIONS '!A:B, 2, FALSE), "Units not found")) -> 1 | M31: =B31*K31 -> 3800 | N31: =IFERROR(VLOOKUP(D31, Product_Category!A:B, 2, FALSE), "Uncategorized") -> CMC | O31: =K31 -> 3.8 | P31: =L31*O31 -> 3.8 | Q31: =Q30 -> 2023 | R31: =IFERROR(VLOOKUP(G31,'Importer Name'!A:B, 2, FALSE), "") -> BABA ENTERPRISES | S31: =IFERROR(VLOOKUP(H31,'Supplier name '!A:B, 2, FALSE), "") -> JIANGSU WEIKEM
A32: CHINA | B32: 15000 | C32: KGS | D32: SODIUM CMC | E32: 2.2366 | F32: USD | G32: PHARCOS SPECIAL | H32: JINING FORTUNE | I32: =I31 -> Jan | J32: =IF(F32="USD", E32, E32 * IFERROR(VLOOKUP(F32, EXCHANGE_RATE!A:B, 2, FALSE), "Currency not found")) -> 2.2366 | K32: =ROUNDUP(J32,2) -> 2.24 | L32: =IF(C32="MTS", B32, B32 * IFERROR(VLOOKUP(C32, 'QTY_CONVERSIONS '!A:B, 2, FALSE), "Units not found")) -> 15 | M32: =B32*K32 -> 33600 | N32: =IFERROR(VLOOKUP(D32, Product_Category!A:B, 2, FALSE), "Uncategorized") -> CMC | O32: =K32 -> 2.24 | P32: =L32*O32 -> 33.6 | Q32: =Q31 -> 2023 | R32: =IFERROR(VLOOKUP(G32,'Importer Name'!A:B, 2, FALSE), "") -> PHARCOS SPECIAL | S32: =IFERROR(VLOOKUP(H32,'Supplier name '!A:B, 2, FALSE), "") -> JINING FORTUNE
A33: CHINA | B33: 1500 | C33: KGS | D33: SODIUM CMC | E33: 2.56 | F33: USD | G33: SANGUINE GENETICS | H33: KERAY CHEM | I33: =I32 -> Jan | J33: =IF(F33="USD", E33, E33 * IFERROR(VLOOKUP(F33, EXCHANGE_RATE!A:B, 2, FALSE), "Currency not found")) -> 2.56 | K33: =ROUNDUP(J33,2) -> 2.56 | L33: =IF(C33="MTS", B33, B33 * IFERROR(VLOOKUP(C33, 'QTY_CONVERSIONS '!A:B, 2, FALSE), "Units not found")) -> 1.5 | M33: =B33*K33 -> 3840 | N33: =IFERROR(VLOOKUP(D33, Product_Category!A:B, 2, FALSE), "Uncategorized") -> CMC | O33: =K33 -> 2.56 | P33: =L33*O33 -> 3.84 | Q33: =Q32 -> 2023 | R33: =IFERROR(VLOOKUP(G33,'Importer Name'!A:B, 2, FALSE), "") -> SANGUINE GENETICS | S33: =IFERROR(VLOOKUP(H33,'Supplier name '!A:B, 2, FALSE), "") -> KERAY CHEM
A34: CHINA | B34: 23000 | C34: KGS | D34: CMC | E34: 1.97 | F34: USD | G34: PAPYRUS PAPER | H34: M/S. JOIN GOAL | I34: =I33 -> Jan | J34: =IF(F34="USD", E34, E34 * IFERROR(VLOOKUP(F34, EXCHANGE_RATE!A:B, 2, FALSE), "Currency not found")) -> 1.97 | K34: =ROUNDUP(J34,2) -> 1.97 | L34: =IF(C34="MTS", B34, B34 * IFERROR(VLOOKUP(C34, 'QTY_CONVERSIONS '!A:B, 2, FALSE), "Units not found")) -> 23 | M34: =B34*K34 -> 45310 | N34: =IFERROR(VLOOKUP(D34, Product_Category!A:B, 2, FALSE), "Uncategorized") -> CMC | O34: =K34 -> 1.97 | P34: =L34*O34 -> 45.31 | Q34: =Q33 -> 2023 | R34: =IFERROR(VLOOKUP(G34,'Importer Name'!A:B, 2, FALSE), "") -> PAPYRUS PAPER | S34: =IFERROR(VLOOKUP(H34,'Supplier name '!A:B, 2, FALSE), "") -> M/S. JOIN GOAL
A35: CHINA | B35: 10000 | C35: KGS | D35: SODIUM CMC | E35: 4.05 | F35: USD | G35: DANISCO (INDIA) | H35: SHANGHAI SHENGUANG | I35: =I34 -> Jan | J35: =IF(F35="USD", E35, E35 * IFERROR(VLOOKUP(F35, EXCHANGE_RATE!A:B, 2, FALSE), "Currency not found")) -> 4.05 | K35: =ROUNDUP(J35,2) -> 4.05 | L35: =IF(C35="MTS", B35, B35 * IFERROR(VLOOKUP(C35, 'QTY_CONVERSIONS '!A:B, 2, FALSE), "Units not found")) -> 10 | M35: =B35*K35 -> 40500 | N35: =IFERROR(VLOOKUP(D35, Product_Category!A:B, 2, FALSE), "Uncategorized") -> CMC | O35: =K35 -> 4.05 | P35: =L35*O35 -> 40.5 | Q35: =Q34 -> 2023 | R35: =IFERROR(VLOOKUP(G35,'Importer Name'!A:B, 2, FALSE), "") -> DANISCO (INDIA) | S35: =IFERROR(VLOOKUP(H35,'Supplier name '!A:B, 2, FALSE), "") -> SHANGHAI SHENGUANG
A36: CHINA | B36: 20000 | C36: KGS | D36: SODIUM CMC | E36: 3.95 | F36: USD | G36: DANISCO (INDIA) | H36: SHANGHAI SHENGUANG | I36: =I35 -> Jan | J36: =IF(F36="USD", E36, E36 * IFERROR(VLOOKUP(F36, EXCHANGE_RATE!A:B, 2, FALSE), "Currency not found")) -> 3.95 | K36: =ROUNDUP(J36,2) -> 3.95 | L36: =IF(C36="MTS", B36, B36 * IFERROR(VLOOKUP(C36, 'QTY_CONVERSIONS '!A:B, 2, FALSE), "Units not found")) -> 20 | M36: =B36*K36 -> 79000 | N36: =IFERROR(VLOOKUP(D36, Product_Category!A:B, 2, FALSE), "Uncategorized") -> CMC | O36: =K36 -> 3.95 | P36: =L36*O36 -> 79 | Q36: =Q35 -> 2023 | R36: =IFERROR(VLOOKUP(G36,'Importer Name'!A:B, 2, FALSE), "") -> DANISCO (INDIA) | S36: =IFERROR(VLOOKUP(H36,'Supplier name '!A:B, 2, FALSE), "") -> SHANGHAI SHENGUANG
... A176: JAPAN | B176: 12000 | C176: KGS | D176: MCC CEOLUS UF-711 | E176: 10.74 | F176: USD | G176: APOTEX RESEARCH | H176: ASAHI KASEI | I176: =I175 -> Jan | J176: =IF(F176="USD", E176, E176 * IFERROR(VLOOKUP(F176, EXCHANGE_RATE!A:B, 2, FALSE), "Currency not found")) -> 10.74 | K176: =ROUNDUP(J176,2) -> 10.74 | L176: =IF(C176="MTS", B176, B176 * IFERROR(VLOOKUP(C176, 'QTY_CONVERSIONS '!A:B, 2, FALSE), "Units not found")) -> 12 | M176: =B176*K176 -> 128880 | N176: =IFERROR(VLOOKUP(D176, Product_Category!A:B, 2, FALSE), "Uncategorized") -> MCC | O176: =K176 -> 10.74 | P176: =L176*O176 -> 128.88 | Q176: =Q175 -> 2023 | R176: =IFERROR(VLOOKUP(G176,'Importer Name'!A:B, 2, FALSE), "") -> APOTEX RESEARCH | S176: =IFERROR(VLOOKUP(H176,'Supplier name '!A:B, 2, FALSE), "") -> ASAHI KASEI
A177: JAPAN | B177: 300 | C177: KGS | D177: MCC CELPHERE CP-708 | E177: 66.58 | F177: USD | G177: SIGNET EXCIPIENTS | H177: ASAHI KASEI | I177: =I176 -> Jan | J177: =IF(F177="USD", E177, E177 * IFERROR(VLOOKUP(F177, EXCHANGE_RATE!A:B, 2, FALSE), "Currency not found")) -> 66.58 | K177: =ROUNDUP(J177,2) -> 66.58 | L177: =IF(C177="MTS", B177, B177 * IFERROR(VLOOKUP(C177, 'QTY_CONVERSIONS '!A:B, 2, FALSE), "Units not found")) -> 0.3 | M177: =B177*K177 -> 19974 | N177: =IFERROR(VLOOKUP(D177, Product_Category!A:B, 2, FALSE), "Uncategorized") -> MCC | O177: =K177*1000 -> 66580 | P177: =L177*O177 -> 19974 | Q177: =Q176 -> 2023 | R177: =IFERROR(VLOOKUP(G177,'Importer Name'!A:B, 2, FALSE), "") -> SIGNET EXCIPIENTS | S177: =IFERROR(VLOOKUP(H177,'Supplier name '!A:B, 2, FALSE), "") -> ASAHI KASEI
A178: JAPAN | B178: 600 | C178: KGS | D178: MCC CEOLUS UF-702 | E178: 10.74 | F178: USD | G178: MYLAN LAB | H178: M/S. ASAHI KASEI | I178: =I177 -> Jan | J178: =IF(F178="USD", E178, E178 * IFERROR(VLOOKUP(F178, EXCHANGE_RATE!A:B, 2, FALSE), "Currency not found")) -> 10.74 | K178: =ROUNDUP(J178,2) -> 10.74 | L178: =IF(C178="MTS", B178, B178 * IFERROR(VLOOKUP(C178, 'QTY_CONVERSIONS '!A:B, 2, FALSE), "Units not found")) -> 0.6 | M178: =B178*K178 -> 6444 | N178: =IFERROR(VLOOKUP(D178, Product_Category!A:B, 2, FALSE), "Uncategorized") -> MCC | O178: =K178 -> 10.74 | P178: =L178*O178 -> 6.444 | Q178: =Q177 -> 2023 | R178: =IFERROR(VLOOKUP(G178,'Importer Name'!A:B, 2, FALSE), "") -> MYLAN LAB | S178: =IFERROR(VLOOKUP(H178,'Supplier name '!A:B, 2, FALSE), "") -> M/S. ASAHI KASEI
A179: JAPAN | B179: 300 | C179: KGS | D179: MCC CEOLUS | E179: 2382 | F179: JPY | G179: KANSAI NEROLAC | H179: YONEI & CO | I179: =I178 -> Jan | J179: =IF(F179="USD", E179, E179 * IFERROR(VLOOKUP(F179, EXCHANGE_RATE!A:B, 2, FALSE), "Currency not found")) -> 15.9594 | K179: =ROUNDUP(J179,2) -> 15.96 | L179: =IF(C179="MTS", B179, B179 * IFERROR(VLOOKUP(C179, 'QTY_CONVERSIONS '!A:B, 2, FALSE), "Units not found")) -> 0.3 | M179: =B179*K179 -> 4788 | N179: =IFERROR(VLOOKUP(D179, Product_Category!A:B, 2, FALSE), "Uncategorized") -> MCC | O179: =K179*1000 -> 15960 | P179: =L179*O179 -> 4788 | Q179: =Q178 -> 2023 | R179: =IFERROR(VLOOKUP(G179,'Importer Name'!A:B, 2, FALSE), "") -> KANSAI NEROLAC | S179: =IFERROR(VLOOKUP(H179,'Supplier name '!A:B, 2, FALSE), "") -> YONEI & CO
A180: NETHERLANDS | B180: 14280 | C180: KGS | D180: LIGAMED MF-2-V-MB- MG STEARATE | E180: 5.198 | F180: EUR | G180: AZELIS (INDIA) | H180: PETER GREVEN | I180: =I179 -> Jan | J180: =IF(F180="USD", E180, E180 * IFERROR(VLOOKUP(F180, EXCHANGE_RATE!A:B, 2, FALSE), "Currency not found")) -> 5.56186 | K180: =ROUNDUP(J180,2) -> 5.57 | L180: =IF(C180="MTS", B180, B180 * IFERROR(VLOOKUP(C180, 'QTY_CONVERSIONS '!A:B, 2, FALSE), "Units not found")) -> 14.28 | M180: =B180*K180 -> 79539.6 | N180: =IFERROR(VLOOKUP(D180, Product_Category!A:B, 2, FALSE), "Uncategorized") -> MAGNESIUM STEARATE | O180: =K180 -> 5.57 | P180: =L180*O180 -> 79.5396 | Q180: =Q179 -> 2023 | R180: =IFERROR(VLOOKUP(G180,'Importer Name'!A:B, 2, FALSE), "") -> AZELIS (INDIA) | S180: =IFERROR(VLOOKUP(H180,'Supplier name '!A:B, 2, FALSE), "") -> PETER GREVEN
A181: NETHERLANDS | B181: 11340 | C181: KGS | D181: LIGAMED MF-2-V-MB- MG STEARATE | E181: 5.412 | F181: EUR | G181: AZELIS (INDIA) | H181: PETER GREVEN | I181: =I180 -> Jan | J181: =IF(F181="USD", E181, E181 * IFERROR(VLOOKUP(F181, EXCHANGE_RATE!A:B, 2, FALSE), "Currency not found")) -> 5.79084 | K181: =ROUNDUP(J181,2) -> 5.8 | L181: =IF(C181="MTS", B181, B181 * IFERROR(VLOOKUP(C181, 'QTY_CONVERSIONS '!A:B, 2, FALSE), "Units not found")) -> 11.34 | M181: =B181*K181 -> 65772 | N181: =IFERROR(VLOOKUP(D181, Product_Category!A:B, 2, FALSE), "Uncategorized") -> MAGNESIUM STEARATE | O181: =K181 -> 5.8 | P181: =L181*O181 -> 65.772 | Q181: =Q180 -> 2023 | R181: =IFERROR(VLOOKUP(G181,'Importer Name'!A:B, 2, FALSE), "") -> AZELIS (INDIA) | S181: =IFERROR(VLOOKUP(H181,'Supplier name '!A:B, 2, FALSE), "") -> PETER GREVEN
A182: NETHERLANDS | B182: 16800 | C182: KGS | D182: LIGAMED MF-2-V-MB- MG STEARATE | E182: 5.489 | F182: EUR | G182: AZELIS (INDIA) | H182: PETER GREVEN | I182: =I181 -> Jan | J182: =IF(F182="USD", E182, E182 * IFERROR(VLOOKUP(F182, EXCHANGE_RATE!A:B, 2, FALSE), "Currency not found")) -> 5.87323 | K182: =ROUNDUP(J182,2) -> 5.88 | L182: =IF(C182="MTS", B182, B182 * IFERROR(VLOOKUP(C182, 'QTY_CONVERSIONS '!A:B, 2, FALSE), "Units not found")) -> 16.8 | M182: =B182*K182 -> 98784 | N182: =IFERROR(VLOOKUP(D182, Product_Category!A:B, 2, FALSE), "Uncategorized") -> MAGNESIUM STEARATE | O182: =K182 -> 5.88 | P182: =L182*O182 -> 98.784 | Q182: =Q181 -> 2023 | R182: =IFERROR(VLOOKUP(G182,'Importer Name'!A:B, 2, FALSE), "") -> AZELIS (INDIA) | S182: =IFERROR(VLOOKUP(H182,'Supplier name '!A:B, 2, FALSE), "") -> PETER GREVEN
A183: NETHERLANDS | B183: 2520 | C183: KGS | D183: LIGAMED MF-2-V-MB- MG STEARATE | E183: 6.014 | F183: EUR | G183: MARKSANS PHARMA | H183: PETER GREVEN | I183: =I182 -> Jan | J183: =IF(F183="USD", E183, E183 * IFERROR(VLOOKUP(F183, EXCHANGE_RATE!A:B, 2, FALSE), "Currency not found")) -> 6.43498 | K183: =ROUNDUP(J183,2) -> 6.44 | L183: =IF(C183="MTS", B183, B183 * IFERROR(VLOOKUP(C183, 'QTY_CONVERSIONS '!A:B, 2, FALSE), "Units not found")) -> 2.52 | M183: =B183*K183 -> 16228.8 | N183: =IFERROR(VLOOKUP(D183, Product_Category!A:B, 2, FALSE), "Uncategorized") -> MAGNESIUM STEARATE | O183: =K183 -> 6.44 | P183: =L183*O183 -> 16.2288 | Q183: =Q182 -> 2023 | R183: =IFERROR(VLOOKUP(G183,'Importer Name'!A:B, 2, FALSE), "") -> MARKSANS PHARMA | S183: =IFERROR(VLOOKUP(H183,'Supplier name '!A:B, 2, FALSE), "") -> PETER GREVEN
A184: NETHERLANDS | B184: 840 | C184: KGS | D184: LIGAMED MF-2-V-MB- MG STEARATE | E184: 7.847 | F184: EUR | G184: MYLAN LAB | H184: PETER GREVEN | I184: =I183 -> Jan | J184: =IF(F184="USD", E184, E184 * IFERROR(VLOOKUP(F184, EXCHANGE_RATE!A:B, 2, FALSE), "Currency not found")) -> 8.39629 | K184: =ROUNDUP(J184,2) -> 8.4 | L184: =IF(C184="MTS", B184, B184 * IFERROR(VLOOKUP(C184, 'QTY_CONVERSIONS '!A:B, 2, FALSE), "Units not found")) -> 0.84 | M184: =B184*K184 -> 7056 | N184: =IFERROR(VLOOKUP(D184, Product_Category!A:B, 2, FALSE), "Uncategorized") -> MAGNESIUM STEARATE | O184: =K184 -> 8.4 | P184: =L184*O184 -> 7.056 | Q184: =Q183 -> 2023 | R184: =IFERROR(VLOOKUP(G184,'Importer Name'!A:B, 2, FALSE), "") -> MYLAN LAB | S184: =IFERROR(VLOOKUP(H184,'Supplier name '!A:B, 2, FALSE), "") -> PETER GREVEN
A185: NETHERLANDS | B185: 4725 | C185: KGS | D185: PRIMELLOSE CCS USP-NF.PH.EUR.JP | E185: 15.44 | F185: EUR | G185: IPCA LAB | H185: DFE PHARMA | I185: =I184 -> Jan | J185: =IF(F185="USD", E185, E185 * IFERROR(VLOOKUP(F185, EXCHANGE_RATE!A:B, 2, FALSE), "Currency not found")) -> 16.5208 | K185: =ROUNDUP(J185,2) -> 16.53 | L185: =IF(C185="MTS", B185, B185 * IFERROR(VLOOKUP(C185, 'QTY_CONVERSIONS '!A:B, 2, FALSE), "Units not found")) -> 4.725 | M185: =B185*K185 -> 78104.25 | N185: =IFERROR(VLOOKUP(D185, Product_Category!A:B, 2, FALSE), "Uncategorized") -> CROSCARMELLOSE SODIUM | O185: =K185 -> 16.53 | P185: =L185*O185 -> 78.10425 | Q185: =Q184 -> 2023 | R185: =IFERROR(VLOOKUP(G185,'Importer Name'!A:B, 2, FALSE), "") -> IPCA LAB | S185: =IFERROR(VLOOKUP(H185,'Supplier name '!A:B, 2, FALSE), "") -> DFE PHARMA
A186: NETHERLANDS | B186: 8820 | C186: KGS | D186: PRIMELLOSE CCS USP-NF.PH.EUR.JP | E186: 14.2 | F186: EUR | G186: IMCD INDIA | H186: DFE PHARMA | I186: =I185 -> Jan | J186: =IF(F186="USD", E186, E186 * IFERROR(VLOOKUP(F186, EXCHANGE_RATE!A:B, 2, FALSE), "Currency not found")) -> 15.194 | K186: =ROUNDUP(J186,2) -> 15.2 | L186: =IF(C186="MTS", B186, B186 * IFERROR(VLOOKUP(C186, 'QTY_CONVERSIONS '!A:B, 2, FALSE), "Units not found")) -> 8.82 | M186: =B186*K186 -> 134064 | N186: =IFERROR(VLOOKUP(D186, Product_Category!A:B, 2, FALSE), "Uncategorized") -> CROSCARMELLOSE SODIUM | O186: =K186 -> 15.2 | P186: =L186*O186 -> 134.064 | Q186: =Q185 -> 2023 | R186: =IFERROR(VLOOKUP(G186,'Importer Name'!A:B, 2, FALSE), "") -> IMCD INDIA | S186: =IFERROR(VLOOKUP(H186,'Supplier name '!A:B, 2, FALSE), "") -> DFE PHARMA
A187: NETHERLANDS | B187: 4760 | C187: KGS | D187: PRIMELLOSE CCS USP-NF.PH.EUR.JP | E187: 14.2 | F187: EUR | G187: IMCD INDIA | H187: DFE PHARMA | I187: =I186 -> Jan | J187: =IF(F187="USD", E187, E187 * IFERROR(VLOOKUP(F187, EXCHANGE_RATE!A:B, 2, FALSE), "Currency not found")) -> 15.194 | K187: =ROUNDUP(J187,2) -> 15.2 | L187: =IF(C187="MTS", B187, B187 * IFERROR(VLOOKUP(C187, 'QTY_CONVERSIONS '!A:B, 2, FALSE), "Units not found")) -> 4.76 | M187: =B187*K187 -> 72352 | N187: =IFERROR(VLOOKUP(D187, Product_Category!A:B, 2, FALSE), "Uncategorized") -> CROSCARMELLOSE SODIUM | O187: =K187 -> 15.2 | P187: =L187*O187 -> 72.352 | Q187: =Q186 -> 2023 | R187: =IFERROR(VLOOKUP(G187,'Importer Name'!A:B, 2, FALSE), "") -> IMCD INDIA | S187: =IFERROR(VLOOKUP(H187,'Supplier name '!A:B, 2, FALSE), "") -> DFE PHARMA
A188: NETHERLANDS | B188: 2030 | C188: KGS | D188: PRIMELLOSE CCS USP-NF.PH.EUR.JP | E188: 12.04 | F188: EUR | G188: IMCD INDIA | H188: DFE PHARMA | I188: =I187 -> Jan | J188: =IF(F188="USD", E188, E188 * IFERROR(VLOOKUP(F188, EXCHANGE_RATE!A:B, 2, FALSE), "Currency not found")) -> 12.8828 | K188: =ROUNDUP(J188,2) -> 12.89 | L188: =IF(C188="MTS", B188, B188 * IFERROR(VLOOKUP(C188, 'QTY_CONVERSIONS '!A:B, 2, FALSE), "Units not found")) -> 2.03 | M188: =B188*K188 -> 26166.7 | N188: =IFERROR(VLOOKUP(D188, Product_Category!A:B, 2, FALSE), "Uncategorized") -> CROSCARMELLOSE SODIUM | O188: =K188 -> 12.89 | P188: =L188*O188 -> 26.1667 | Q188: =Q187 -> 2023 | R188: =IFERROR(VLOOKUP(G188,'Importer Name'!A:B, 2, FALSE), "") -> IMCD INDIA | S188: =IFERROR(VLOOKUP(H188,'Supplier name '!A:B, 2, FALSE), "") -> DFE PHARMA
A189: NETHERLANDS | B189: 1000 | C189: KGS | D189: CCS AC-DI-SOL (R) SD-711 -NF, PH.EUR.,JP | E189: 14.93 | F189: USD | G189: AUROBINDO PHARMA | H189: DUPONT NUTRITION | I189: =I188 -> Jan | J189: =IF(F189="USD", E189, E189 * IFERROR(VLOOKUP(F189, EXCHANGE_RATE!A:B, 2, FALSE), "Currency not found")) -> 14.93 | K189: =ROUNDUP(J189,2) -> 14.93 | L189: =IF(C189="MTS", B189, B189 * IFERROR(VLOOKUP(C189, 'QTY_CONVERSIONS '!A:B, 2, FALSE), "Units not found")) -> 1 | M189: =B189*K189 -> 14930 | N189: =IFERROR(VLOOKUP(D189, Product_Category!A:B, 2, FALSE), "Uncategorized") -> CROSCARMELLOSE SODIUM | O189: =K189 -> 14.93 | P189: =L189*O189 -> 14.93 | Q189: =Q188 -> 2023 | R189: =IFERROR(VLOOKUP(G189,'Importer Name'!A:B, 2, FALSE), "") -> AUROBINDO PHARMA | S189: =IFERROR(VLOOKUP(H189,'Supplier name '!A:B, 2, FALSE), "") -> DUPONT NUTRITION
A190: NETHERLANDS | B190: 1000 | C190: KGS | D190: CCS AC-DI-SOL (R) SD-711 -NF, PH.EUR.,JP | E190: 14.93 | F190: USD | G190: AUROBINDO PHARMA | H190: DUPONT NUTRITION | I190: =I189 -> Jan | J190: =IF(F190="USD", E190, E190 * IFERROR(VLOOKUP(F190, EXCHANGE_RATE!A:B, 2, FALSE), "Currency not found")) -> 14.93 | K190: =ROUNDUP(J190,2) -> 14.93 | L190: =IF(C190="MTS", B190, B190 * IFERROR(VLOOKUP(C190, 'QTY_CONVERSIONS '!A:B, 2, FALSE), "Units not found")) -> 1 | M190: =B190*K190 -> 14930 | N190: =IFERROR(VLOOKUP(D190, Product_Category!A:B, 2, FALSE), "Uncategorized") -> CROSCARMELLOSE SODIUM | O190: =K190 -> 14.93 | P190: =L190*O190 -> 14.93 | Q190: =Q189 -> 2023 | R190: =IFERROR(VLOOKUP(G190,'Importer Name'!A:B, 2, FALSE), "") -> AUROBINDO PHARMA | S190: =IFERROR(VLOOKUP(H190,'Supplier name '!A:B, 2, FALSE), "") -> DUPONT NUTRITION
A191: NETHERLANDS | B191: 1000 | C191: KGS | D191: CCS AC-DI-SOL (R) SD-711 -NF, PH.EUR.,JP | E191: 14.93 | F191: USD | G191: AUROBINDO PHARMA | H191: DUPONT NUTRITION | I191: =I190 -> Jan | J191: =IF(F191="USD", E191, E191 * IFERROR(VLOOKUP(F191, EXCHANGE_RATE!A:B, 2, FALSE), "Currency not found")) -> 14.93 | K191: =ROUNDUP(J191,2) -> 14.93 | L191: =IF(C191="MTS", B191, B191 * IFERROR(VLOOKUP(C191, 'QTY_CONVERSIONS '!A:B, 2, FALSE), "Units not found")) -> 1 | M191: =B191*K191 -> 14930 | N191: =IFERROR(VLOOKUP(D191, Product_Category!A:B, 2, FALSE), "Uncategorized") -> CROSCARMELLOSE SODIUM | O191: =K191 -> 14.93 | P191: =L191*O191 -> 14.93 | Q191: =Q190 -> 2023 | R191: =IFERROR(VLOOKUP(G191,'Importer Name'!A:B, 2, FALSE), "") -> AUROBINDO PHARMA | S191: =IFERROR(VLOOKUP(H191,'Supplier name '!A:B, 2, FALSE), "") -> DUPONT NUTRITION
... A226: US | B226: 160 | C226: KGS | D226: MG STEARATE NF/EP/JP/KP | E226: 20.049 | F226: USD | G226: MYLAN LAB | H226: MALLINCKRODT | I226: =I225 -> Jan | J226: =IF(F226="USD", E226, E226 * IFERROR(VLOOKUP(F226, EXCHANGE_RATE!A:B, 2, FALSE), "Currency not found")) -> 20.049 | K226: =ROUNDUP(J226,2) -> 20.05 | L226: =IF(C226="MTS", B226, B226 * IFERROR(VLOOKUP(C226, 'QTY_CONVERSIONS '!A:B, 2, FALSE), "Units not found")) -> 0.16 | M226: =B226*K226 -> 3208 | N226: =IFERROR(VLOOKUP(D226, Product_Category!A:B, 2, FALSE), "Uncategorized") -> MAGNESIUM STEARATE | O226: =K226 -> 20.05 | P226: =L226*O226 -> 3.208 | Q226: =Q225 -> 2023 | R226: =IFERROR(VLOOKUP(G226,'Importer Name'!A:B, 2, FALSE), "") -> MYLAN LAB | S226: =IFERROR(VLOOKUP(H226,'Supplier name '!A:B, 2, FALSE), "") -> MALLINCKRODT
A227: US | B227: 10 | C227: KGS | D227: AQUALON SODIUM CMC | E227: 155 | F227: USD | G227: DKSH INDIA | H227: ASHLAND SPECIAL | I227: =I226 -> Jan | J227: =IF(F227="USD", E227, E227 * IFERROR(VLOOKUP(F227, EXCHANGE_RATE!A:B, 2, FALSE), "Currency not found")) -> 155 | K227: =ROUNDUP(J227,2) -> 155 | L227: =IF(C227="MTS", B227, B227 * IFERROR(VLOOKUP(C227, 'QTY_CONVERSIONS '!A:B, 2, FALSE), "Units not found")) -> 0.01 | M227: =B227*K227 -> 1550 | N227: =IFERROR(VLOOKUP(D227, Product_Category!A:B, 2, FALSE), "Uncategorized") -> CMC | O227: =K227*1000 -> 155000 | P227: =L227*O227 -> 1550 | Q227: =Q226 -> 2023 | R227: =IFERROR(VLOOKUP(G227,'Importer Name'!A:B, 2, FALSE), "") -> DKSH INDIA | S227: =IFERROR(VLOOKUP(H227,'Supplier name '!A:B, 2, FALSE), "") -> ASHLAND SPECIAL
A228: US | B228: 20 | C228: KGS | D228: AQUALON SODIUM CMC | E228: 155 | F228: USD | G228: DKSH INDIA | H228: ASHLAND SPECIAL | I228: =I227 -> Jan | J228: =IF(F228="USD", E228, E228 * IFERROR(VLOOKUP(F228, EXCHANGE_RATE!A:B, 2, FALSE), "Currency not found")) -> 155 | K228: =ROUNDUP(J228,2) -> 155 | L228: =IF(C228="MTS", B228, B228 * IFERROR(VLOOKUP(C228, 'QTY_CONVERSIONS '!A:B, 2, FALSE), "Units not found")) -> 0.02 | M228: =B228*K228 -> 3100 | N228: =IFERROR(VLOOKUP(D228, Product_Category!A:B, 2, FALSE), "Uncategorized") -> CMC | O228: =K228*1000 -> 155000 | P228: =L228*O228 -> 3100 | Q228: =Q227 -> 2023 | R228: =IFERROR(VLOOKUP(G228,'Importer Name'!A:B, 2, FALSE), "") -> DKSH INDIA | S228: =IFERROR(VLOOKUP(H228,'Supplier name '!A:B, 2, FALSE), "") -> ASHLAND SPECIAL
A229: US | B229: 22.68 | C229: KGS | D229: AQUALON CMC | E229: 25.3999 | F229: USD | G229: MYLAN LAB | H229: ASHLAND SPECIAL | I229: =I228 -> Jan | J229: =IF(F229="USD", E229, E229 * IFERROR(VLOOKUP(F229, EXCHANGE_RATE!A:B, 2, FALSE), "Currency not found")) -> 25.3999 | K229: =ROUNDUP(J229,2) -> 25.4 | L229: =IF(C229="MTS", B229, B229 * IFERROR(VLOOKUP(C229, 'QTY_CONVERSIONS '!A:B, 2, FALSE), "Units not found")) -> 0.02268 | M229: =B229*K229 -> 576.072 | N229: =IFERROR(VLOOKUP(D229, Product_Category!A:B, 2, FALSE), "Uncategorized") -> CMC | O229: =K229 -> 25.4 | P229: =L229*O229 -> 0.576072 | Q229: =Q228 -> 2023 | R229: =IFERROR(VLOOKUP(G229,'Importer Name'!A:B, 2, FALSE), "") -> MYLAN LAB | S229: =IFERROR(VLOOKUP(H229,'Supplier name '!A:B, 2, FALSE), "") -> ASHLAND SPECIAL
A230: US | B230: 22.68 | C230: KGS | D230: AQUALON CMC | E230: 23.35 | F230: USD | G230: MYLAN LAB | H230: ASHLAND SPECIAL | I230: =I229 -> Jan | J230: =IF(F230="USD", E230, E230 * IFERROR(VLOOKUP(F230, EXCHANGE_RATE!A:B, 2, FALSE), "Currency not found")) -> 23.35 | K230: =ROUNDUP(J230,2) -> 23.35 | L230: =IF(C230="MTS", B230, B230 * IFERROR(VLOOKUP(C230, 'QTY_CONVERSIONS '!A:B, 2, FALSE), "Units not found")) -> 0.02268 | M230: =B230*K230 -> 529.578 | N230: =IFERROR(VLOOKUP(D230, Product_Category!A:B, 2, FALSE), "Uncategorized") -> CMC | O230: =K230 -> 23.35 | P230: =L230*O230 -> 0.529578 | Q230: =Q229 -> 2023 | R230: =IFERROR(VLOOKUP(G230,'Importer Name'!A:B, 2, FALSE), "") -> MYLAN LAB | S230: =IFERROR(VLOOKUP(H230,'Supplier name '!A:B, 2, FALSE), "") -> ASHLAND SPECIAL
A231: US | B231: 1 | C231: KGS | D231: AQUALON SODIUM CMC | E231: 4.96 | F231: USD | G231: INT SPECIALTY | H231: CHEMICAL MARKETING | I231: =I230 -> Jan | J231: =IF(F231="USD", E231, E231 * IFERROR(VLOOKUP(F231, EXCHANGE_RATE!A:B, 2, FALSE), "Currency not found")) -> 4.96 | K231: =ROUNDUP(J231,2) -> 4.96 | L231: =IF(C231="MTS", B231, B231 * IFERROR(VLOOKUP(C231, 'QTY_CONVERSIONS '!A:B, 2, FALSE), "Units not found")) -> 0.001 | M231: =B231*K231 -> 4.96 | N231: =IFERROR(VLOOKUP(D231, Product_Category!A:B, 2, FALSE), "Uncategorized") -> CMC | O231: =K231 -> 4.96 | P231: =L231*O231 -> 0.00496 | Q231: =Q230 -> 2023 | R231: =IFERROR(VLOOKUP(G231,'Importer Name'!A:B, 2, FALSE), "") -> INT SPECIALTY | S231: =IFERROR(VLOOKUP(H231,'Supplier name '!A:B, 2, FALSE), "") -> CHEMICAL MARKETING
A232: US | B232: 1200 | C232: KGS | D232: MCC VIVAPUR 101 | E232: 3.281 | F232: USD | G232: PAR FORMULATIONS | H232: JRS PHARMA | I232: =I231 -> Jan | J232: =IF(F232="USD", E232, E232 * IFERROR(VLOOKUP(F232, EXCHANGE_RATE!A:B, 2, FALSE), "Currency not found")) -> 3.281 | K232: =ROUNDUP(J232,2) -> 3.29 | L232: =IF(C232="MTS", B232, B232 * IFERROR(VLOOKUP(C232, 'QTY_CONVERSIONS '!A:B, 2, FALSE), "Units not found")) -> 1.2 | M232: =B232*K232 -> 3948 | N232: =IFERROR(VLOOKUP(D232, Product_Category!A:B, 2, FALSE), "Uncategorized") -> MCC | O232: =K232 -> 3.29 | P232: =L232*O232 -> 3.948 | Q232: =Q231 -> 2023 | R232: =IFERROR(VLOOKUP(G232,'Importer Name'!A:B, 2, FALSE), "") -> PAR FORMULATIONS | S232: =IFERROR(VLOOKUP(H232,'Supplier name '!A:B, 2, FALSE), "") -> JRS PHARMA
A233: US | B233: 2800 | C233: KGS | D233: MCC VIVAPUR 102 | E233: 3.281 | F233: USD | G233: PAR FORMULATIONS | H233: JRS PHARMA | I233: =I232 -> Jan | J233: =IF(F233="USD", E233, E233 * IFERROR(VLOOKUP(F233, EXCHANGE_RATE!A:B, 2, FALSE), "Currency not found")) -> 3.281 | K233: =ROUNDUP(J233,2) -> 3.29 | L233: =IF(C233="MTS", B233, B233 * IFERROR(VLOOKUP(C233, 'QTY_CONVERSIONS '!A:B, 2, FALSE), "Units not found")) -> 2.8 | M233: =B233*K233 -> 9212 | N233: =IFERROR(VLOOKUP(D233, Product_Category!A:B, 2, FALSE), "Uncategorized") -> MCC | O233: =K233 -> 3.29 | P233: =L233*O233 -> 9.212 | Q233: =Q232 -> 2023 | R233: =IFERROR(VLOOKUP(G233,'Importer Name'!A:B, 2, FALSE), "") -> PAR FORMULATIONS | S233: =IFERROR(VLOOKUP(H233,'Supplier name '!A:B, 2, FALSE), "") -> JRS PHARMA
A234: US | B234: 14800 | C234: KGS | D234: MCC VIVAPUR 101 | E234: 3.281 | F234: USD | G234: RETTENMAIER INDIA | H234: JRS PHARMA | I234: =I233 -> Jan | J234: =IF(F234="USD", E234, E234 * IFERROR(VLOOKUP(F234, EXCHANGE_RATE!A:B, 2, FALSE), "Currency not found")) -> 3.281 | K234: =ROUNDUP(J234,2) -> 3.29 | L234: =IF(C234="MTS", B234, B234 * IFERROR(VLOOKUP(C234, 'QTY_CONVERSIONS '!A:B, 2, FALSE), "Units not found")) -> 14.8 | M234: =B234*K234 -> 48692 | N234: =IFERROR(VLOOKUP(D234, Product_Category!A:B, 2, FALSE), "Uncategorized") -> MCC | O234: =K234 -> 3.29 | P234: =L234*O234 -> 48.692 | Q234: =Q233 -> 2023 | R234: =IFERROR(VLOOKUP(G234,'Importer Name'!A:B, 2, FALSE), "") -> RETTENMAIER INDIA | S234: =IFERROR(VLOOKUP(H234,'Supplier name '!A:B, 2, FALSE), "") -> JRS PHARMA
A235: Brazil | B235: 5 | C235: KGS | D235: MCC MICROCEL MC-101 | E235: 1 | F235: USD | G235: AZELIS INDIA | H235: ITACEL FARMO | I235: Feb | J235: =IF(F235="USD", E235, E235 * IFERROR(VLOOKUP(F235, EXCHANGE_RATE!A:B, 2, FALSE), "Currency not found")) -> 1 | K235: =ROUNDUP(J235,2) -> 1 | L235: =IF(C235="MTS", B235, B235 * IFERROR(VLOOKUP(C235, 'QTY_CONVERSIONS '!A:B, 2, FALSE), "Units not found")) -> 0.005 | M235: =B235*K235 -> 5 | N235: =IFERROR(VLOOKUP(D235, Product_Category!A:B, 2, FALSE), "Uncategorized") -> MCC | O235: =K235 -> 1 | P235: =L235*O235 -> 0.005 | Q235: =Q234 -> 2023 | R235: =IFERROR(VLOOKUP(G235,'Importer Name'!A:B, 2, FALSE), "") -> AZELIS INDIA | S235: =IFERROR(VLOOKUP(H235,'Supplier name '!A:B, 2, FALSE), "") -> ITACEL FARMO
A236: Brazil | B236: 5 | C236: KGS | D236: MCC MICROCEL MC-101 | E236: 1 | F236: USD | G236: AZELIS INDIA | H236: ITACEL FARMO | I236: =I235 -> Feb | J236: =IF(F236="USD", E236, E236 * IFERROR(VLOOKUP(F236, EXCHANGE_RATE!A:B, 2, FALSE), "Currency not found")) -> 1 | K236: =ROUNDUP(J236,2) -> 1 | L236: =IF(C236="MTS", B236, B236 * IFERROR(VLOOKUP(C236, 'QTY_CONVERSIONS '!A:B, 2, FALSE), "Units not found")) -> 0.005 | M236: =B236*K236 -> 5 | N236: =IFERROR(VLOOKUP(D236, Product_Category!A:B, 2, FALSE), "Uncategorized") -> MCC | O236: =K236 -> 1 | P236: =L236*O236 -> 0.005 | Q236: =Q235 -> 2023 | R236: =IFERROR(VLOOKUP(G236,'Importer Name'!A:B, 2, FALSE), "") -> AZELIS INDIA | S236: =IFERROR(VLOOKUP(H236,'Supplier name '!A:B, 2, FALSE), "") -> ITACEL FARMO
A237: Brazil | B237: 5 | C237: KGS | D237: MCC MICROCEL MC-101 | E237: 1 | F237: USD | G237: AZELIS INDIA | H237: ITACEL FARMO | I237: =I236 -> Feb | J237: =IF(F237="USD", E237, E237 * IFERROR(VLOOKUP(F237, EXCHANGE_RATE!A:B, 2, FALSE), "Currency not found")) -> 1 | K237: =ROUNDUP(J237,2) -> 1 | L237: =IF(C237="MTS", B237, B237 * IFERROR(VLOOKUP(C237, 'QTY_CONVERSIONS '!A:B, 2, FALSE), "Units not found")) -> 0.005 | M237: =B237*K237 -> 5 | N237: =IFERROR(VLOOKUP(D237, Product_Category!A:B, 2, FALSE), "Uncategorized") -> MCC | O237: =K237 -> 1 | P237: =L237*O237 -> 0.005 | Q237: =Q236 -> 2023 | R237: =IFERROR(VLOOKUP(G237,'Importer Name'!A:B, 2, FALSE), "") -> AZELIS INDIA | S237: =IFERROR(VLOOKUP(H237,'Supplier name '!A:B, 2, FALSE), "") -> ITACEL FARMO
A238: Brazil | B238: 5 | C238: KGS | D238: MCC MICROCEL MC-102 | E238: 1 | F238: USD | G238: AZELIS INDIA | H238: ITACEL FARMO | I238: =I237 -> Feb | J238: =IF(F238="USD", E238, E238 * IFERROR(VLOOKUP(F238, EXCHANGE_RATE!A:B, 2, FALSE), "Currency not found")) -> 1 | K238: =ROUNDUP(J238,2) -> 1 | L238: =IF(C238="MTS", B238, B238 * IFERROR(VLOOKUP(C238, 'QTY_CONVERSIONS '!A:B, 2, FALSE), "Units not found")) -> 0.005 | M238: =B238*K238 -> 5 | N238: =IFERROR(VLOOKUP(D238, Product_Category!A:B, 2, FALSE), "Uncategorized") -> MCC | O238: =K238 -> 1 | P238: =L238*O238 -> 0.005 | Q238: =Q237 -> 2023 | R238: =IFERROR(VLOOKUP(G238,'Importer Name'!A:B, 2, FALSE), "") -> AZELIS INDIA | S238: =IFERROR(VLOOKUP(H238,'Supplier name '!A:B, 2, FALSE), "") -> ITACEL FARMO
A239: Brazil | B239: 5 | C239: KGS | D239: MCC MICROCEL MC-102 | E239: 1 | F239: USD | G239: AZELIS INDIA | H239: ITACEL FARMO | I239: =I238 -> Feb | J239: =IF(F239="USD", E239, E239 * IFERROR(VLOOKUP(F239, EXCHANGE_RATE!A:B, 2, FALSE), "Currency not found")) -> 1 | K239: =ROUNDUP(J239,2) -> 1 | L239: =IF(C239="MTS", B239, B239 * IFERROR(VLOOKUP(C239, 'QTY_CONVERSIONS '!A:B, 2, FALSE), "Units not found")) -> 0.005 | M239: =B239*K239 -> 5 | N239: =IFERROR(VLOOKUP(D239, Product_Category!A:B, 2, FALSE), "Uncategorized") -> MCC | O239: =K239 -> 1 | P239: =L239*O239 -> 0.005 | Q239: =Q238 -> 2023 | R239: =IFERROR(VLOOKUP(G239,'Importer Name'!A:B, 2, FALSE), "") -> AZELIS INDIA | S239: =IFERROR(VLOOKUP(H239,'Supplier name '!A:B, 2, FALSE), "") -> ITACEL FARMO
A240: Brazil | B240: 5 | C240: KGS | D240: MCC MICROCEL MC-102 | E240: 1 | F240: USD | G240: AZELIS INDIA | H240: ITACEL FARMO | I240: =I239 -> Feb | J240: =IF(F240="USD", E240, E240 * IFERROR(VLOOKUP(F240, EXCHANGE_RATE!A:B, 2, FALSE), "Currency not found")) -> 1 | K240: =ROUNDUP(J240,2) -> 1 | L240: =IF(C240="MTS", B240, B240 * IFERROR(VLOOKUP(C240, 'QTY_CONVERSIONS '!A:B, 2, FALSE), "Units not found")) -> 0.005 | M240: =B240*K240 -> 5 | N240: =IFERROR(VLOOKUP(D240, Product_Category!A:B, 2, FALSE), "Uncategorized") -> MCC | O240: =K240 -> 1 | P240: =L240*O240 -> 0.005 | Q240: =Q239 -> 2023 | R240: =IFERROR(VLOOKUP(G240,'Importer Name'!A:B, 2, FALSE), "") -> AZELIS INDIA | S240: =IFERROR(VLOOKUP(H240,'Supplier name '!A:B, 2, FALSE), "") -> ITACEL FARMO
A241: Brazil | B241: 5 | C241: KGS | D241: MCC MICROCEL MC-112 | E241: 1 | F241: USD | G241: AZELIS INDIA | H241: ITACEL FARMO | I241: =I240 -> Feb | J241: =IF(F241="USD", E241, E241 * IFERROR(VLOOKUP(F241, EXCHANGE_RATE!A:B, 2, FALSE), "Currency not found")) -> 1 | K241: =ROUNDUP(J241,2) -> 1 | L241: =IF(C241="MTS", B241, B241 * IFERROR(VLOOKUP(C241, 'QTY_CONVERSIONS '!A:B, 2, FALSE), "Units not found")) -> 0.005 | M241: =B241*K241 -> 5 | N241: =IFERROR(VLOOKUP(D241, Product_Category!A:B, 2, FALSE), "Uncategorized") -> MCC | O241: =K241 -> 1 | P241: =L241*O241 -> 0.005 | Q241: =Q240 -> 2023 | R241: =IFERROR(VLOOKUP(G241,'Importer Name'!A:B, 2, FALSE), "") -> AZELIS INDIA | S241: =IFERROR(VLOOKUP(H241,'Supplier name '!A:B, 2, FALSE), "") -> ITACEL FARMO
A242: Brazil | B242: 5 | C242: KGS | D242: MCC MICROCEL MC-112 | E242: 1 | F242: USD | G242: AZELIS INDIA | H242: ITACEL FARMO | I242: =I241 -> Feb | J242: =IF(F242="USD", E242, E242 * IFERROR(VLOOKUP(F242, EXCHANGE_RATE!A:B, 2, FALSE), "Currency not found")) -> 1 | K242: =ROUNDUP(J242,2) -> 1 | L242: =IF(C242="MTS", B242, B242 * IFERROR(VLOOKUP(C242, 'QTY_CONVERSIONS '!A:B, 2, FALSE), "Units not found")) -> 0.005 | M242: =B242*K242 -> 5 | N242: =IFERROR(VLOOKUP(D242, Product_Category!A:B, 2, FALSE), "Uncategorized") -> MCC | O242: =K242 -> 1 | P242: =L242*O242 -> 0.005 | Q242: =Q241 -> 2023 | R242: =IFERROR(VLOOKUP(G242,'Importer Name'!A:B, 2, FALSE), "") -> AZELIS INDIA | S242: =IFERROR(VLOOKUP(H242,'Supplier name '!A:B, 2, FALSE), "") -> ITACEL FARMO
A243: Brazil | B243: 5 | C243: KGS | D243: MCC MICROCEL MC-112 | E243: 1 | F243: USD | G243: AZELIS INDIA | H243: ITACEL FARMO | I243: =I242 -> Feb | J243: =IF(F243="USD", E243, E243 * IFERROR(VLOOKUP(F243, EXCHANGE_RATE!A:B, 2, FALSE), "Currency not found")) -> 1 | K243: =ROUNDUP(J243,2) -> 1 | L243: =IF(C243="MTS", B243, B243 * IFERROR(VLOOKUP(C243, 'QTY_CONVERSIONS '!A:B, 2, FALSE), "Units not found")) -> 0.005 | M243: =B243*K243 -> 5 | N243: =IFERROR(VLOOKUP(D243, Product_Category!A:B, 2, FALSE), "Uncategorized") -> MCC | O243: =K243 -> 1 | P243: =L243*O243 -> 0.005 | Q243: =Q242 -> 2023 | R243: =IFERROR(VLOOKUP(G243,'Importer Name'!A:B, 2, FALSE), "") -> AZELIS INDIA | S243: =IFERROR(VLOOKUP(H243,'Supplier name '!A:B, 2, FALSE), "") -> ITACEL FARMO
A244: Brazil | B244: 5 | C244: KGS | D244: MCC MICROCEL MC-112 | E244: 1 | F244: USD | G244: AZELIS INDIA | H244: ITACEL FARMO | I244: =I243 -> Feb | J244: =IF(F244="USD", E244, E244 * IFERROR(VLOOKUP(F244, EXCHANGE_RATE!A:B, 2, FALSE), "Currency not found")) -> 1 | K244: =ROUNDUP(J244,2) -> 1 | L244: =IF(C244="MTS", B244, B244 * IFERROR(VLOOKUP(C244, 'QTY_CONVERSIONS '!A:B, 2, FALSE), "Units not found")) -> 0.005 | M244: =B244*K244 -> 5 | N244: =IFERROR(VLOOKUP(D244, Product_Category!A:B, 2, FALSE), "Uncategorized") -> MCC | O244: =K244 -> 1 | P244: =L244*O244 -> 0.005 | Q244: =Q243 -> 2023 | R244: =IFERROR(VLOOKUP(G244,'Importer Name'!A:B, 2, FALSE), "") -> AZELIS INDIA | S244: =IFERROR(VLOOKUP(H244,'Supplier name '!A:B, 2, FALSE), "") -> ITACEL FARMO
A245: Brazil | B245: 5 | C245: KGS | D245: MCC MICROCEL MC-12 | E245: 1 | F245: USD | G245: AZELIS INDIA | H245: ITACEL FARMO | I245: =I244 -> Feb | J245: =IF(F245="USD", E245, E245 * IFERROR(VLOOKUP(F245, EXCHANGE_RATE!A:B, 2, FALSE), "Currency not found")) -> 1 | K245: =ROUNDUP(J245,2) -> 1 | L245: =IF(C245="MTS", B245, B245 * IFERROR(VLOOKUP(C245, 'QTY_CONVERSIONS '!A:B, 2, FALSE), "Units not found")) -> 0.005 | M245: =B245*K245 -> 5 | N245: =IFERROR(VLOOKUP(D245, Product_Category!A:B, 2, FALSE), "Uncategorized") -> MCC | O245: =K245 -> 1 | P245: =L245*O245 -> 0.005 | Q245: =Q244 -> 2023 | R245: =IFERROR(VLOOKUP(G245,'Importer Name'!A:B, 2, FALSE), "") -> AZELIS INDIA | S245: =IFERROR(VLOOKUP(H245,'Supplier name '!A:B, 2, FALSE), "") -> ITACEL FARMO
A246: Brazil | B246: 5 | C246: KGS | D246: MCC MICROCEL MC-200 | E246: 1 | F246: USD | G246: AZELIS INDIA | H246: ITACEL FARMO | I246: =I245 -> Feb | J246: =IF(F246="USD", E246, E246 * IFERROR(VLOOKUP(F246, EXCHANGE_RATE!A:B, 2, FALSE), "Currency not found")) -> 1 | K246: =ROUNDUP(J246,2) -> 1 | L246: =IF(C246="MTS", B246, B246 * IFERROR(VLOOKUP(C246, 'QTY_CONVERSIONS '!A:B, 2, FALSE), "Units not found")) -> 0.005 | M246: =B246*K246 -> 5 | N246: =IFERROR(VLOOKUP(D246, Product_Category!A:B, 2, FALSE), "Uncategorized") -> MCC | O246: =K246 -> 1 | P246: =L246*O246 -> 0.005 | Q246: =Q245 -> 2023 | R246: =IFERROR(VLOOKUP(G246,'Importer Name'!A:B, 2, FALSE), "") -> AZELIS INDIA | S246: =IFERROR(VLOOKUP(H246,'Supplier name '!A:B, 2, FALSE), "") -> ITACEL FARMO
A247: Brazil | B247: 5 | C247: KGS | D247: MCC MICROCEL MC-200 | E247: 1 | F247: USD | G247: AZELIS INDIA | H247: ITACEL FARMO | I247: =I246 -> Feb | J247: =IF(F247="USD", E247, E247 * IFERROR(VLOOKUP(F247, EXCHANGE_RATE!A:B, 2, FALSE), "Currency not found")) -> 1 | K247: =ROUNDUP(J247,2) -> 1 | L247: =IF(C247="MTS", B247, B247 * IFERROR(VLOOKUP(C247, 'QTY_CONVERSIONS '!A:B, 2, FALSE), "Units not found")) -> 0.005 | M247: =B247*K247 -> 5 | N247: =IFERROR(VLOOKUP(D247, Product_Category!A:B, 2, FALSE), "Uncategorized") -> MCC | O247: =K247 -> 1 | P247: =L247*O247 -> 0.005 | Q247: =Q246 -> 2023 | R247: =IFERROR(VLOOKUP(G247,'Importer Name'!A:B, 2, FALSE), "") -> AZELIS INDIA | S247: =IFERROR(VLOOKUP(H247,'Supplier name '!A:B, 2, FALSE), "") -> ITACEL FARMO
... A269: China | B269: 10000 | C269: KGS | D269: SODIUM CMC | E269: 30.6394 | F269: CNY | G269: COLGATE PALMOLIVE | H269: CHONGQING LIHONG | I269: =I268 -> Feb | J269: =IF(F269="USD", E269, E269 * IFERROR(VLOOKUP(F269, EXCHANGE_RATE!A:B, 2, FALSE), "Currency not found")) -> 4.289516 | K269: =ROUNDUP(J269,2) -> 4.29 | L269: =IF(C269="MTS", B269, B269 * IFERROR(VLOOKUP(C269, 'QTY_CONVERSIONS '!A:B, 2, FALSE), "Units not found")) -> 10 | M269: =B269*K269 -> 42900 | N269: =IFERROR(VLOOKUP(D269, Product_Category!A:B, 2, FALSE), "Uncategorized") -> CMC | O269: =K269 -> 4.29 | P269: =L269*O269 -> 42.9 | Q269: =Q268 -> 2023 | R269: =IFERROR(VLOOKUP(G269,'Importer Name'!A:B, 2, FALSE), "") -> COLGATE PALMOLIVE | S269: =IFERROR(VLOOKUP(H269,'Supplier name '!A:B, 2, FALSE), "") -> CHONGQING LIHONG
A270: China | B270: 20 | C270: MTS | D270: SODIUM CMC | E270: 2849.943 | F270: USD | G270: MERIDIAN POLYMERS | H270: CHONGQING LIHONG | I270: =I269 -> Feb | J270: =IF(F270="USD", E270, E270 * IFERROR(VLOOKUP(F270, EXCHANGE_RATE!A:B, 2, FALSE), "Currency not found")) -> 2849.943 | K270: =ROUNDUP(J270,2) -> 2849.95 | L270: =IF(C270="MTS", B270, B270 * IFERROR(VLOOKUP(C270, 'QTY_CONVERSIONS '!A:B, 2, FALSE), "Units not found")) -> 20 | M270: =B270*K270 -> 56999 | N270: =IFERROR(VLOOKUP(D270, Product_Category!A:B, 2, FALSE), "Uncategorized") -> CMC | O270: =K270*1000 -> 2849950 | P270: =L270*O270 -> 56999000 | Q270: =Q269 -> 2023 | R270: =IFERROR(VLOOKUP(G270,'Importer Name'!A:B, 2, FALSE), "") -> MERIDIAN POLYMERS | S270: =IFERROR(VLOOKUP(H270,'Supplier name '!A:B, 2, FALSE), "") -> CHONGQING LIHONG
A271: China | B271: 20 | C271: MTS | D271: SODIUM CMC | E271: 2849.943 | F271: USD | G271: MERIDIAN POLYMERS | H271: CHONGQING LIHONG | I271: =I270 -> Feb | J271: =IF(F271="USD", E271, E271 * IFERROR(VLOOKUP(F271, EXCHANGE_RATE!A:B, 2, FALSE), "Currency not found")) -> 2849.943 | K271: =ROUNDUP(J271,2) -> 2849.95 | L271: =IF(C271="MTS", B271, B271 * IFERROR(VLOOKUP(C271, 'QTY_CONVERSIONS '!A:B, 2, FALSE), "Units not found")) -> 20 | M271: =B271*K271 -> 56999 | N271: =IFERROR(VLOOKUP(D271, Product_Category!A:B, 2, FALSE), "Uncategorized") -> CMC | O271: =K271*1000 -> 2849950 | P271: =L271*O271 -> 56999000 | Q271: =Q270 -> 2023 | R271: =IFERROR(VLOOKUP(G271,'Importer Name'!A:B, 2, FALSE), "") -> MERIDIAN POLYMERS | S271: =IFERROR(VLOOKUP(H271,'Supplier name '!A:B, 2, FALSE), "") -> CHONGQING LIHONG
A272: China | B272: 15000 | C272: KGS | D272: SODIUM CMC | E272: 3.8849 | F272: USD | G272: GUJCHEM SURFA | H272: JINING FORTUNE | I272: =I271 -> Feb | J272: =IF(F272="USD", E272, E272 * IFERROR(VLOOKUP(F272, EXCHANGE_RATE!A:B, 2, FALSE), "Currency not found")) -> 3.8849 | K272: =ROUNDUP(J272,2) -> 3.89 | L272: =IF(C272="MTS", B272, B272 * IFERROR(VLOOKUP(C272, 'QTY_CONVERSIONS '!A:B, 2, FALSE), "Units not found")) -> 15 | M272: =B272*K272 -> 58350 | N272: =IFERROR(VLOOKUP(D272, Product_Category!A:B, 2, FALSE), "Uncategorized") -> CMC | O272: =K272 -> 3.89 | P272: =L272*O272 -> 58.35 | Q272: =Q271 -> 2023 | R272: =IFERROR(VLOOKUP(G272,'Importer Name'!A:B, 2, FALSE), "") -> GUJCHEM SURFA | S272: =IFERROR(VLOOKUP(H272,'Supplier name '!A:B, 2, FALSE), "") -> JINING FORTUNE
A273: China | B273: 21000 | C273: KGS | D273: SODIUM CMC | E273: 2.5 | F273: USD | G273: HI TECH PAPERS | H273: M S HANSSTAR | I273: =I272 -> Feb | J273: =IF(F273="USD", E273, E273 * IFERROR(VLOOKUP(F273, EXCHANGE_RATE!A:B, 2, FALSE), "Currency not found")) -> 2.5 | K273: =ROUNDUP(J273,2) -> 2.5 | L273: =IF(C273="MTS", B273, B273 * IFERROR(VLOOKUP(C273, 'QTY_CONVERSIONS '!A:B, 2, FALSE), "Units not found")) -> 21 | M273: =B273*K273 -> 52500 | N273: =IFERROR(VLOOKUP(D273, Product_Category!A:B, 2, FALSE), "Uncategorized") -> CMC | O273: =K273 -> 2.5 | P273: =L273*O273 -> 52.5 | Q273: =Q272 -> 2023 | R273: =IFERROR(VLOOKUP(G273,'Importer Name'!A:B, 2, FALSE), "") -> HI TECH PAPERS | S273: =IFERROR(VLOOKUP(H273,'Supplier name '!A:B, 2, FALSE), "") -> M S HANSSTAR
A274: China | B274: 21000 | C274: KGS | D274: SODIUM CMC | E274: 2.6999 | F274: USD | G274: HI TECH PAPERS | H274: M S HANSSTAR | I274: =I273 -> Feb | J274: =IF(F274="USD", E274, E274 * IFERROR(VLOOKUP(F274, EXCHANGE_RATE!A:B, 2, FALSE), "Currency not found")) -> 2.6999 | K274: =ROUNDUP(J274,2) -> 2.7 | L274: =IF(C274="MTS", B274, B274 * IFERROR(VLOOKUP(C274, 'QTY_CONVERSIONS '!A:B, 2, FALSE), "Units not found")) -> 21 | M274: =B274*K274 -> 56700 | N274: =IFERROR(VLOOKUP(D274, Product_Category!A:B, 2, FALSE), "Uncategorized") -> CMC | O274: =K274 -> 2.7 | P274: =L274*O274 -> 56.7 | Q274: =Q273 -> 2023 | R274: =IFERROR(VLOOKUP(G274,'Importer Name'!A:B, 2, FALSE), "") -> HI TECH PAPERS | S274: =IFERROR(VLOOKUP(H274,'Supplier name '!A:B, 2, FALSE), "") -> M S HANSSTAR
A275: China | B275: 21000 | C275: KGS | D275: SODIUM CMC | E275: 2.45 | F275: USD | G275: HI TECH PAPERS | H275: M S HANSSTAR | I275: =I274 -> Feb | J275: =IF(F275="USD", E275, E275 * IFERROR(VLOOKUP(F275, EXCHANGE_RATE!A:B, 2, FALSE), "Currency not found")) -> 2.45 | K275: =ROUNDUP(J275,2) -> 2.45 | L275: =IF(C275="MTS", B275, B275 * IFERROR(VLOOKUP(C275, 'QTY_CONVERSIONS '!A:B, 2, FALSE), "Units not found")) -> 21 | M275: =B275*K275 -> 51450 | N275: =IFERROR(VLOOKUP(D275, Product_Category!A:B, 2, FALSE), "Uncategorized") -> CMC | O275: =K275 -> 2.45 | P275: =L275*O275 -> 51.45 | Q275: =Q274 -> 2023 | R275: =IFERROR(VLOOKUP(G275,'Importer Name'!A:B, 2, FALSE), "") -> HI TECH PAPERS | S275: =IFERROR(VLOOKUP(H275,'Supplier name '!A:B, 2, FALSE), "") -> M S HANSSTAR
A276: China | B276: 21000 | C276: KGS | D276: SODIUM CMC | E276: 2.45 | F276: USD | G276: HI TECH PAPERS | H276: M S HANSSTAR | I276: =I275 -> Feb | J276: =IF(F276="USD", E276, E276 * IFERROR(VLOOKUP(F276, EXCHANGE_RATE!A:B, 2, FALSE), "Currency not found")) -> 2.45 | K276: =ROUNDUP(J276,2) -> 2.45 | L276: =IF(C276="MTS", B276, B276 * IFERROR(VLOOKUP(C276, 'QTY_CONVERSIONS '!A:B, 2, FALSE), "Units not found")) -> 21 | M276: =B276*K276 -> 51450 | N276: =IFERROR(VLOOKUP(D276, Product_Category!A:B, 2, FALSE), "Uncategorized") -> CMC | O276: =K276 -> 2.45 | P276: =L276*O276 -> 51.45 | Q276: =Q275 -> 2023 | R276: =IFERROR(VLOOKUP(G276,'Importer Name'!A:B, 2, FALSE), "") -> HI TECH PAPERS | S276: =IFERROR(VLOOKUP(H276,'Supplier name '!A:B, 2, FALSE), "") -> M S HANSSTAR
A277: China | B277: 40000 | C277: KGS | D277: MODIFIED SODIUM CMC | E277: 1.7 | F277: USD | G277: GT PAPERS | H277: SHANDONG GUAN | I277: =I276 -> Feb | J277: =IF(F277="USD", E277, E277 * IFERROR(VLOOKUP(F277, EXCHANGE_RATE!A:B, 2, FALSE), "Currency not found")) -> 1.7 | K277: =ROUNDUP(J277,2) -> 1.7 | L277: =IF(C277="MTS", B277, B277 * IFERROR(VLOOKUP(C277, 'QTY_CONVERSIONS '!A:B, 2, FALSE), "Units not found")) -> 40 | M277: =B277*K277 -> 68000 | N277: =IFERROR(VLOOKUP(D277, Product_Category!A:B, 2, FALSE), "Uncategorized") -> CMC | O277: =K277 -> 1.7 | P277: =L277*O277 -> 68 | Q277: =Q276 -> 2023 | R277: =IFERROR(VLOOKUP(G277,'Importer Name'!A:B, 2, FALSE), "") -> GT PAPERS | S277: =IFERROR(VLOOKUP(H277,'Supplier name '!A:B, 2, FALSE), "") -> SHANDONG GUAN
A278: China | B278: 1400 | C278: KGS | D278: SODIUM CMC | E278: 4.6999 | F278: USD | G278: PIOMA CHEMICALS | H278: SHANGHAI SHENGUANG | I278: =I277 -> Feb | J278: =IF(F278="USD", E278, E278 * IFERROR(VLOOKUP(F278, EXCHANGE_RATE!A:B, 2, FALSE), "Currency not found")) -> 4.6999 | K278: =ROUNDUP(J278,2) -> 4.7 | L278: =IF(C278="MTS", B278, B278 * IFERROR(VLOOKUP(C278, 'QTY_CONVERSIONS '!A:B, 2, FALSE), "Units not found")) -> 1.4 | M278: =B278*K278 -> 6580 | N278: =IFERROR(VLOOKUP(D278, Product_Category!A:B, 2, FALSE), "Uncategorized") -> CMC | O278: =K278 -> 4.7 | P278: =L278*O278 -> 6.58 | Q278: =Q277 -> 2023 | R278: =IFERROR(VLOOKUP(G278,'Importer Name'!A:B, 2, FALSE), "") -> PIOMA CHEMICALS | S278: =IFERROR(VLOOKUP(H278,'Supplier name '!A:B, 2, FALSE), "") -> SHANGHAI SHENGUANG
A279: China | B279: 5600 | C279: KGS | D279: SODIUM CMC | E279: 4.5999 | F279: USD | G279: PIOMA CHEMICALS | H279: SHANGHAI SHENGUANG | I279: =I278 -> Feb | J279: =IF(F279="USD", E279, E279 * IFERROR(VLOOKUP(F279, EXCHANGE_RATE!A:B, 2, FALSE), "Currency not found")) -> 4.5999 | K279: =ROUNDUP(J279,2) -> 4.6 | L279: =IF(C279="MTS", B279, B279 * IFERROR(VLOOKUP(C279, 'QTY_CONVERSIONS '!A:B, 2, FALSE), "Units not found")) -> 5.6 | M279: =B279*K279 -> 25760 | N279: =IFERROR(VLOOKUP(D279, Product_Category!A:B, 2, FALSE), "Uncategorized") -> CMC | O279: =K279 -> 4.6 | P279: =L279*O279 -> 25.76 | Q279: =Q278 -> 2023 | R279: =IFERROR(VLOOKUP(G279,'Importer Name'!A:B, 2, FALSE), "") -> PIOMA CHEMICALS | S279: =IFERROR(VLOOKUP(H279,'Supplier name '!A:B, 2, FALSE), "") -> SHANGHAI SHENGUANG
A280: China | B280: 2300 | C280: KGS | D280: SODIUM CMC | E280: 4.7999 | F280: USD | G280: PIOMA CHEMICALS | H280: SHANGHAI SHENGUANG | I280: =I279 -> Feb | J280: =IF(F280="USD", E280, E280 * IFERROR(VLOOKUP(F280, EXCHANGE_RATE!A:B, 2, FALSE), "Currency not found")) -> 4.7999 | K280: =ROUNDUP(J280,2) -> 4.8 | L280: =IF(C280="MTS", B280, B280 * IFERROR(VLOOKUP(C280, 'QTY_CONVERSIONS '!A:B, 2, FALSE), "Units not found")) -> 2.3 | M280: =B280*K280 -> 11040 | N280: =IFERROR(VLOOKUP(D280, Product_Category!A:B, 2, FALSE), "Uncategorized") -> CMC | O280: =K280 -> 4.8 | P280: =L280*O280 -> 11.04 | Q280: =Q279 -> 2023 | R280: =IFERROR(VLOOKUP(G280,'Importer Name'!A:B, 2, FALSE), "") -> PIOMA CHEMICALS | S280: =IFERROR(VLOOKUP(H280,'Supplier name '!A:B, 2, FALSE), "") -> SHANGHAI SHENGUANG
A281: China | B281: 500 | C281: KGS | D281: SODIUM CMC | E281: 4.4999 | F281: USD | G281: PIOMA CHEMICALS | H281: SHANGHAI SHENGUANG | I281: =I280 -> Feb | J281: =IF(F281="USD", E281, E281 * IFERROR(VLOOKUP(F281, EXCHANGE_RATE!A:B, 2, FALSE), "Currency not found")) -> 4.4999 | K281: =ROUNDUP(J281,2) -> 4.5 | L281: =IF(C281="MTS", B281, B281 * IFERROR(VLOOKUP(C281, 'QTY_CONVERSIONS '!A:B, 2, FALSE), "Units not found")) -> 0.5 | M281: =B281*K281 -> 2250 | N281: =IFERROR(VLOOKUP(D281, Product_Category!A:B, 2, FALSE), "Uncategorized") -> CMC | O281: =K281 -> 4.5 | P281: =L281*O281 -> 2.25 | Q281: =Q280 -> 2023 | R281: =IFERROR(VLOOKUP(G281,'Importer Name'!A:B, 2, FALSE), "") -> PIOMA CHEMICALS | S281: =IFERROR(VLOOKUP(H281,'Supplier name '!A:B, 2, FALSE), "") -> SHANGHAI SHENGUANG
A282: China | B282: 21000 | C282: KGS | D282: SODIUM CMC | E282: 2.8099 | F282: USD | G282: ARYAN CERAMICS | H282: SIDLEY CHEMICAL | I282: =I281 -> Feb | J282: =IF(F282="USD", E282, E282 * IFERROR(VLOOKUP(F282, EXCHANGE_RATE!A:B, 2, FALSE), "Currency not found")) -> 2.8099 | K282: =ROUNDUP(J282,2) -> 2.81 | L282: =IF(C282="MTS", B282, B282 * IFERROR(VLOOKUP(C282, 'QTY_CONVERSIONS '!A:B, 2, FALSE), "Units not found")) -> 21 | M282: =B282*K282 -> 59010 | N282: =IFERROR(VLOOKUP(D282, Product_Category!A:B, 2, FALSE), "Uncategorized") -> CMC | O282: =K282 -> 2.81 | P282: =L282*O282 -> 59.01 | Q282: =Q281 -> 2023 | R282: =IFERROR(VLOOKUP(G282,'Importer Name'!A:B, 2, FALSE), "") -> ARYAN CERAMICS | S282: =IFERROR(VLOOKUP(H282,'Supplier name '!A:B, 2, FALSE), "") -> SIDLEY CHEMICAL
A283: China | B283: 9000 | C283: KGS | D283: SODIUM CMC | E283: 4.2499 | F283: USD | G283: PRACHIN CHEMICAL | H283: SUZHOU DECAN | I283: =I282 -> Feb | J283: =IF(F283="USD", E283, E283 * IFERROR(VLOOKUP(F283, EXCHANGE_RATE!A:B, 2, FALSE), "Currency not found")) -> 4.2499 | K283: =ROUNDUP(J283,2) -> 4.25 | L283: =IF(C283="MTS", B283, B283 * IFERROR(VLOOKUP(C283, 'QTY_CONVERSIONS '!A:B, 2, FALSE), "Units not found")) -> 9 | M283: =B283*K283 -> 38250 | N283: =IFERROR(VLOOKUP(D283, Product_Category!A:B, 2, FALSE), "Uncategorized") -> CMC | O283: =K283 -> 4.25 | P283: =L283*O283 -> 38.25 | Q283: =Q282 -> 2023 | R283: =IFERROR(VLOOKUP(G283,'Importer Name'!A:B, 2, FALSE), "") -> PRACHIN CHEMICAL | S283: =IFERROR(VLOOKUP(H283,'Supplier name '!A:B, 2, FALSE), "") -> SUZHOU DECAN
... A319: Germany | B319: 100 | C319: KGS | D319: MG STEARATE PH.EUR.10ED.,NF 38 | E319: 12.0898 | F319: EUR | G319: CADILA HEALTHCARE | H319: DR PAUL LOHMANN | I319: =I318 -> Feb | J319: =IF(F319="USD", E319, E319 * IFERROR(VLOOKUP(F319, EXCHANGE_RATE!A:B, 2, FALSE), "Currency not found")) -> 12.936086 | K319: =ROUNDUP(J319,2) -> 12.94 | L319: =IF(C319="MTS", B319, B319 * IFERROR(VLOOKUP(C319, 'QTY_CONVERSIONS '!A:B, 2, FALSE), "Units not found")) -> 0.1 | M319: =B319*K319 -> 1294 | N319: =IFERROR(VLOOKUP(D319, Product_Category!A:B, 2, FALSE), "Uncategorized") -> MAGNESIUM STEARATE | O319: =K319 -> 12.94 | P319: =L319*O319 -> 1.294 | Q319: =Q318 -> 2023 | R319: =IFERROR(VLOOKUP(G319,'Importer Name'!A:B, 2, FALSE), "") -> CADILA HEALTHCARE | S319: =IFERROR(VLOOKUP(H319,'Supplier name '!A:B, 2, FALSE), "") -> DR PAUL LOHMANN
A320: Germany | B320: 20 | C320: KGS | D320: MG STEARATE PH.EUR.10ED.,NF 38 | E320: 49.519 | F320: EUR | G320: CADILA HEALTHCARE | H320: DR PAUL LOHMANN | I320: =I319 -> Feb | J320: =IF(F320="USD", E320, E320 * IFERROR(VLOOKUP(F320, EXCHANGE_RATE!A:B, 2, FALSE), "Currency not found")) -> 52.98533 | K320: =ROUNDUP(J320,2) -> 52.99 | L320: =IF(C320="MTS", B320, B320 * IFERROR(VLOOKUP(C320, 'QTY_CONVERSIONS '!A:B, 2, FALSE), "Units not found")) -> 0.02 | M320: =B320*K320 -> 1059.8 | N320: =IFERROR(VLOOKUP(D320, Product_Category!A:B, 2, FALSE), "Uncategorized") -> MAGNESIUM STEARATE | O320: =K320*1000 -> 52990 | P320: =L320*O320 -> 1059.8 | Q320: =Q319 -> 2023 | R320: =IFERROR(VLOOKUP(G320,'Importer Name'!A:B, 2, FALSE), "") -> CADILA HEALTHCARE | S320: =IFERROR(VLOOKUP(H320,'Supplier name '!A:B, 2, FALSE), "") -> DR PAUL LOHMANN
A321: Germany | B321: 20 | C321: KGS | D321: MG STEARATE PH.EUR.10ED.,NF 38 | E321: 49.519 | F321: EUR | G321: ZYDUS HEALTHCARE | H321: DR PAUL LOHMANN | I321: =I320 -> Feb | J321: =IF(F321="USD", E321, E321 * IFERROR(VLOOKUP(F321, EXCHANGE_RATE!A:B, 2, FALSE), "Currency not found")) -> 52.98533 | K321: =ROUNDUP(J321,2) -> 52.99 | L321: =IF(C321="MTS", B321, B321 * IFERROR(VLOOKUP(C321, 'QTY_CONVERSIONS '!A:B, 2, FALSE), "Units not found")) -> 0.02 | M321: =B321*K321 -> 1059.8 | N321: =IFERROR(VLOOKUP(D321, Product_Category!A:B, 2, FALSE), "Uncategorized") -> MAGNESIUM STEARATE | O321: =K321*1000 -> 52990 | P321: =L321*O321 -> 1059.8 | Q321: =Q320 -> 2023 | R321: =IFERROR(VLOOKUP(G321,'Importer Name'!A:B, 2, FALSE), "") -> ZYDUS HEALTHCARE | S321: =IFERROR(VLOOKUP(H321,'Supplier name '!A:B, 2, FALSE), "") -> DR PAUL LOHMANN
A322: Germany | B322: 16000 | C322: KGS | D322: MCC EMCOCEL 112 | E322: 3.0704 | F322: EUR | G322: RETTENMAIER | H322: JRS PHARMA | I322: =I321 -> Feb | J322: =IF(F322="USD", E322, E322 * IFERROR(VLOOKUP(F322, EXCHANGE_RATE!A:B, 2, FALSE), "Currency not found")) -> 3.285328 | K322: =ROUNDUP(J322,2) -> 3.29 | L322: =IF(C322="MTS", B322, B322 * IFERROR(VLOOKUP(C322, 'QTY_CONVERSIONS '!A:B, 2, FALSE), "Units not found")) -> 16 | M322: =B322*K322 -> 52640 | N322: =IFERROR(VLOOKUP(D322, Product_Category!A:B, 2, FALSE), "Uncategorized") -> MCC | O322: =K322 -> 3.29 | P322: =L322*O322 -> 52.64 | Q322: =Q321 -> 2023 | R322: =IFERROR(VLOOKUP(G322,'Importer Name'!A:B, 2, FALSE), "") -> RETTENMAIER | S322: =IFERROR(VLOOKUP(H322,'Supplier name '!A:B, 2, FALSE), "") -> JRS PHARMA
A323: Germany | B323: 14400 | C323: KGS | D323: MCC EMCOCEL 112 | E323: 3.3033 | F323: EUR | G323: RETTENMAIER | H323: JRS PHARMA | I323: =I322 -> Feb | J323: =IF(F323="USD", E323, E323 * IFERROR(VLOOKUP(F323, EXCHANGE_RATE!A:B, 2, FALSE), "Currency not found")) -> 3.534531 | K323: =ROUNDUP(J323,2) -> 3.54 | L323: =IF(C323="MTS", B323, B323 * IFERROR(VLOOKUP(C323, 'QTY_CONVERSIONS '!A:B, 2, FALSE), "Units not found")) -> 14.4 | M323: =B323*K323 -> 50976 | N323: =IFERROR(VLOOKUP(D323, Product_Category!A:B, 2, FALSE), "Uncategorized") -> MCC | O323: =K323 -> 3.54 | P323: =L323*O323 -> 50.976 | Q323: =Q322 -> 2023 | R323: =IFERROR(VLOOKUP(G323,'Importer Name'!A:B, 2, FALSE), "") -> RETTENMAIER | S323: =IFERROR(VLOOKUP(H323,'Supplier name '!A:B, 2, FALSE), "") -> JRS PHARMA
A324: Germany | B324: 16000 | C324: KGS | D324: MCC EMCOCEL 112 | E324: 3.0704 | F324: EUR | G324: RETTENMAIER | H324: JRS PHARMA | I324: =I323 -> Feb | J324: =IF(F324="USD", E324, E324 * IFERROR(VLOOKUP(F324, EXCHANGE_RATE!A:B, 2, FALSE), "Currency not found")) -> 3.285328 | K324: =ROUNDUP(J324,2) -> 3.29 | L324: =IF(C324="MTS", B324, B324 * IFERROR(VLOOKUP(C324, 'QTY_CONVERSIONS '!A:B, 2, FALSE), "Units not found")) -> 16 | M324: =B324*K324 -> 52640 | N324: =IFERROR(VLOOKUP(D324, Product_Category!A:B, 2, FALSE), "Uncategorized") -> MCC | O324: =K324 -> 3.29 | P324: =L324*O324 -> 52.64 | Q324: =Q323 -> 2023 | R324: =IFERROR(VLOOKUP(G324,'Importer Name'!A:B, 2, FALSE), "") -> RETTENMAIER | S324: =IFERROR(VLOOKUP(H324,'Supplier name '!A:B, 2, FALSE), "") -> JRS PHARMA
A325: Germany | B325: 6400 | C325: KGS | D325: MCC EMCOCEL LP 200 | E325: 3.3328 | F325: EUR | G325: RETTENMAIER | H325: JRS PHARMA | I325: =I324 -> Feb | J325: =IF(F325="USD", E325, E325 * IFERROR(VLOOKUP(F325, EXCHANGE_RATE!A:B, 2, FALSE), "Currency not found")) -> 3.566096 | K325: =ROUNDUP(J325,2) -> 3.57 | L325: =IF(C325="MTS", B325, B325 * IFERROR(VLOOKUP(C325, 'QTY_CONVERSIONS '!A:B, 2, FALSE), "Units not found")) -> 6.4 | M325: =B325*K325 -> 22848 | N325: =IFERROR(VLOOKUP(D325, Product_Category!A:B, 2, FALSE), "Uncategorized") -> MCC | O325: =K325 -> 3.57 | P325: =L325*O325 -> 22.848 | Q325: =Q324 -> 2023 | R325: =IFERROR(VLOOKUP(G325,'Importer Name'!A:B, 2, FALSE), "") -> RETTENMAIER | S325: =IFERROR(VLOOKUP(H325,'Supplier name '!A:B, 2, FALSE), "") -> JRS PHARMA
A326: Germany | B326: 16000 | C326: KGS | D326: MCC VIVAPUR 102-NF | E326: 2.934 | F326: EUR | G326: RETTENMAIER | H326: JRS PHARMA | I326: =I325 -> Feb | J326: =IF(F326="USD", E326, E326 * IFERROR(VLOOKUP(F326, EXCHANGE_RATE!A:B, 2, FALSE), "Currency not found")) -> 3.13938 | K326: =ROUNDUP(J326,2) -> 3.14 | L326: =IF(C326="MTS", B326, B326 * IFERROR(VLOOKUP(C326, 'QTY_CONVERSIONS '!A:B, 2, FALSE), "Units not found")) -> 16 | M326: =B326*K326 -> 50240 | N326: =IFERROR(VLOOKUP(D326, Product_Category!A:B, 2, FALSE), "Uncategorized") -> MCC | O326: =K326 -> 3.14 | P326: =L326*O326 -> 50.24 | Q326: =Q325 -> 2023 | R326: =IFERROR(VLOOKUP(G326,'Importer Name'!A:B, 2, FALSE), "") -> RETTENMAIER | S326: =IFERROR(VLOOKUP(H326,'Supplier name '!A:B, 2, FALSE), "") -> JRS PHARMA
A327: Germany | B327: 16000 | C327: KGS | D327: MCC VIVAPUR 102-NF | E327: 2.6751 | F327: EUR | G327: RETTENMAIER | H327: JRS PHARMA | I327: =I326 -> Feb | J327: =IF(F327="USD", E327, E327 * IFERROR(VLOOKUP(F327, EXCHANGE_RATE!A:B, 2, FALSE), "Currency not found")) -> 2.862357 | K327: =ROUNDUP(J327,2) -> 2.87 | L327: =IF(C327="MTS", B327, B327 * IFERROR(VLOOKUP(C327, 'QTY_CONVERSIONS '!A:B, 2, FALSE), "Units not found")) -> 16 | M327: =B327*K327 -> 45920 | N327: =IFERROR(VLOOKUP(D327, Product_Category!A:B, 2, FALSE), "Uncategorized") -> MCC | O327: =K327 -> 2.87 | P327: =L327*O327 -> 45.92 | Q327: =Q326 -> 2023 | R327: =IFERROR(VLOOKUP(G327,'Importer Name'!A:B, 2, FALSE), "") -> RETTENMAIER | S327: =IFERROR(VLOOKUP(H327,'Supplier name '!A:B, 2, FALSE), "") -> JRS PHARMA
A328: Germany | B328: 16000 | C328: KGS | D328: MCC VIVAPUR 102-NF | E328: 2.934 | F328: EUR | G328: RETTENMAIER | H328: JRS PHARMA | I328: =I327 -> Feb | J328: =IF(F328="USD", E328, E328 * IFERROR(VLOOKUP(F328, EXCHANGE_RATE!A:B, 2, FALSE), "Currency not found")) -> 3.13938 | K328: =ROUNDUP(J328,2) -> 3.14 | L328: =IF(C328="MTS", B328, B328 * IFERROR(VLOOKUP(C328, 'QTY_CONVERSIONS '!A:B, 2, FALSE), "Units not found")) -> 16 | M328: =B328*K328 -> 50240 | N328: =IFERROR(VLOOKUP(D328, Product_Category!A:B, 2, FALSE), "Uncategorized") -> MCC | O328: =K328 -> 3.14 | P328: =L328*O328 -> 50.24 | Q328: =Q327 -> 2023 | R328: =IFERROR(VLOOKUP(G328,'Importer Name'!A:B, 2, FALSE), "") -> RETTENMAIER | S328: =IFERROR(VLOOKUP(H328,'Supplier name '!A:B, 2, FALSE), "") -> JRS PHARMA
A329: Germany | B329: 14000 | C329: KGS | D329: MCC VIVAPUR 102-NF | E329: 2.934 | F329: EUR | G329: RETTENMAIER | H329: JRS PHARMA | I329: =I328 -> Feb | J329: =IF(F329="USD", E329, E329 * IFERROR(VLOOKUP(F329, EXCHANGE_RATE!A:B, 2, FALSE), "Currency not found")) -> 3.13938 | K329: =ROUNDUP(J329,2) -> 3.14 | L329: =IF(C329="MTS", B329, B329 * IFERROR(VLOOKUP(C329, 'QTY_CONVERSIONS '!A:B, 2, FALSE), "Units not found")) -> 14 | M329: =B329*K329 -> 43960 | N329: =IFERROR(VLOOKUP(D329, Product_Category!A:B, 2, FALSE), "Uncategorized") -> MCC | O329: =K329 -> 3.14 | P329: =L329*O329 -> 43.96 | Q329: =Q328 -> 2023 | R329: =IFERROR(VLOOKUP(G329,'Importer Name'!A:B, 2, FALSE), "") -> RETTENMAIER | S329: =IFERROR(VLOOKUP(H329,'Supplier name '!A:B, 2, FALSE), "") -> JRS PHARMA
A330: Germany | B330: 25 | C330: KGS | D330: VIVAPUR MCC | E330: 7.4387 | F330: EUR | G330: RETTENMAIER | H330: JRS PHARMA | I330: =I329 -> Feb | J330: =IF(F330="USD", E330, E330 * IFERROR(VLOOKUP(F330, EXCHANGE_RATE!A:B, 2, FALSE), "Currency not found")) -> 7.959409 | K330: =ROUNDUP(J330,2) -> 7.96 | L330: =IF(C330="MTS", B330, B330 * IFERROR(VLOOKUP(C330, 'QTY_CONVERSIONS '!A:B, 2, FALSE), "Units not found")) -> 0.025 | M330: =B330*K330 -> 199 | N330: =IFERROR(VLOOKUP(D330, Product_Category!A:B, 2, FALSE), "Uncategorized") -> MCC | O330: =K330 -> 7.96 | P330: =L330*O330 -> 0.199 | Q330: =Q329 -> 2023 | R330: =IFERROR(VLOOKUP(G330,'Importer Name'!A:B, 2, FALSE), "") -> RETTENMAIER | S330: =IFERROR(VLOOKUP(H330,'Supplier name '!A:B, 2, FALSE), "") -> JRS PHARMA
A331: Germany | B331: 25 | C331: KGS | D331: VIVAPUR MCC | E331: 7.4387 | F331: EUR | G331: RETTENMAIER | H331: JRS PHARMA | I331: =I330 -> Feb | J331: =IF(F331="USD", E331, E331 * IFERROR(VLOOKUP(F331, EXCHANGE_RATE!A:B, 2, FALSE), "Currency not found")) -> 7.959409 | K331: =ROUNDUP(J331,2) -> 7.96 | L331: =IF(C331="MTS", B331, B331 * IFERROR(VLOOKUP(C331, 'QTY_CONVERSIONS '!A:B, 2, FALSE), "Units not found")) -> 0.025 | M331: =B331*K331 -> 199 | N331: =IFERROR(VLOOKUP(D331, Product_Category!A:B, 2, FALSE), "Uncategorized") -> MCC | O331: =K331 -> 7.96 | P331: =L331*O331 -> 0.199 | Q331: =Q330 -> 2023 | R331: =IFERROR(VLOOKUP(G331,'Importer Name'!A:B, 2, FALSE), "") -> RETTENMAIER | S331: =IFERROR(VLOOKUP(H331,'Supplier name '!A:B, 2, FALSE), "") -> JRS PHARMA
A332: Germany | B332: 100 | C332: KGS | D332: MCC CELLETS 700-PH EUR-USP-NF | E332: 29.9994 | F332: EUR | G332: ARIHANT INNOCHEM | H332: M S PHARMATRANS | I332: =I331 -> Feb | J332: =IF(F332="USD", E332, E332 * IFERROR(VLOOKUP(F332, EXCHANGE_RATE!A:B, 2, FALSE), "Currency not found")) -> 32.099358 | K332: =ROUNDUP(J332,2) -> 32.1 | L332: =IF(C332="MTS", B332, B332 * IFERROR(VLOOKUP(C332, 'QTY_CONVERSIONS '!A:B, 2, FALSE), "Units not found")) -> 0.1 | M332: =B332*K332 -> 3210 | N332: =IFERROR(VLOOKUP(D332, Product_Category!A:B, 2, FALSE), "Uncategorized") -> MCC | O332: =K332 -> 32.1 | P332: =L332*O332 -> 3.21 | Q332: =Q331 -> 2023 | R332: =IFERROR(VLOOKUP(G332,'Importer Name'!A:B, 2, FALSE), "") -> ARIHANT INNOCHEM | S332: =IFERROR(VLOOKUP(H332,'Supplier name '!A:B, 2, FALSE), "") -> M S PHARMATRANS
A333: Germany | B333: 1000 | C333: KGS | D333: TEXTURECEL PA SODIUM CMC | E333: 12.2998 | F333: USD | G333: S KUSHALCHAND INT | H333: NUTRITION BIOSCI | I333: =I332 -> Feb | J333: =IF(F333="USD", E333, E333 * IFERROR(VLOOKUP(F333, EXCHANGE_RATE!A:B, 2, FALSE), "Currency not found")) -> 12.2998 | K333: =ROUNDUP(J333,2) -> 12.3 | L333: =IF(C333="MTS", B333, B333 * IFERROR(VLOOKUP(C333, 'QTY_CONVERSIONS '!A:B, 2, FALSE), "Units not found")) -> 1 | M333: =B333*K333 -> 12300 | N333: =IFERROR(VLOOKUP(D333, Product_Category!A:B, 2, FALSE), "Uncategorized") -> CMC | O333: =K333 -> 12.3 | P333: =L333*O333 -> 12.3 | Q333: =Q332 -> 2023 | R333: =IFERROR(VLOOKUP(G333,'Importer Name'!A:B, 2, FALSE), "") -> S KUSHALCHAND INT | S333: =IFERROR(VLOOKUP(H333,'Supplier name '!A:B, 2, FALSE), "") -> NUTRITION BIOSCI
... A463: US | B463: 25000 | C463: GMS | D463: SODIUM CMC | E463: 1.18 | F463: INR | G463: SIGMA ALDRICH | H463: M S SIGMA ALDRICH | I463: =I462 -> Feb | J463: =IF(F463="USD", E463, E463 * IFERROR(VLOOKUP(F463, EXCHANGE_RATE!A:B, 2, FALSE), "Currency not found")) -> 0.01416 | K463: =ROUNDUP(J463,2) -> 0.02 | L463: =IF(C463="MTS", B463, B463 * IFERROR(VLOOKUP(C463, 'QTY_CONVERSIONS '!A:B, 2, FALSE), "Units not found")) -> 0.025 | M463: =B463*K463 -> 500 | N463: =IFERROR(VLOOKUP(D463, Product_Category!A:B, 2, FALSE), "Uncategorized") -> CMC | O463: =K463 -> 0.02 | P463: =L463*O463 -> 0.0005 | Q463: =Q462 -> 2023 | R463: =IFERROR(VLOOKUP(G463,'Importer Name'!A:B, 2, FALSE), "") -> SIGMA ALDRICH | S463: =IFERROR(VLOOKUP(H463,'Supplier name '!A:B, 2, FALSE), "") -> M S SIGMA ALDRICH
A464: BELGIUM | B464: 1 | C464: KGS | D464: SODIUM CMC | E464: 48.49 | F464: USD | G464: THERMO FISHER | H464: ACROS ORGANICS | I464: Mar | J464: =IF(F464="USD", E464, E464 * IFERROR(VLOOKUP(F464, EXCHANGE_RATE!A:B, 2, FALSE), "Currency not found")) -> 48.49 | K464: =ROUNDUP(J464,2) -> 48.49 | L464: =IF(C464="MTS", B464, B464 * IFERROR(VLOOKUP(C464, 'QTY_CONVERSIONS '!A:B, 2, FALSE), "Units not found")) -> 0.001 | M464: =B464*K464 -> 48.49 | N464: =IFERROR(VLOOKUP(D464, Product_Category!A:B, 2, FALSE), "Uncategorized") -> CMC | O464: =K464*1000 -> 48490 | P464: =L464*O464 -> 48.49 | Q464: =Q463 -> 2023 | R464: =IFERROR(VLOOKUP(G464,'Importer Name'!A:B, 2, FALSE), "") -> THERMO FISHER | S464: =IFERROR(VLOOKUP(H464,'Supplier name '!A:B, 2, FALSE), "") -> ACROS ORGANICS
A465: CHINA | B465: 2000 | C465: KGS | D465: SODIUM CMC | E465: 3.05 | F465: USD | G465: KAMDHENU IMPEX | H465: AGC IND | I465: =I464 -> Mar | J465: =IF(F465="USD", E465, E465 * IFERROR(VLOOKUP(F465, EXCHANGE_RATE!A:B, 2, FALSE), "Currency not found")) -> 3.05 | K465: =ROUNDUP(J465,2) -> 3.05 | L465: =IF(C465="MTS", B465, B465 * IFERROR(VLOOKUP(C465, 'QTY_CONVERSIONS '!A:B, 2, FALSE), "Units not found")) -> 2 | M465: =B465*K465 -> 6100 | N465: =IFERROR(VLOOKUP(D465, Product_Category!A:B, 2, FALSE), "Uncategorized") -> CMC | O465: =K465 -> 3.05 | P465: =L465*O465 -> 6.1 | Q465: =Q464 -> 2023 | R465: =IFERROR(VLOOKUP(G465,'Importer Name'!A:B, 2, FALSE), "") -> KAMDHENU IMPEX | S465: =IFERROR(VLOOKUP(H465,'Supplier name '!A:B, 2, FALSE), "") -> AGC INDUSTRIES CO LIMITED
A466: CHINA | B466: 10000 | C466: KGS | D466: SODIUM CMC | E466: 3.1 | F466: USD | G466: KAMDHENU IMPEX | H466: AGC IND | I466: =I465 -> Mar | J466: =IF(F466="USD", E466, E466 * IFERROR(VLOOKUP(F466, EXCHANGE_RATE!A:B, 2, FALSE), "Currency not found")) -> 3.1 | K466: =ROUNDUP(J466,2) -> 3.1 | L466: =IF(C466="MTS", B466, B466 * IFERROR(VLOOKUP(C466, 'QTY_CONVERSIONS '!A:B, 2, FALSE), "Units not found")) -> 10 | M466: =B466*K466 -> 31000 | N466: =IFERROR(VLOOKUP(D466, Product_Category!A:B, 2, FALSE), "Uncategorized") -> CMC | O466: =K466 -> 3.1 | P466: =L466*O466 -> 31 | Q466: =Q465 -> 2023 | R466: =IFERROR(VLOOKUP(G466,'Importer Name'!A:B, 2, FALSE), "") -> KAMDHENU IMPEX | S466: =IFERROR(VLOOKUP(H466,'Supplier name '!A:B, 2, FALSE), "") -> AGC INDUSTRIES CO LIMITED
...

Sheet EXPORT_DATA
A1: Country | B1: Qty(KGS) | C1: Units | D1: Product Name | E1: PRICE PER KGS | F1: Currency | G1: SOURCE COMPANY | H1: CUSTOMER NAME | I1: MONTH | J1: PRICE FOR KGS(USD) | K1: PRICE(USD) | L1: QTY(MTS) | M1: TOTAL PRICE(USD) | N1: PRODUCT_CATEGORY | O1: PRICE FOR TONN(USD) | P1: TOTAL PRICE(USD-TONN) | Q1: Year | R1: SOURCE COMPANY FINAL | S1: CUSTOMER NAME FINAL
A2: ALGERIA | B2: 4500 | C2: KGS | D2: MCC | E2: 2.55 | F2: USD | G2: JAI RADHE SALES | H2: TO THE ORDER | I2: Jan | J2: =IF(F2="USD", E2, E2 * IFERROR(VLOOKUP(F2, EXCHANGE_RATE!A:B, 2, FALSE), "Currency not found")) -> 2.55 | K2: =ROUNDUP(J2,2) -> 2.55 | L2: =IF(C2="MTS", B2, B2 * IFERROR(VLOOKUP(C2, 'QTY_CONVERSIONS '!A:B, 2, FALSE), "Units not found")) -> 4.5 | M2: =B2*K2 -> 11475 | N2: =IFERROR(VLOOKUP(D2, Product_Category!A:B, 2, FALSE), "Uncategorized") -> MCC | O2: =K2*1000 -> 2550 | P2: =L2*O2 -> 11475 | Q2: 2023 | R2: =IFERROR(VLOOKUP(G2,'SOURCE COMPANY'!A:B, 2, FALSE), "") -> JAI RADHE SALES | S2: =IFERROR(VLOOKUP(H2,'CUSTOMER NAME'!A:B, 2, FALSE), "") -> TO THE ORDER
A3: ALGERIA | B3: 13000 | C3: KGS | D3: MCC | E3: 2.45 | F3: USD | G3: JAI RADHE SALES | H3: TO THE ORDER | I3: =I2 -> Jan | J3: =IF(F3="USD", E3, E3 * IFERROR(VLOOKUP(F3, EXCHANGE_RATE!A:B, 2, FALSE), "Currency not found")) -> 2.45 | K3: =ROUNDUP(J3,2) -> 2.45 | L3: =IF(C3="MTS", B3, B3 * IFERROR(VLOOKUP(C3, 'QTY_CONVERSIONS '!A:B, 2, FALSE), "Units not found")) -> 13 | M3: =B3*K3 -> 31850 | N3: =IFERROR(VLOOKUP(D3, Product_Category!A:B, 2, FALSE), "Uncategorized") -> MCC | O3: =K3*1000 -> 2450 | P3: =L3*O3 -> 31850 | Q3: 2023 | R3: =IFERROR(VLOOKUP(G3,'SOURCE COMPANY'!A:B, 2, FALSE), "") -> JAI RADHE SALES | S3: =IFERROR(VLOOKUP(H3,'CUSTOMER NAME'!A:B, 2, FALSE), "") -> TO THE ORDER
A4: ALGERIA | B4: 12500 | C4: KGS | D4: MCC | E4: 3.95 | F4: USD | G4: JAI RADHE SALES | H4: TO THE ORDER | I4: =I3 -> Jan | J4: =IF(F4="USD", E4, E4 * IFERROR(VLOOKUP(F4, EXCHANGE_RATE!A:B, 2, FALSE), "Currency not found")) -> 3.95 | K4: =ROUNDUP(J4,2) -> 3.95 | L4: =IF(C4="MTS", B4, B4 * IFERROR(VLOOKUP(C4, 'QTY_CONVERSIONS '!A:B, 2, FALSE), "Units not found")) -> 12.5 | M4: =B4*K4 -> 49375 | N4: =IFERROR(VLOOKUP(D4, Product_Category!A:B, 2, FALSE), "Uncategorized") -> MCC | O4: =K4*1000 -> 3950 | P4: =L4*O4 -> 49375 | Q4: 2023 | R4: =IFERROR(VLOOKUP(G4,'SOURCE COMPANY'!A:B, 2, FALSE), "") -> JAI RADHE SALES | S4: =IFERROR(VLOOKUP(H4,'CUSTOMER NAME'!A:B, 2, FALSE), "") -> TO THE ORDER
A5: ALGERIA | B5: 4500 | C5: KGS | D5: MCC | E5: 2.55 | F5: USD | G5: JAI RADHE SALES | H5: TO THE ORDER | I5: =I4 -> Jan | J5: =IF(F5="USD", E5, E5 * IFERROR(VLOOKUP(F5, EXCHANGE_RATE!A:B, 2, FALSE), "Currency not found")) -> 2.55 | K5: =ROUNDUP(J5,2) -> 2.55 | L5: =IF(C5="MTS", B5, B5 * IFERROR(VLOOKUP(C5, 'QTY_CONVERSIONS '!A:B, 2, FALSE), "Units not found")) -> 4.5 | M5: =B5*K5 -> 11475 | N5: =IFERROR(VLOOKUP(D5, Product_Category!A:B, 2, FALSE), "Uncategorized") -> MCC | O5: =K5*1000 -> 2550 | P5: =L5*O5 -> 11475 | Q5: 2023 | R5: =IFERROR(VLOOKUP(G5,'SOURCE COMPANY'!A:B, 2, FALSE), "") -> JAI RADHE SALES | S5: =IFERROR(VLOOKUP(H5,'CUSTOMER NAME'!A:B, 2, FALSE), "") -> TO THE ORDER
A6: ALGERIA | B6: 13000 | C6: KGS | D6: MCC | E6: 2.45 | F6: USD | G6: JAI RADHE SALES | H6: TO THE ORDER | I6: =I5 -> Jan | J6: =IF(F6="USD", E6, E6 * IFERROR(VLOOKUP(F6, EXCHANGE_RATE!A:B, 2, FALSE), "Currency not found")) -> 2.45 | K6: =ROUNDUP(J6,2) -> 2.45 | L6: =IF(C6="MTS", B6, B6 * IFERROR(VLOOKUP(C6, 'QTY_CONVERSIONS '!A:B, 2, FALSE), "Units not found")) -> 13 | M6: =B6*K6 -> 31850 | N6: =IFERROR(VLOOKUP(D6, Product_Category!A:B, 2, FALSE), "Uncategorized") -> MCC | O6: =K6*1000 -> 2450 | P6: =L6*O6 -> 31850 | Q6: 2023 | R6: =IFERROR(VLOOKUP(G6,'SOURCE COMPANY'!A:B, 2, FALSE), "") -> JAI RADHE SALES | S6: =IFERROR(VLOOKUP(H6,'CUSTOMER NAME'!A:B, 2, FALSE), "") -> TO THE ORDER
A7: ALGERIA | B7: 12500 | C7: KGS | D7: MCC | E7: 3.95 | F7: USD | G7: JAI RADHE SALES | H7: TO THE ORDER | I7: =I6 -> Jan | J7: =IF(F7="USD", E7, E7 * IFERROR(VLOOKUP(F7, EXCHANGE_RATE!A:B, 2, FALSE), "Currency not found")) -> 3.95 | K7: =ROUNDUP(J7,2) -> 3.95 | L7: =IF(C7="MTS", B7, B7 * IFERROR(VLOOKUP(C7, 'QTY_CONVERSIONS '!A:B, 2, FALSE), "Units not found")) -> 12.5 | M7: =B7*K7 -> 49375 | N7: =IFERROR(VLOOKUP(D7, Product_Category!A:B, 2, FALSE), "Uncategorized") -> MCC | O7: =K7*1000 -> 3950 | P7: =L7*O7 -> 49375 | Q7: 2023 | R7: =IFERROR(VLOOKUP(G7,'SOURCE COMPANY'!A:B, 2, FALSE), "") -> JAI RADHE SALES | S7: =IFERROR(VLOOKUP(H7,'CUSTOMER NAME'!A:B, 2, FALSE), "") -> TO THE ORDER
A8: UAE | B8: 24000 | C8: KGS | D8: ACECEL-102 | E8: 2.04 | F8: EUR | G8: SIGACHI | H8: AEGON SHIPPING LLC | I8: October | J8: =IF(F8="USD", E8, E8 * IFERROR(VLOOKUP(F8, EXCHANGE_RATE!A:B, 2, FALSE), "Currency not found")) -> 2.1828 | K8: =ROUNDUP(J8,2) -> 2.19 | L8: =IF(C8="MTS", B8, B8 * IFERROR(VLOOKUP(C8, 'QTY_CONVERSIONS '!A:B, 2, FALSE), "Units not found")) -> 24 | M8: =B8*K8 -> 52560 | N8: =IFERROR(VLOOKUP(D8, Product_Category!A:B, 2, FALSE), "Uncategorized") -> MCC | O8: =K8*1000 -> 2190 | P8: =L8*O8 -> 52560 | Q8: 2023 | R8: =IFERROR(VLOOKUP(G8,'SOURCE COMPANY'!A:B, 2, FALSE), "") -> Sigachi Industries limited | S8: =IFERROR(VLOOKUP(H8,'CUSTOMER NAME'!A:B, 2, FALSE), "") -> AEGON SHIPPING LLC
A9: UAE | B9: 24000 | C9: KGS | D9: ACECEL-101 | E9: 1.93 | F9: EUR | G9: SIGACHI | H9: AEGON SHIPPING LLC | I9: October | J9: =IF(F9="USD", E9, E9 * IFERROR(VLOOKUP(F9, EXCHANGE_RATE!A:B, 2, FALSE), "Currency not found")) -> 2.0651 | K9: =ROUNDUP(J9,2) -> 2.07 | L9: =IF(C9="MTS", B9, B9 * IFERROR(VLOOKUP(C9, 'QTY_CONVERSIONS '!A:B, 2, FALSE), "Units not found")) -> 24 | M9: =B9*K9 -> 49680 | N9: =IFERROR(VLOOKUP(D9, Product_Category!A:B, 2, FALSE), "Uncategorized") -> MCC | O9: =K9*1000 -> 2070 | P9: =L9*O9 -> 49680 | Q9: 2023 | R9: =IFERROR(VLOOKUP(G9,'SOURCE COMPANY'!A:B, 2, FALSE), "") -> Sigachi Industries limited | S9: =IFERROR(VLOOKUP(H9,'CUSTOMER NAME'!A:B, 2, FALSE), "") -> AEGON SHIPPING LLC
A10: Nigeria | B10: 500 | C10: KGS | D10: SODIUM CMC | E10: 5.46 | F10: USD | G10: DABUR INDIA LIMITED | H10: AFRICAN CONSUMER CARE | I10: September | J10: =IF(F10="USD", E10, E10 * IFERROR(VLOOKUP(F10, EXCHANGE_RATE!A:B, 2, FALSE), "Currency not found")) -> 5.46 | K10: =ROUNDUP(J10,2) -> 5.46 | L10: =IF(C10="MTS", B10, B10 * IFERROR(VLOOKUP(C10, 'QTY_CONVERSIONS '!A:B, 2, FALSE), "Units not found")) -> 0.5 | M10: =B10*K10 -> 2730 | N10: =IFERROR(VLOOKUP(D10, Product_Category!A:B, 2, FALSE), "Uncategorized") -> CMC | O10: =K10*1000 -> 5460 | P10: =L10*O10 -> 2730 | Q10: 2023 | R10: =IFERROR(VLOOKUP(G10,'SOURCE COMPANY'!A:B, 2, FALSE), "") -> DABUR INDIA LIMITED | S10: =IFERROR(VLOOKUP(H10,'CUSTOMER NAME'!A:B, 2, FALSE), "") -> AFRICAN CONSUMER CARE
A11: CONGO | B11: 500 | C11: KGS | D11: SODIUM CMC | E11: 3.35 | F11: USD | G11: VINPA EXPORTS | H11: AFRICAN CONSUMER CARE | I11: =I10 -> September | J11: =IF(F11="USD", E11, E11 * IFERROR(VLOOKUP(F11, EXCHANGE_RATE!A:B, 2, FALSE), "Currency not found")) -> 3.35 | K11: =ROUNDUP(J11,2) -> 3.35 | L11: =IF(C11="MTS", B11, B11 * IFERROR(VLOOKUP(C11, 'QTY_CONVERSIONS '!A:B, 2, FALSE), "Units not found")) -> 0.5 | M11: =B11*K11 -> 1675 | N11: =IFERROR(VLOOKUP(D11, Product_Category!A:B, 2, FALSE), "Uncategorized") -> CMC | O11: =K11*1000 -> 3350 | P11: =L11*O11 -> 1675 | Q11: 2023 | R11: =IFERROR(VLOOKUP(G11,'SOURCE COMPANY'!A:B, 2, FALSE), "") -> VINPA EXPORTS | S11: =IFERROR(VLOOKUP(H11,'CUSTOMER NAME'!A:B, 2, FALSE), "") -> AFRICAN CONSUMER CARE
A12: Ivory Coast | B12: 400 | C12: KGS | D12: MCC BP | E12: 2.86 | F12: USD | G12: AFRICURE PHARMA | H12: AFRICURE PHARMA | I12: =I11 -> September | J12: =IF(F12="USD", E12, E12 * IFERROR(VLOOKUP(F12, EXCHANGE_RATE!A:B, 2, FALSE), "Currency not found")) -> 2.86 | K12: =ROUNDUP(J12,2) -> 2.86 | L12: =IF(C12="MTS", B12, B12 * IFERROR(VLOOKUP(C12, 'QTY_CONVERSIONS '!A:B, 2, FALSE), "Units not found")) -> 0.4 | M12: =B12*K12 -> 1144 | N12: =IFERROR(VLOOKUP(D12, Product_Category!A:B, 2, FALSE), "Uncategorized") -> MCC | O12: =K12*1000 -> 2860 | P12: =L12*O12 -> 1144 | Q12: 2023 | R12: =IFERROR(VLOOKUP(G12,'SOURCE COMPANY'!A:B, 2, FALSE), "") -> AFRICURE PHARMA | S12: =IFERROR(VLOOKUP(H12,'CUSTOMER NAME'!A:B, 2, FALSE), "") -> AFRICURE PHARMA
A13: Cameroon | B13: 250 | C13: KGS | D13: Magnesium Stearate | E13: 2.33 | F13: USD | G13: AFRICURE PHARMA | H13: AFRICURE PHARMA | I13: October | J13: =IF(F13="USD", E13, E13 * IFERROR(VLOOKUP(F13, EXCHANGE_RATE!A:B, 2, FALSE), "Currency not found")) -> 2.33 | K13: =ROUNDUP(J13,2) -> 2.33 | L13: =IF(C13="MTS", B13, B13 * IFERROR(VLOOKUP(C13, 'QTY_CONVERSIONS '!A:B, 2, FALSE), "Units not found")) -> 0.25 | M13: =B13*K13 -> 582.5 | N13: =IFERROR(VLOOKUP(D13, Product_Category!A:B, 2, FALSE), "Uncategorized") -> MAGNESIUM STEARATE | O13: =K13*1000 -> 2330 | P13: =L13*O13 -> 582.5 | Q13: 2023 | R13: =IFERROR(VLOOKUP(G13,'SOURCE COMPANY'!A:B, 2, FALSE), "") -> AFRICURE PHARMA | S13: =IFERROR(VLOOKUP(H13,'CUSTOMER NAME'!A:B, 2, FALSE), "") -> AFRICURE PHARMA
A14: DJIBOUTI | B14: 100 | C14: KGS | D14: MG STEARATE BP | E14: 2.5 | F14: USD | G14: AFRICURE PHARMA | H14: AFRICURE PHARMA | I14: =I13 -> October | J14: =IF(F14="USD", E14, E14 * IFERROR(VLOOKUP(F14, EXCHANGE_RATE!A:B, 2, FALSE), "Currency not found")) -> 2.5 | K14: =ROUNDUP(J14,2) -> 2.5 | L14: =IF(C14="MTS", B14, B14 * IFERROR(VLOOKUP(C14, 'QTY_CONVERSIONS '!A:B, 2, FALSE), "Units not found")) -> 0.1 | M14: =B14*K14 -> 250 | N14: =IFERROR(VLOOKUP(D14, Product_Category!A:B, 2, FALSE), "Uncategorized") -> MAGNESIUM STEARATE | O14: =K14*1000 -> 2500 | P14: =L14*O14 -> 250 | Q14: 2023 | R14: =IFERROR(VLOOKUP(G14,'SOURCE COMPANY'!A:B, 2, FALSE), "") -> AFRICURE PHARMA | S14: =IFERROR(VLOOKUP(H14,'CUSTOMER NAME'!A:B, 2, FALSE), "") -> AFRICURE PHARMA
A15: Cameroon | B15: 250 | C15: KGS | D15: Magnesium Stearate | E15: 2.33 | F15: USD | G15: AFRICURE PHARMA | H15: AFRICURE PHARMA | I15: September | J15: =IF(F15="USD", E15, E15 * IFERROR(VLOOKUP(F15, EXCHANGE_RATE!A:B, 2, FALSE), "Currency not found")) -> 2.33 | K15: =ROUNDUP(J15,2) -> 2.33 | L15: =IF(C15="MTS", B15, B15 * IFERROR(VLOOKUP(C15, 'QTY_CONVERSIONS '!A:B, 2, FALSE), "Units not found")) -> 0.25 | M15: =B15*K15 -> 582.5 | N15: =IFERROR(VLOOKUP(D15, Product_Category!A:B, 2, FALSE), "Uncategorized") -> MAGNESIUM STEARATE | O15: =K15*1000 -> 2330 | P15: =L15*O15 -> 582.5 | Q15: 2023 | R15: =IFERROR(VLOOKUP(G15,'SOURCE COMPANY'!A:B, 2, FALSE), "") -> AFRICURE PHARMA | S15: =IFERROR(VLOOKUP(H15,'CUSTOMER NAME'!A:B, 2, FALSE), "") -> AFRICURE PHARMA
A16: DJIBOUTI | B16: 25 | C16: KGS | D16: Magnesium Stearate BP | E16: 2.5 | F16: USD | G16: AFRICURE PHARMA | H16: AFRICURE PHARMA | I16: =I15 -> September | J16: =IF(F16="USD", E16, E16 * IFERROR(VLOOKUP(F16, EXCHANGE_RATE!A:B, 2, FALSE), "Currency not found")) -> 2.5 | K16: =ROUNDUP(J16,2) -> 2.5 | L16: =IF(C16="MTS", B16, B16 * IFERROR(VLOOKUP(C16, 'QTY_CONVERSIONS '!A:B, 2, FALSE), "Units not found")) -> 0.025 | M16: =B16*K16 -> 62.5 | N16: =IFERROR(VLOOKUP(D16, Product_Category!A:B, 2, FALSE), "Uncategorized") -> MAGNESIUM STEARATE | O16: =K16*1000 -> 2500 | P16: =L16*O16 -> 62.5 | Q16: 2023 | R16: =IFERROR(VLOOKUP(G16,'SOURCE COMPANY'!A:B, 2, FALSE), "") -> AFRICURE PHARMA | S16: =IFERROR(VLOOKUP(H16,'CUSTOMER NAME'!A:B, 2, FALSE), "") -> AFRICURE PHARMA
A17: Ivory Coast | B17: 400 | C17: KGS | D17: MCC | E17: 2.86 | F17: USD | G17: AFRICURE PHARMA | H17: AFRICURE PHARMA | I17: September | J17: =IF(F17="USD", E17, E17 * IFERROR(VLOOKUP(F17, EXCHANGE_RATE!A:B, 2, FALSE), "Currency not found")) -> 2.86 | K17: =ROUNDUP(J17,2) -> 2.86 | L17: =IF(C17="MTS", B17, B17 * IFERROR(VLOOKUP(C17, 'QTY_CONVERSIONS '!A:B, 2, FALSE), "Units not found")) -> 0.4 | M17: =B17*K17 -> 1144 | N17: =IFERROR(VLOOKUP(D17, Product_Category!A:B, 2, FALSE), "Uncategorized") -> MCC | O17: =K17*1000 -> 2860 | P17: =L17*O17 -> 1144 | Q17: 2023 | R17: =IFERROR(VLOOKUP(G17,'SOURCE COMPANY'!A:B, 2, FALSE), "") -> AFRICURE PHARMA | S17: =IFERROR(VLOOKUP(H17,'CUSTOMER NAME'!A:B, 2, FALSE), "") -> AFRICURE PHARMA
A18: Sudan | B18: 425 | C18: KGS | D18: MCC & CMC | E18: 35.643 | F18: AED | G18: GANILK PRIVATE | H18: AGEEB PARMA | I18: =I17 -> September | J18: =IF(F18="USD", E18, E18 * IFERROR(VLOOKUP(F18, EXCHANGE_RATE!A:B, 2, FALSE), "Currency not found")) -> 9.62361 | K18: =ROUNDUP(J18,2) -> 9.63 | L18: =IF(C18="MTS", B18, B18 * IFERROR(VLOOKUP(C18, 'QTY_CONVERSIONS '!A:B, 2, FALSE), "Units not found")) -> 0.425 | M18: =B18*K18 -> 4092.75 | N18: =IFERROR(VLOOKUP(D18, Product_Category!A:B, 2, FALSE), "Uncategorized") -> CMC | O18: =K18*1000 -> 9630 | P18: =L18*O18 -> 4092.75 | Q18: 2023 | R18: =IFERROR(VLOOKUP(G18,'SOURCE COMPANY'!A:B, 2, FALSE), "") -> GANILK PRIVATE | S18: =IFERROR(VLOOKUP(H18,'CUSTOMER NAME'!A:B, 2, FALSE), "") -> AGEEB PARMA
A19: Sudan | B19: 425 | C19: KGS | D19: MCC & CMC | E19: 35.643 | F19: AED | G19: GANILK PRIVATE | H19: AGEEB PARMA | I19: =I18 -> September | J19: =IF(F19="USD", E19, E19 * IFERROR(VLOOKUP(F19, EXCHANGE_RATE!A:B, 2, FALSE), "Currency not found")) -> 9.62361 | K19: =ROUNDUP(J19,2) -> 9.63 | L19: =IF(C19="MTS", B19, B19 * IFERROR(VLOOKUP(C19, 'QTY_CONVERSIONS '!A:B, 2, FALSE), "Units not found")) -> 0.425 | M19: =B19*K19 -> 4092.75 | N19: =IFERROR(VLOOKUP(D19, Product_Category!A:B, 2, FALSE), "Uncategorized") -> CMC | O19: =K19*1000 -> 9630 | P19: =L19*O19 -> 4092.75 | Q19: 2023 | R19: =IFERROR(VLOOKUP(G19,'SOURCE COMPANY'!A:B, 2, FALSE), "") -> GANILK PRIVATE | S19: =IFERROR(VLOOKUP(H19,'CUSTOMER NAME'!A:B, 2, FALSE), "") -> AGEEB PARMA
A20: UAE | B20: 1 | C20: KGS | D20: CMC | E20: 3.72 | F20: USD | G20: RATNAVEL TRADERS | H20: AL HANEEN Manufacturing | I20: November | J20: =IF(F20="USD", E20, E20 * IFERROR(VLOOKUP(F20, EXCHANGE_RATE!A:B, 2, FALSE), "Currency not found")) -> 3.72 | K20: =ROUNDUP(J20,2) -> 3.72 | L20: =IF(C20="MTS", B20, B20 * IFERROR(VLOOKUP(C20, 'QTY_CONVERSIONS '!A:B, 2, FALSE), "Units not found")) -> 0.001 | M20: =B20*K20 -> 3.72 | N20: =IFERROR(VLOOKUP(D20, Product_Category!A:B, 2, FALSE), "Uncategorized") -> CMC | O20: =K20*1000 -> 3720 | P20: =L20*O20 -> 3.72 | Q20: 2023 | R20: =IFERROR(VLOOKUP(G20,'SOURCE COMPANY'!A:B, 2, FALSE), "") -> RATNAVEL TRADERS | S20: =IFERROR(VLOOKUP(H20,'CUSTOMER NAME'!A:B, 2, FALSE), "") -> AL HANEEN Manufacturing
A21: Tunisia | B21: 2 | C21: KGS | D21: SODIUM CMC | E21: 4.94 | F21: USD | G21: SISCO LABS | H21: AL S A IND FARMA | I21: November | J21: =IF(F21="USD", E21, E21 * IFERROR(VLOOKUP(F21, EXCHANGE_RATE!A:B, 2, FALSE), "Currency not found")) -> 4.94 | K21: =ROUNDUP(J21,2) -> 4.94 | L21: =IF(C21="MTS", B21, B21 * IFERROR(VLOOKUP(C21, 'QTY_CONVERSIONS '!A:B, 2, FALSE), "Units not found")) -> 0.002 | M21: =B21*K21 -> 9.88 | N21: =IFERROR(VLOOKUP(D21, Product_Category!A:B, 2, FALSE), "Uncategorized") -> CMC | O21: =K21*1000 -> 4940 | P21: =L21*O21 -> 9.88 | Q21: 2023 | R21: =IFERROR(VLOOKUP(G21,'SOURCE COMPANY'!A:B, 2, FALSE), "") -> SISCO Research Labs | S21: =IFERROR(VLOOKUP(H21,'CUSTOMER NAME'!A:B, 2, FALSE), "") -> AL S A IND FARMA
A22: Tunisia | B22: 10 | C22: KGS | D22: SODIUM CMC | E22: 4.94 | F22: USD | G22: SISCO LABS | H22: AL S A IND FARMA | I22: November | J22: =IF(F22="USD", E22, E22 * IFERROR(VLOOKUP(F22, EXCHANGE_RATE!A:B, 2, FALSE), "Currency not found")) -> 4.94 | K22: =ROUNDUP(J22,2) -> 4.94 | L22: =IF(C22="MTS", B22, B22 * IFERROR(VLOOKUP(C22, 'QTY_CONVERSIONS '!A:B, 2, FALSE), "Units not found")) -> 0.01 | M22: =B22*K22 -> 49.4 | N22: =IFERROR(VLOOKUP(D22, Product_Category!A:B, 2, FALSE), "Uncategorized") -> CMC | O22: =K22*1000 -> 4940 | P22: =L22*O22 -> 49.4 | Q22: 2023 | R22: =IFERROR(VLOOKUP(G22,'SOURCE COMPANY'!A:B, 2, FALSE), "") -> SISCO Research Labs | S22: =IFERROR(VLOOKUP(H22,'CUSTOMER NAME'!A:B, 2, FALSE), "") -> AL S A IND FARMA
A23: Yemen | B23: 20 | C23: PCS | D23: MG STEARATE | E23: 2.4199516 | F23: USD | G23: HIGH PURITY LAB | H23: AL SHAMIL TRADING | I23: =I22 -> November | J23: =IF(F23="USD", E23, E23 * IFERROR(VLOOKUP(F23, EXCHANGE_RATE!A:B, 2, FALSE), "Currency not found")) -> 2.4199516 | K23: =ROUNDUP(J23,2) -> 2.42 | L23: =IF(C23="MTS", B23, B23 * IFERROR(VLOOKUP(C23, 'QTY_CONVERSIONS '!A:B, 2, FALSE), "Units not found")) -> 4 | M23: =B23*K23 -> 48.4 | N23: =IFERROR(VLOOKUP(D23, Product_Category!A:B, 2, FALSE), "Uncategorized") -> MAGNESIUM STEARATE | O23: =K23*1000 -> 2420 | P23: =L23*O23 -> 9680 | Q23: 2023 | R23: =IFERROR(VLOOKUP(G23,'SOURCE COMPANY'!A:B, 2, FALSE), "") -> HIGH PURITY LAB | S23: =IFERROR(VLOOKUP(H23,'CUSTOMER NAME'!A:B, 2, FALSE), "") -> AL SHAMIL TRADING
A24: Bangladesh | B24: 4000 | C24: KGS | D24: Magnesium Sterate | E24: 1.55 | F24: USD | G24: MLA INDUSTRIES | H24: AL-ARAFAH ISLAMI | I24: November | J24: =IF(F24="USD", E24, E24 * IFERROR(VLOOKUP(F24, EXCHANGE_RATE!A:B, 2, FALSE), "Currency not found")) -> 1.55 | K24: =ROUNDUP(J24,2) -> 1.55 | L24: =IF(C24="MTS", B24, B24 * IFERROR(VLOOKUP(C24, 'QTY_CONVERSIONS '!A:B, 2, FALSE), "Units not found")) -> 4 | M24: =B24*K24 -> 6200 | N24: =IFERROR(VLOOKUP(D24, Product_Category!A:B, 2, FALSE), "Uncategorized") -> MAGNESIUM STEARATE | O24: =K24*1000 -> 1550 | P24: =L24*O24 -> 6200 | Q24: 2023 | R24: =IFERROR(VLOOKUP(G24,'SOURCE COMPANY'!A:B, 2, FALSE), "") -> MLA INDUSTRIES | S24: =IFERROR(VLOOKUP(H24,'CUSTOMER NAME'!A:B, 2, FALSE), "") -> AL-ARAFAH ISLAMI
A25: Bangladesh | B25: 1000 | C25: KGS | D25: MCC NUTRACEL TM 112 USP NF PH EUR JP IP | E25: 9.6 | F25: USD | G25: DFE PHARMA | H25: ALCHEM ENTERPRISE | I25: =I24 -> November | J25: =IF(F25="USD", E25, E25 * IFERROR(VLOOKUP(F25, EXCHANGE_RATE!A:B, 2, FALSE), "Currency not found")) -> 9.6 | K25: =ROUNDUP(J25,2) -> 9.6 | L25: =IF(C25="MTS", B25, B25 * IFERROR(VLOOKUP(C25, 'QTY_CONVERSIONS '!A:B, 2, FALSE), "Units not found")) -> 1 | M25: =B25*K25 -> 9600 | N25: =IFERROR(VLOOKUP(D25, Product_Category!A:B, 2, FALSE), "Uncategorized") -> MCC | O25: =K25*1000 -> 9600 | P25: =L25*O25 -> 9600 | Q25: 2023 | R25: =IFERROR(VLOOKUP(G25,'SOURCE COMPANY'!A:B, 2, FALSE), "") -> DFE PHARMA | S25: =IFERROR(VLOOKUP(H25,'CUSTOMER NAME'!A:B, 2, FALSE), "") -> ALCHEM ENTERPRISE
A26: Bangladesh | B26: 2000 | C26: KGS | D26: MCC PHARMACEL 112 USP NF PH EUR JP IP | E26: 9 | F26: USD | G26: DFE PHARMA | H26: ALCHEM ENTERPRISE | I26: =I25 -> November | J26: =IF(F26="USD", E26, E26 * IFERROR(VLOOKUP(F26, EXCHANGE_RATE!A:B, 2, FALSE), "Currency not found")) -> 9 | K26: =ROUNDUP(J26,2) -> 9 | L26: =IF(C26="MTS", B26, B26 * IFERROR(VLOOKUP(C26, 'QTY_CONVERSIONS '!A:B, 2, FALSE), "Units not found")) -> 2 | M26: =B26*K26 -> 18000 | N26: =IFERROR(VLOOKUP(D26, Product_Category!A:B, 2, FALSE), "Uncategorized") -> MCC | O26: =K26*1000 -> 9000 | P26: =L26*O26 -> 18000 | Q26: 2023 | R26: =IFERROR(VLOOKUP(G26,'SOURCE COMPANY'!A:B, 2, FALSE), "") -> DFE PHARMA | S26: =IFERROR(VLOOKUP(H26,'CUSTOMER NAME'!A:B, 2, FALSE), "") -> ALCHEM ENTERPRISE
A27: Bangladesh | B27: 100 | C27: KGS | D27: PHARMACEL SMCC 90 MCC USP NF PH EUR JP IP | E27: 14 | F27: USD | G27: DFE PHARMA | H27: ALCHEM ENTERPRISE | I27: =I26 -> November | J27: =IF(F27="USD", E27, E27 * IFERROR(VLOOKUP(F27, EXCHANGE_RATE!A:B, 2, FALSE), "Currency not found")) -> 14 | K27: =ROUNDUP(J27,2) -> 14 | L27: =IF(C27="MTS", B27, B27 * IFERROR(VLOOKUP(C27, 'QTY_CONVERSIONS '!A:B, 2, FALSE), "Units not found")) -> 0.1 | M27: =B27*K27 -> 1400 | N27: =IFERROR(VLOOKUP(D27, Product_Category!A:B, 2, FALSE), "Uncategorized") -> MCC | O27: =K27*1000 -> 14000 | P27: =L27*O27 -> 1400 | Q27: 2023 | R27: =IFERROR(VLOOKUP(G27,'SOURCE COMPANY'!A:B, 2, FALSE), "") -> DFE PHARMA | S27: =IFERROR(VLOOKUP(H27,'CUSTOMER NAME'!A:B, 2, FALSE), "") -> ALCHEM ENTERPRISE
A28: Iraq | B28: 6 | C28: KGS | D28: Magnesium Stearate | E28: 3.5 | F28: USD | G28: SISCO LABS | H28: ALCHEMY SCIENTIFIC QUARTER | I28: October | J28: =IF(F28="USD", E28, E28 * IFERROR(VLOOKUP(F28, EXCHANGE_RATE!A:B, 2, FALSE), "Currency not found")) -> 3.5 | K28: =ROUNDUP(J28,2) -> 3.5 | L28: =IF(C28="MTS", B28, B28 * IFERROR(VLOOKUP(C28, 'QTY_CONVERSIONS '!A:B, 2, FALSE), "Units not found")) -> 0.006 | M28: =B28*K28 -> 21 | N28: =IFERROR(VLOOKUP(D28, Product_Category!A:B, 2, FALSE), "Uncategorized") -> MAGNESIUM STEARATE | O28: =K28*1000 -> 3500 | P28: =L28*O28 -> 21 | Q28: 2023 | R28: =IFERROR(VLOOKUP(G28,'SOURCE COMPANY'!A:B, 2, FALSE), "") -> SISCO Research Labs | S28: =IFERROR(VLOOKUP(H28,'CUSTOMER NAME'!A:B, 2, FALSE), "") -> ALCHEMY SCIENTIFIC QUARTER
A29: Iraq | B29: 6 | C29: KGS | D29: SSG | E29: 3.16 | F29: USD | G29: SISCO LABS | H29: ALCHEMY SCIENTIFIC QUARTER | I29: October | J29: =IF(F29="USD", E29, E29 * IFERROR(VLOOKUP(F29, EXCHANGE_RATE!A:B, 2, FALSE), "Currency not found")) -> 3.16 | K29: =ROUNDUP(J29,2) -> 3.16 | L29: =IF(C29="MTS", B29, B29 * IFERROR(VLOOKUP(C29, 'QTY_CONVERSIONS '!A:B, 2, FALSE), "Units not found")) -> 0.006 | M29: =B29*K29 -> 18.96 | N29: =IFERROR(VLOOKUP(D29, Product_Category!A:B, 2, FALSE), "Uncategorized") -> SSG | O29: =K29*1000 -> 3160 | P29: =L29*O29 -> 18.96 | Q29: 2023 | R29: =IFERROR(VLOOKUP(G29,'SOURCE COMPANY'!A:B, 2, FALSE), "") -> SISCO Research Labs | S29: =IFERROR(VLOOKUP(H29,'CUSTOMER NAME'!A:B, 2, FALSE), "") -> ALCHEMY SCIENTIFIC QUARTER
A30: Iraq | B30: 6 | C30: KGS | D30: SODIUM CMC | E30: 5.26 | F30: USD | G30: SISCO LABS | H30: ALCHEMY SCIENTIFIC QUARTER | I30: October | J30: =IF(F30="USD", E30, E30 * IFERROR(VLOOKUP(F30, EXCHANGE_RATE!A:B, 2, FALSE), "Currency not found")) -> 5.26 | K30: =ROUNDUP(J30,2) -> 5.26 | L30: =IF(C30="MTS", B30, B30 * IFERROR(VLOOKUP(C30, 'QTY_CONVERSIONS '!A:B, 2, FALSE), "Units not found")) -> 0.006 | M30: =B30*K30 -> 31.56 | N30: =IFERROR(VLOOKUP(D30, Product_Category!A:B, 2, FALSE), "Uncategorized") -> CMC | O30: =K30*1000 -> 5260 | P30: =L30*O30 -> 31.56 | Q30: 2023 | R30: =IFERROR(VLOOKUP(G30,'SOURCE COMPANY'!A:B, 2, FALSE), "") -> SISCO Research Labs | S30: =IFERROR(VLOOKUP(H30,'CUSTOMER NAME'!A:B, 2, FALSE), "") -> ALCHEMY SCIENTIFIC QUARTER
A31: Iraq | B31: 6 | C31: KGS | D31: SODIUM CMC | E31: 4.94 | F31: USD | G31: SISCO LABS | H31: ALCHEMY SCIENTIFIC QUARTER | I31: October | J31: =IF(F31="USD", E31, E31 * IFERROR(VLOOKUP(F31, EXCHANGE_RATE!A:B, 2, FALSE), "Currency not found")) -> 4.94 | K31: =ROUNDUP(J31,2) -> 4.94 | L31: =IF(C31="MTS", B31, B31 * IFERROR(VLOOKUP(C31, 'QTY_CONVERSIONS '!A:B, 2, FALSE), "Units not found")) -> 0.006 | M31: =B31*K31 -> 29.64 | N31: =IFERROR(VLOOKUP(D31, Product_Category!A:B, 2, FALSE), "Uncategorized") -> CMC | O31: =K31*1000 -> 4940 | P31: =L31*O31 -> 29.64 | Q31: 2023 | R31: =IFERROR(VLOOKUP(G31,'SOURCE COMPANY'!A:B, 2, FALSE), "") -> SISCO Research Labs | S31: =IFERROR(VLOOKUP(H31,'CUSTOMER NAME'!A:B, 2, FALSE), "") -> ALCHEMY SCIENTIFIC QUARTER
A32: Iraq | B32: 6 | C32: KGS | D32: SODIUM CMC | E32: 6.44 | F32: USD | G32: SISCO LABS | H32: ALCHEMY SCIENTIFIC QUARTER | I32: October | J32: =IF(F32="USD", E32, E32 * IFERROR(VLOOKUP(F32, EXCHANGE_RATE!A:B, 2, FALSE), "Currency not found")) -> 6.44 | K32: =ROUNDUP(J32,2) -> 6.44 | L32: =IF(C32="MTS", B32, B32 * IFERROR(VLOOKUP(C32, 'QTY_CONVERSIONS '!A:B, 2, FALSE), "Units not found")) -> 0.006 | M32: =B32*K32 -> 38.64 | N32: =IFERROR(VLOOKUP(D32, Product_Category!A:B, 2, FALSE), "Uncategorized") -> CMC | O32: =K32*1000 -> 6440 | P32: =L32*O32 -> 38.64 | Q32: 2023 | R32: =IFERROR(VLOOKUP(G32,'SOURCE COMPANY'!A:B, 2, FALSE), "") -> SISCO Research Labs | S32: =IFERROR(VLOOKUP(H32,'CUSTOMER NAME'!A:B, 2, FALSE), "") -> ALCHEMY SCIENTIFIC QUARTER
A33: Iraq | B33: 12 | C33: KGS | D33: MCC PURE TLC 98% | E33: 1.44 | F33: USD | G33: SISCO LABS | H33: ALCHEMY SCIENTIFIC QUARTER | I33: October | J33: =IF(F33="USD", E33, E33 * IFERROR(VLOOKUP(F33, EXCHANGE_RATE!A:B, 2, FALSE), "Currency not found")) -> 1.44 | K33: =ROUNDUP(J33,2) -> 1.44 | L33: =IF(C33="MTS", B33, B33 * IFERROR(VLOOKUP(C33, 'QTY_CONVERSIONS '!A:B, 2, FALSE), "Units not found")) -> 0.012 | M33: =B33*K33 -> 17.28 | N33: =IFERROR(VLOOKUP(D33, Product_Category!A:B, 2, FALSE), "Uncategorized") -> MCC | O33: =K33*1000 -> 1440 | P33: =L33*O33 -> 17.28 | Q33: 2023 | R33: =IFERROR(VLOOKUP(G33,'SOURCE COMPANY'!A:B, 2, FALSE), "") -> SISCO Research Labs | S33: =IFERROR(VLOOKUP(H33,'CUSTOMER NAME'!A:B, 2, FALSE), "") -> ALCHEMY SCIENTIFIC QUARTER
A34: Nicaragua | B34: 0.5 | C34: KGS | D34: SODIUM CMC | E34: 2 | F34: USD | G34: GEMINI EXPORTS | H34: ALCOBENDAS-MADRID VAT | I34: November | J34: =IF(F34="USD", E34, E34 * IFERROR(VLOOKUP(F34, EXCHANGE_RATE!A:B, 2, FALSE), "Currency not found")) -> 2 | K34: =ROUNDUP(J34,2) -> 2 | L34: =IF(C34="MTS", B34, B34 * IFERROR(VLOOKUP(C34, 'QTY_CONVERSIONS '!A:B, 2, FALSE), "Units not found")) -> 0.0005 | M34: =B34*K34 -> 1 | N34: =IFERROR(VLOOKUP(D34, Product_Category!A:B, 2, FALSE), "Uncategorized") -> CMC | O34: =K34*1000 -> 2000 | P34: =L34*O34 -> 1 | Q34: 2023 | R34: =IFERROR(VLOOKUP(G34,'SOURCE COMPANY'!A:B, 2, FALSE), "") -> GEMINI EXPORTS | S34: =IFERROR(VLOOKUP(H34,'CUSTOMER NAME'!A:B, 2, FALSE), "") -> ALCOBENDAS-MADRID VAT
A35: Nicaragua | B35: 700 | C35: KGS | D35: SODIUM CMC | E35: 6 | F35: USD | G35: GEMINI EXPORTS | H35: ALCOBENDAS-MADRID VAT | I35: November | J35: =IF(F35="USD", E35, E35 * IFERROR(VLOOKUP(F35, EXCHANGE_RATE!A:B, 2, FALSE), "Currency not found")) -> 6 | K35: =ROUNDUP(J35,2) -> 6 | L35: =IF(C35="MTS", B35, B35 * IFERROR(VLOOKUP(C35, 'QTY_CONVERSIONS '!A:B, 2, FALSE), "Units not found")) -> 0.7 | M35: =B35*K35 -> 4200 | N35: =IFERROR(VLOOKUP(D35, Product_Category!A:B, 2, FALSE), "Uncategorized") -> CMC | O35: =K35*1000 -> 6000 | P35: =L35*O35 -> 4200 | Q35: 2023 | R35: =IFERROR(VLOOKUP(G35,'SOURCE COMPANY'!A:B, 2, FALSE), "") -> GEMINI EXPORTS | S35: =IFERROR(VLOOKUP(H35,'CUSTOMER NAME'!A:B, 2, FALSE), "") -> ALCOBENDAS-MADRID VAT
A36: Mexico | B36: 50 | C36: KGS | D36: MICCEL-102 | E36: 16 | F36: USD | G36: ANKIT PULPS | H36: ALFAMEX INDUSTRIAL | I36: December | J36: =IF(F36="USD", E36, E36 * IFERROR(VLOOKUP(F36, EXCHANGE_RATE!A:B, 2, FALSE), "Currency not found")) -> 16 | K36: =ROUNDUP(J36,2) -> 16 | L36: =IF(C36="MTS", B36, B36 * IFERROR(VLOOKUP(C36, 'QTY_CONVERSIONS '!A:B, 2, FALSE), "Units not found")) -> 0.05 | M36: =B36*K36 -> 800 | N36: =IFERROR(VLOOKUP(D36, Product_Category!A:B, 2, FALSE), "Uncategorized") -> MCC | O36: =K36*1000 -> 16000 | P36: =L36*O36 -> 800 | Q36: 2023 | R36: =IFERROR(VLOOKUP(G36,'SOURCE COMPANY'!A:B, 2, FALSE), "") -> Ankit Pulps & Boards | S36: =IFERROR(VLOOKUP(H36,'CUSTOMER NAME'!A:B, 2, FALSE), "") -> ALFAMEX INDUSTRIAL
A37: Mexico | B37: 18000 | C37: KGS | D37: MCC PH-102 | E37: 2.75 | F37: USD | G37: MURLI KRISHNA EXPORTS | H37: ALI FARMA | I37: September | J37: =IF(F37="USD", E37, E37 * IFERROR(VLOOKUP(F37, EXCHANGE_RATE!A:B, 2, FALSE), "Currency not found")) -> 2.75 | K37: =ROUNDUP(J37,2) -> 2.75 | L37: =IF(C37="MTS", B37, B37 * IFERROR(VLOOKUP(C37, 'QTY_CONVERSIONS '!A:B, 2, FALSE), "Units not found")) -> 18 | M37: =B37*K37 -> 49500 | N37: =IFERROR(VLOOKUP(D37, Product_Category!A:B, 2, FALSE), "Uncategorized") -> MCC | O37: =K37*1000 -> 2750 | P37: =L37*O37 -> 49500 | Q37: 2023 | R37: =IFERROR(VLOOKUP(G37,'SOURCE COMPANY'!A:B, 2, FALSE), "") -> MURLI KRISHNA EXPORTS | S37: =IFERROR(VLOOKUP(H37,'CUSTOMER NAME'!A:B, 2, FALSE), "") -> ALI FARMA
A38: Myanmar | B38: 375 | C38: KGS | D38: MG STEARATE PH.EUR | E38: 2.57 | F38: USD | G38: CADILA HEALTHCARE | H38: ALIDAC HEALTHCARE | I38: =I37 -> September | J38: =IF(F38="USD", E38, E38 * IFERROR(VLOOKUP(F38, EXCHANGE_RATE!A:B, 2, FALSE), "Currency not found")) -> 2.57 | K38: =ROUNDUP(J38,2) -> 2.57 | L38: =IF(C38="MTS", B38, B38 * IFERROR(VLOOKUP(C38, 'QTY_CONVERSIONS '!A:B, 2, FALSE), "Units not found")) -> 0.375 | M38: =B38*K38 -> 963.75 | N38: =IFERROR(VLOOKUP(D38, Product_Category!A:B, 2, FALSE), "Uncategorized") -> MAGNESIUM STEARATE | O38: =K38*1000 -> 2570 | P38: =L38*O38 -> 963.75 | Q38: 2023 | R38: =IFERROR(VLOOKUP(G38,'SOURCE COMPANY'!A:B, 2, FALSE), "") -> CADILA HEALTHCARE | S38: =IFERROR(VLOOKUP(H38,'CUSTOMER NAME'!A:B, 2, FALSE), "") -> ALIDAC HEALTHCARE
A39: Myanmar | B39: 150 | C39: KGS | D39: SODIUM CCM | E39: 10.85 | F39: USD | G39: CADILA HEALTHCARE | H39: ALIDAC HEALTHCARE | I39: October | J39: =IF(F39="USD", E39, E39 * IFERROR(VLOOKUP(F39, EXCHANGE_RATE!A:B, 2, FALSE), "Currency not found")) -> 10.85 | K39: =ROUNDUP(J39,2) -> 10.85 | L39: =IF(C39="MTS", B39, B39 * IFERROR(VLOOKUP(C39, 'QTY_CONVERSIONS '!A:B, 2, FALSE), "Units not found")) -> 0.15 | M39: =B39*K39 -> 1627.5 | N39: =IFERROR(VLOOKUP(D39, Product_Category!A:B, 2, FALSE), "Uncategorized") -> CROSCARMELLOSE SODIUM | O39: =K39*1000 -> 10850 | P39: =L39*O39 -> 1627.5 | Q39: 2023 | R39: =IFERROR(VLOOKUP(G39,'SOURCE COMPANY'!A:B, 2, FALSE), "") -> CADILA HEALTHCARE | S39: =IFERROR(VLOOKUP(H39,'CUSTOMER NAME'!A:B, 2, FALSE), "") -> ALIDAC HEALTHCARE
A40: Myanmar | B40: 40 | C40: KGS | D40: MCC | E40: 5.43 | F40: USD | G40: CADILA HEALTHCARE | H40: ALIDAC HEALTHCARE | I40: October | J40: =IF(F40="USD", E40, E40 * IFERROR(VLOOKUP(F40, EXCHANGE_RATE!A:B, 2, FALSE), "Currency not found")) -> 5.43 | K40: =ROUNDUP(J40,2) -> 5.43 | L40: =IF(C40="MTS", B40, B40 * IFERROR(VLOOKUP(C40, 'QTY_CONVERSIONS '!A:B, 2, FALSE), "Units not found")) -> 0.04 | M40: =B40*K40 -> 217.2 | N40: =IFERROR(VLOOKUP(D40, Product_Category!A:B, 2, FALSE), "Uncategorized") -> MCC | O40: =K40*1000 -> 5430 | P40: =L40*O40 -> 217.2 | Q40: 2023 | R40: =IFERROR(VLOOKUP(G40,'SOURCE COMPANY'!A:B, 2, FALSE), "") -> CADILA HEALTHCARE | S40: =IFERROR(VLOOKUP(H40,'CUSTOMER NAME'!A:B, 2, FALSE), "") -> ALIDAC HEALTHCARE
A41: Myanmar | B41: 240 | C41: KGS | D41: AVICEL PH102 | E41: 11.03 | F41: USD | G41: CADILA HEALTHCARE | H41: ALIDAC HEALTHCARE | I41: October | J41: =IF(F41="USD", E41, E41 * IFERROR(VLOOKUP(F41, EXCHANGE_RATE!A:B, 2, FALSE), "Currency not found")) -> 11.03 | K41: =ROUNDUP(J41,2) -> 11.03 | L41: =IF(C41="MTS", B41, B41 * IFERROR(VLOOKUP(C41, 'QTY_CONVERSIONS '!A:B, 2, FALSE), "Units not found")) -> 0.24 | M41: =B41*K41 -> 2647.2 | N41: =IFERROR(VLOOKUP(D41, Product_Category!A:B, 2, FALSE), "Uncategorized") -> MCC | O41: =K41*1000 -> 11030 | P41: =L41*O41 -> 2647.2 | Q41: 2023 | R41: =IFERROR(VLOOKUP(G41,'SOURCE COMPANY'!A:B, 2, FALSE), "") -> CADILA HEALTHCARE | S41: =IFERROR(VLOOKUP(H41,'CUSTOMER NAME'!A:B, 2, FALSE), "") -> ALIDAC HEALTHCARE
A42: Myanmar | B42: 50 | C42: KGS | D42: COMPRECEL M200 | E42: 6.29 | F42: USD | G42: CADILA HEALTHCARE | H42: ALIDAC HEALTHCARE | I42: October | J42: =IF(F42="USD", E42, E42 * IFERROR(VLOOKUP(F42, EXCHANGE_RATE!A:B, 2, FALSE), "Currency not found")) -> 6.29 | K42: =ROUNDUP(J42,2) -> 6.29 | L42: =IF(C42="MTS", B42, B42 * IFERROR(VLOOKUP(C42, 'QTY_CONVERSIONS '!A:B, 2, FALSE), "Units not found")) -> 0.05 | M42: =B42*K42 -> 314.5 | N42: =IFERROR(VLOOKUP(D42, Product_Category!A:B, 2, FALSE), "Uncategorized") -> MCC | O42: =K42*1000 -> 6290 | P42: =L42*O42 -> 314.5 | Q42: 2023 | R42: =IFERROR(VLOOKUP(G42,'SOURCE COMPANY'!A:B, 2, FALSE), "") -> CADILA HEALTHCARE | S42: =IFERROR(VLOOKUP(H42,'CUSTOMER NAME'!A:B, 2, FALSE), "") -> ALIDAC HEALTHCARE
A43: Myanmar | B43: 2000 | C43: KGS | D43: MCC | E43: 2.53 | F43: USD | G43: CADILA HEALTHCARE | H43: ALIDAC HEALTHCARE | I43: October | J43: =IF(F43="USD", E43, E43 * IFERROR(VLOOKUP(F43, EXCHANGE_RATE!A:B, 2, FALSE), "Currency not found")) -> 2.53 | K43: =ROUNDUP(J43,2) -> 2.53 | L43: =IF(C43="MTS", B43, B43 * IFERROR(VLOOKUP(C43, 'QTY_CONVERSIONS '!A:B, 2, FALSE), "Units not found")) -> 2 | M43: =B43*K43 -> 5060 | N43: =IFERROR(VLOOKUP(D43, Product_Category!A:B, 2, FALSE), "Uncategorized") -> MCC | O43: =K43*1000 -> 2530 | P43: =L43*O43 -> 5060 | Q43: 2023 | R43: =IFERROR(VLOOKUP(G43,'SOURCE COMPANY'!A:B, 2, FALSE), "") -> CADILA HEALTHCARE | S43: =IFERROR(VLOOKUP(H43,'CUSTOMER NAME'!A:B, 2, FALSE), "") -> ALIDAC HEALTHCARE
A44: Myanmar | B44: 2000 | C44: KGS | D44: AVICEL PH102 | E44: 11.03 | F44: USD | G44: CADILA HEALTHCARE | H44: ALIDAC HEALTHCARE | I44: October | J44: =IF(F44="USD", E44, E44 * IFERROR(VLOOKUP(F44, EXCHANGE_RATE!A:B, 2, FALSE), "Currency not found")) -> 11.03 | K44: =ROUNDUP(J44,2) -> 11.03 | L44: =IF(C44="MTS", B44, B44 * IFERROR(VLOOKUP(C44, 'QTY_CONVERSIONS '!A:B, 2, FALSE), "Units not found")) -> 2 | M44: =B44*K44 -> 22060 | N44: =IFERROR(VLOOKUP(D44, Product_Category!A:B, 2, FALSE), "Uncategorized") -> MCC | O44: =K44*1000 -> 11030 | P44: =L44*O44 -> 22060 | Q44: 2023 | R44: =IFERROR(VLOOKUP(G44,'SOURCE COMPANY'!A:B, 2, FALSE), "") -> CADILA HEALTHCARE | S44: =IFERROR(VLOOKUP(H44,'CUSTOMER NAME'!A:B, 2, FALSE), "") -> ALIDAC HEALTHCARE
A45: Myanmar | B45: 1500 | C45: KGS | D45: MCC RQ 102 | E45: 2.53 | F45: USD | G45: CADILA HEALTHCARE | H45: ALIDAC HEALTHCARE | I45: October | J45: =IF(F45="USD", E45, E45 * IFERROR(VLOOKUP(F45, EXCHANGE_RATE!A:B, 2, FALSE), "Currency not found")) -> 2.53 | K45: =ROUNDUP(J45,2) -> 2.53 | L45: =IF(C45="MTS", B45, B45 * IFERROR(VLOOKUP(C45, 'QTY_CONVERSIONS '!A:B, 2, FALSE), "Units not found")) -> 1.5 | M45: =B45*K45 -> 3795 | N45: =IFERROR(VLOOKUP(D45, Product_Category!A:B, 2, FALSE), "Uncategorized") -> MCC | O45: =K45*1000 -> 2530 | P45: =L45*O45 -> 3795 | Q45: 2023 | R45: =IFERROR(VLOOKUP(G45,'SOURCE COMPANY'!A:B, 2, FALSE), "") -> CADILA HEALTHCARE | S45: =IFERROR(VLOOKUP(H45,'CUSTOMER NAME'!A:B, 2, FALSE), "") -> ALIDAC HEALTHCARE
A46: Myanmar | B46: 150 | C46: KGS | D46: COMPRECEL M112D | E46: 8.06 | F46: USD | G46: CADILA HEALTHCARE | H46: ALIDAC HEALTHCARE | I46: October | J46: =IF(F46="USD", E46, E46 * IFERROR(VLOOKUP(F46, EXCHANGE_RATE!A:B, 2, FALSE), "Currency not found")) -> 8.06 | K46: =ROUNDUP(J46,2) -> 8.06 | L46: =IF(C46="MTS", B46, B46 * IFERROR(VLOOKUP(C46, 'QTY_CONVERSIONS '!A:B, 2, FALSE), "Units not found")) -> 0.15 | M46: =B46*K46 -> 1209 | N46: =IFERROR(VLOOKUP(D46, Product_Category!A:B, 2, FALSE), "Uncategorized") -> MCC | O46: =K46*1000 -> 8060 | P46: =L46*O46 -> 1209 | Q46: 2023 | R46: =IFERROR(VLOOKUP(G46,'SOURCE COMPANY'!A:B, 2, FALSE), "") -> CADILA HEALTHCARE | S46: =IFERROR(VLOOKUP(H46,'CUSTOMER NAME'!A:B, 2, FALSE), "") -> ALIDAC HEALTHCARE
A47: Myanmar | B47: 50 | C47: KGS | D47: COMPRECEL M101D | E47: 4.88 | F47: USD | G47: CADILA HEALTHCARE | H47: ALIDAC HEALTHCARE | I47: October | J47: =IF(F47="USD", E47, E47 * IFERROR(VLOOKUP(F47, EXCHANGE_RATE!A:B, 2, FALSE), "Currency not found")) -> 4.88 | K47: =ROUNDUP(J47,2) -> 4.88 | L47: =IF(C47="MTS", B47, B47 * IFERROR(VLOOKUP(C47, 'QTY_CONVERSIONS '!A:B, 2, FALSE), "Units not found")) -> 0.05 | M47: =B47*K47 -> 244 | N47: =IFERROR(VLOOKUP(D47, Product_Category!A:B, 2, FALSE), "Uncategorized") -> MCC | O47: =K47*1000 -> 4880 | P47: =L47*O47 -> 244 | Q47: 2023 | R47: =IFERROR(VLOOKUP(G47,'SOURCE COMPANY'!A:B, 2, FALSE), "") -> CADILA HEALTHCARE | S47: =IFERROR(VLOOKUP(H47,'CUSTOMER NAME'!A:B, 2, FALSE), "") -> ALIDAC HEALTHCARE
A48: Myanmar | B48: 50 | C48: KGS | D48: AVICEL PH102 | E48: 11.12 | F48: USD | G48: CADILA PHARMA | H48: ALIDAC HEALTHCARE | I48: August | J48: =IF(F48="USD", E48, E48 * IFERROR(VLOOKUP(F48, EXCHANGE_RATE!A:B, 2, FALSE), "Currency not found")) -> 11.12 | K48: =ROUNDUP(J48,2) -> 11.12 | L48: =IF(C48="MTS", B48, B48 * IFERROR(VLOOKUP(C48, 'QTY_CONVERSIONS '!A:B, 2, FALSE), "Units not found")) -> 0.05 | M48: =B48*K48 -> 556 | N48: =IFERROR(VLOOKUP(D48, Product_Category!A:B, 2, FALSE), "Uncategorized") -> MCC | O48: =K48*1000 -> 11120 | P48: =L48*O48 -> 556 | Q48: 2023 | R48: =IFERROR(VLOOKUP(G48,'SOURCE COMPANY'!A:B, 2, FALSE), "") -> CADILA HEALTHCARE | S48: =IFERROR(VLOOKUP(H48,'CUSTOMER NAME'!A:B, 2, FALSE), "") -> ALIDAC HEALTHCARE
A49: Myanmar | B49: 500 | C49: KGS | D49: MCC 102 RANQ | E49: 2.55 | F49: USD | G49: CADILA PHARMA | H49: ALIDAC HEALTHCARE | I49: August | J49: =IF(F49="USD", E49, E49 * IFERROR(VLOOKUP(F49, EXCHANGE_RATE!A:B, 2, FALSE), "Currency not found")) -> 2.55 | K49: =ROUNDUP(J49,2) -> 2.55 | L49: =IF(C49="MTS", B49, B49 * IFERROR(VLOOKUP(C49, 'QTY_CONVERSIONS '!A:B, 2, FALSE), "Units not found")) -> 0.5 | M49: =B49*K49 -> 1275 | N49: =IFERROR(VLOOKUP(D49, Product_Category!A:B, 2, FALSE), "Uncategorized") -> MCC | O49: =K49*1000 -> 2550 | P49: =L49*O49 -> 1275 | Q49: 2023 | R49: =IFERROR(VLOOKUP(G49,'SOURCE COMPANY'!A:B, 2, FALSE), "") -> CADILA HEALTHCARE | S49: =IFERROR(VLOOKUP(H49,'CUSTOMER NAME'!A:B, 2, FALSE), "") -> ALIDAC HEALTHCARE
A50: Myanmar | B50: 100 | C50: KGS | D50: 101 COMPRECEL | E50: 4.72 | F50: USD | G50: CADILA PHARMA | H50: ALIDAC HEALTHCARE | I50: August | J50: =IF(F50="USD", E50, E50 * IFERROR(VLOOKUP(F50, EXCHANGE_RATE!A:B, 2, FALSE), "Currency not found")) -> 4.72 | K50: =ROUNDUP(J50,2) -> 4.72 | L50: =IF(C50="MTS", B50, B50 * IFERROR(VLOOKUP(C50, 'QTY_CONVERSIONS '!A:B, 2, FALSE), "Units not found")) -> 0.1 | M50: =B50*K50 -> 472 | N50: =IFERROR(VLOOKUP(D50, Product_Category!A:B, 2, FALSE), "Uncategorized") -> MCC | O50: =K50*1000 -> 4720 | P50: =L50*O50 -> 472 | Q50: 2023 | R50: =IFERROR(VLOOKUP(G50,'SOURCE COMPANY'!A:B, 2, FALSE), "") -> CADILA HEALTHCARE | S50: =IFERROR(VLOOKUP(H50,'CUSTOMER NAME'!A:B, 2, FALSE), "") -> ALIDAC HEALTHCARE
... A59: Myanmar | B59: 150 | C59: KGS | D59: AVICEL PH 101 | E59: 10.74 | F59: USD | G59: CADILA PHARMA | H59: ALIDAC HEALTHCARE | I59: September | J59: =IF(F59="USD", E59, E59 * IFERROR(VLOOKUP(F59, EXCHANGE_RATE!A:B, 2, FALSE), "Currency not found")) -> 10.74 | K59: =ROUNDUP(J59,2) -> 10.74 | L59: =IF(C59="MTS", B59, B59 * IFERROR(VLOOKUP(C59, 'QTY_CONVERSIONS '!A:B, 2, FALSE), "Units not found")) -> 0.15 | M59: =B59*K59 -> 1611 | N59: =IFERROR(VLOOKUP(D59, Product_Category!A:B, 2, FALSE), "Uncategorized") -> MCC | O59: =K59*1000 -> 10740 | P59: =L59*O59 -> 1611 | Q59: 2023 | R59: =IFERROR(VLOOKUP(G59,'SOURCE COMPANY'!A:B, 2, FALSE), "") -> CADILA HEALTHCARE | S59: =IFERROR(VLOOKUP(H59,'CUSTOMER NAME'!A:B, 2, FALSE), "") -> ALIDAC HEALTHCARE
A60: Myanmar | B60: 100 | C60: KGS | D60: MCC PH EUR BP AVICEL PH102 | E60: 9.51 | F60: USD | G60: ZYDUS | H60: ALIDAC HEALTHCARE | I60: =I59 -> September | J60: =IF(F60="USD", E60, E60 * IFERROR(VLOOKUP(F60, EXCHANGE_RATE!A:B, 2, FALSE), "Currency not found")) -> 9.51 | K60: =ROUNDUP(J60,2) -> 9.51 | L60: =IF(C60="MTS", B60, B60 * IFERROR(VLOOKUP(C60, 'QTY_CONVERSIONS '!A:B, 2, FALSE), "Units not found")) -> 0.1 | M60: =B60*K60 -> 951 | N60: =IFERROR(VLOOKUP(D60, Product_Category!A:B, 2, FALSE), "Uncategorized") -> MCC | O60: =K60*1000 -> 9510 | P60: =L60*O60 -> 951 | Q60: 2023 | R60: =IFERROR(VLOOKUP(G60,'SOURCE COMPANY'!A:B, 2, FALSE), "") -> ZYDUS | S60: =IFERROR(VLOOKUP(H60,'CUSTOMER NAME'!A:B, 2, FALSE), "") -> ALIDAC HEALTHCARE
A61: Myanmar | B61: 200 | C61: KGS | D61: MCC AVICEL PH 101 | E61: 9.18 | F61: USD | G61: ZYDUS | H61: ALIDAC HEALTHCARE | I61: =I60 -> September | J61: =IF(F61="USD", E61, E61 * IFERROR(VLOOKUP(F61, EXCHANGE_RATE!A:B, 2, FALSE), "Currency not found")) -> 9.18 | K61: =ROUNDUP(J61,2) -> 9.18 | L61: =IF(C61="MTS", B61, B61 * IFERROR(VLOOKUP(C61, 'QTY_CONVERSIONS '!A:B, 2, FALSE), "Units not found")) -> 0.2 | M61: =B61*K61 -> 1836 | N61: =IFERROR(VLOOKUP(D61, Product_Category!A:B, 2, FALSE), "Uncategorized") -> MCC | O61: =K61*1000 -> 9180 | P61: =L61*O61 -> 1836 | Q61: 2023 | R61: =IFERROR(VLOOKUP(G61,'SOURCE COMPANY'!A:B, 2, FALSE), "") -> ZYDUS | S61: =IFERROR(VLOOKUP(H61,'CUSTOMER NAME'!A:B, 2, FALSE), "") -> ALIDAC HEALTHCARE
A62: Myanmar | B62: 250 | C62: KGS | D62: MCC AVICEL PH 101 | E62: 9.38 | F62: USD | G62: ZYDUS | H62: ALIDAC HEALTHCARE | I62: =I61 -> September | J62: =IF(F62="USD", E62, E62 * IFERROR(VLOOKUP(F62, EXCHANGE_RATE!A:B, 2, FALSE), "Currency not found")) -> 9.38 | K62: =ROUNDUP(J62,2) -> 9.38 | L62: =IF(C62="MTS", B62, B62 * IFERROR(VLOOKUP(C62, 'QTY_CONVERSIONS '!A:B, 2, FALSE), "Units not found")) -> 0.25 | M62: =B62*K62 -> 2345 | N62: =IFERROR(VLOOKUP(D62, Product_Category!A:B, 2, FALSE), "Uncategorized") -> MCC | O62: =K62*1000 -> 9380 | P62: =L62*O62 -> 2345 | Q62: 2023 | R62: =IFERROR(VLOOKUP(G62,'SOURCE COMPANY'!A:B, 2, FALSE), "") -> ZYDUS | S62: =IFERROR(VLOOKUP(H62,'CUSTOMER NAME'!A:B, 2, FALSE), "") -> ALIDAC HEALTHCARE
A63: Myanmar | B63: 300 | C63: KGS | D63: MAGNESIUM STEARATE | E63: 2.89 | F63: USD | G63: ZYDUS | H63: ALIDAC HEALTHCARE | I63: August | J63: =IF(F63="USD", E63, E63 * IFERROR(VLOOKUP(F63, EXCHANGE_RATE!A:B, 2, FALSE), "Currency not found")) -> 2.89 | K63: =ROUNDUP(J63,2) -> 2.89 | L63: =IF(C63="MTS", B63, B63 * IFERROR(VLOOKUP(C63, 'QTY_CONVERSIONS '!A:B, 2, FALSE), "Units not found")) -> 0.3 | M63: =B63*K63 -> 867 | N63: =IFERROR(VLOOKUP(D63, Product_Category!A:B, 2, FALSE), "Uncategorized") -> MAGNESIUM STEARATE | O63: =K63*1000 -> 2890 | P63: =L63*O63 -> 867 | Q63: 2023 | R63: =IFERROR(VLOOKUP(G63,'SOURCE COMPANY'!A:B, 2, FALSE), "") -> ZYDUS | S63: =IFERROR(VLOOKUP(H63,'CUSTOMER NAME'!A:B, 2, FALSE), "") -> ALIDAC HEALTHCARE
A64: Myanmar | B64: 100 | C64: KGS | D64: MCC | E64: 8.04 | F64: USD | G64: ZYDUS | H64: ALIDAC HEALTHCARE | I64: December | J64: =IF(F64="USD", E64, E64 * IFERROR(VLOOKUP(F64, EXCHANGE_RATE!A:B, 2, FALSE), "Currency not found")) -> 8.04 | K64: =ROUNDUP(J64,2) -> 8.04 | L64: =IF(C64="MTS", B64, B64 * IFERROR(VLOOKUP(C64, 'QTY_CONVERSIONS '!A:B, 2, FALSE), "Units not found")) -> 0.1 | M64: =B64*K64 -> 804 | N64: =IFERROR(VLOOKUP(D64, Product_Category!A:B, 2, FALSE), "Uncategorized") -> MCC | O64: =K64*1000 -> 8040 | P64: =L64*O64 -> 804 | Q64: 2023 | R64: =IFERROR(VLOOKUP(G64,'SOURCE COMPANY'!A:B, 2, FALSE), "") -> ZYDUS | S64: =IFERROR(VLOOKUP(H64,'CUSTOMER NAME'!A:B, 2, FALSE), "") -> ALIDAC HEALTHCARE
A65: Myanmar | B65: 1000 | C65: KGS | D65: MCC | E65: 2.52 | F65: USD | G65: ZYDUS | H65: ALIDAC HEALTHCARE | I65: December | J65: =IF(F65="USD", E65, E65 * IFERROR(VLOOKUP(F65, EXCHANGE_RATE!A:B, 2, FALSE), "Currency not found")) -> 2.52 | K65: =ROUNDUP(J65,2) -> 2.52 | L65: =IF(C65="MTS", B65, B65 * IFERROR(VLOOKUP(C65, 'QTY_CONVERSIONS '!A:B, 2, FALSE), "Units not found")) -> 1 | M65: =B65*K65 -> 2520 | N65: =IFERROR(VLOOKUP(D65, Product_Category!A:B, 2, FALSE), "Uncategorized") -> MCC | O65: =K65*1000 -> 2520 | P65: =L65*O65 -> 2520 | Q65: 2023 | R65: =IFERROR(VLOOKUP(G65,'SOURCE COMPANY'!A:B, 2, FALSE), "") -> ZYDUS | S65: =IFERROR(VLOOKUP(H65,'CUSTOMER NAME'!A:B, 2, FALSE), "") -> ALIDAC HEALTHCARE
A66: Nepal | B66: 100 | C66: KGS | D66: SSG | E66: 1.68 | F66: USD | G66: JAYANA PHARMA | H66: ALIVE PHARMA | I66: October | J66: =IF(F66="USD", E66, E66 * IFERROR(VLOOKUP(F66, EXCHANGE_RATE!A:B, 2, FALSE), "Currency not found")) -> 1.68 | K66: =ROUNDUP(J66,2) -> 1.68 | L66: =IF(C66="MTS", B66, B66 * IFERROR(VLOOKUP(C66, 'QTY_CONVERSIONS '!A:B, 2, FALSE), "Units not found")) -> 0.1 | M66: =B66*K66 -> 168 | N66: =IFERROR(VLOOKUP(D66, Product_Category!A:B, 2, FALSE), "Uncategorized") -> SSG | O66: =K66*1000 -> 1680 | P66: =L66*O66 -> 168 | Q66: 2023 | R66: =IFERROR(VLOOKUP(G66,'SOURCE COMPANY'!A:B, 2, FALSE), "") -> JAYANA PHARMA | S66: =IFERROR(VLOOKUP(H66,'CUSTOMER NAME'!A:B, 2, FALSE), "") -> ALIVE PHARMA
A67: Nepal | B67: 100 | C67: KGS | D67: SODIUM CCM | E67: 3 | F67: USD | G67: JAYANA PHARMA | H67: ALIVE PHARMA | I67: October | J67: =IF(F67="USD", E67, E67 * IFERROR(VLOOKUP(F67, EXCHANGE_RATE!A:B, 2, FALSE), "Currency not found")) -> 3 | K67: =ROUNDUP(J67,2) -> 3 | L67: =IF(C67="MTS", B67, B67 * IFERROR(VLOOKUP(C67, 'QTY_CONVERSIONS '!A:B, 2, FALSE), "Units not found")) -> 0.1 | M67: =B67*K67 -> 300 | N67: =IFERROR(VLOOKUP(D67, Product_Category!A:B, 2, FALSE), "Uncategorized") -> CROSCARMELLOSE SODIUM | O67: =K67*1000 -> 3000 | P67: =L67*O67 -> 300 | Q67: 2023 | R67: =IFERROR(VLOOKUP(G67,'SOURCE COMPANY'!A:B, 2, FALSE), "") -> JAYANA PHARMA | S67: =IFERROR(VLOOKUP(H67,'CUSTOMER NAME'!A:B, 2, FALSE), "") -> ALIVE PHARMA
A68: Nepal | B68: 100 | C68: KGS | D68: MCCP 102 | E68: 1.96 | F68: USD | G68: ORIENT PHARMA | H68: ALIVE PHARMA | I68: December | J68: =IF(F68="USD", E68, E68 * IFERROR(VLOOKUP(F68, EXCHANGE_RATE!A:B, 2, FALSE), "Currency not found")) -> 1.96 | K68: =ROUNDUP(J68,2) -> 1.96 | L68: =IF(C68="MTS", B68, B68 * IFERROR(VLOOKUP(C68, 'QTY_CONVERSIONS '!A:B, 2, FALSE), "Units not found")) -> 0.1 | M68: =B68*K68 -> 196 | N68: =IFERROR(VLOOKUP(D68, Product_Category!A:B, 2, FALSE), "Uncategorized") -> MCC | O68: =K68*1000 -> 1960 | P68: =L68*O68 -> 196 | Q68: 2023 | R68: =IFERROR(VLOOKUP(G68,'SOURCE COMPANY'!A:B, 2, FALSE), "") -> ORIENT PHARMA | S68: =IFERROR(VLOOKUP(H68,'CUSTOMER NAME'!A:B, 2, FALSE), "") -> ALIVE PHARMA
A69: Nepal | B69: 700 | C69: KGS | D69: MCCP 101 | E69: 1.94 | F69: USD | G69: ORIENT PHARMA | H69: ALIVE PHARMA | I69: December | J69: =IF(F69="USD", E69, E69 * IFERROR(VLOOKUP(F69, EXCHANGE_RATE!A:B, 2, FALSE), "Currency not found")) -> 1.94 | K69: =ROUNDUP(J69,2) -> 1.94 | L69: =IF(C69="MTS", B69, B69 * IFERROR(VLOOKUP(C69, 'QTY_CONVERSIONS '!A:B, 2, FALSE), "Units not found")) -> 0.7 | M69: =B69*K69 -> 1358 | N69: =IFERROR(VLOOKUP(D69, Product_Category!A:B, 2, FALSE), "Uncategorized") -> MCC | O69: =K69*1000 -> 1940 | P69: =L69*O69 -> 1358 | Q69: 2023 | R69: =IFERROR(VLOOKUP(G69,'SOURCE COMPANY'!A:B, 2, FALSE), "") -> ORIENT PHARMA | S69: =IFERROR(VLOOKUP(H69,'CUSTOMER NAME'!A:B, 2, FALSE), "") -> ALIVE PHARMA
A70: Nepal | B70: 75 | C70: KGS | D70: SSG | E70: 1.76 | F70: USD | G70: ORIENT PHARMA | H70: ALIVE PHARMA | I70: October | J70: =IF(F70="USD", E70, E70 * IFERROR(VLOOKUP(F70, EXCHANGE_RATE!A:B, 2, FALSE), "Currency not found")) -> 1.76 | K70: =ROUNDUP(J70,2) -> 1.76 | L70: =IF(C70="MTS", B70, B70 * IFERROR(VLOOKUP(C70, 'QTY_CONVERSIONS '!A:B, 2, FALSE), "Units not found")) -> 0.075 | M70: =B70*K70 -> 132 | N70: =IFERROR(VLOOKUP(D70, Product_Category!A:B, 2, FALSE), "Uncategorized") -> SSG | O70: =K70*1000 -> 1760 | P70: =L70*O70 -> 132 | Q70: 2023 | R70: =IFERROR(VLOOKUP(G70,'SOURCE COMPANY'!A:B, 2, FALSE), "") -> ORIENT PHARMA | S70: =IFERROR(VLOOKUP(H70,'CUSTOMER NAME'!A:B, 2, FALSE), "") -> ALIVE PHARMA
A71: Nepal | B71: 350 | C71: KGS | D71: MICCEL-101 | E71: 1.91 | F71: USD | G71: ORIENT PHARMA | H71: ALIVE PHARMA | I71: September | J71: =IF(F71="USD", E71, E71 * IFERROR(VLOOKUP(F71, EXCHANGE_RATE!A:B, 2, FALSE), "Currency not found")) -> 1.91 | K71: =ROUNDUP(J71,2) -> 1.91 | L71: =IF(C71="MTS", B71, B71 * IFERROR(VLOOKUP(C71, 'QTY_CONVERSIONS '!A:B, 2, FALSE), "Units not found")) -> 0.35 | M71: =B71*K71 -> 668.5 | N71: =IFERROR(VLOOKUP(D71, Product_Category!A:B, 2, FALSE), "Uncategorized") -> MCC | O71: =K71*1000 -> 1910 | P71: =L71*O71 -> 668.5 | Q71: 2023 | R71: =IFERROR(VLOOKUP(G71,'SOURCE COMPANY'!A:B, 2, FALSE), "") -> ORIENT PHARMA | S71: =IFERROR(VLOOKUP(H71,'CUSTOMER NAME'!A:B, 2, FALSE), "") -> ALIVE PHARMA
A72: Nepal | B72: 50 | C72: KGS | D72: COMPRECEL 102 | E72: 6.48 | F72: USD | G72: SDM AGENCIES | H72: ALIVE PHARMA | I72: October | J72: =IF(F72="USD", E72, E72 * IFERROR(VLOOKUP(F72, EXCHANGE_RATE!A:B, 2, FALSE), "Currency not found")) -> 6.48 | K72: =ROUNDUP(J72,2) -> 6.48 | L72: =IF(C72="MTS", B72, B72 * IFERROR(VLOOKUP(C72, 'QTY_CONVERSIONS '!A:B, 2, FALSE), "Units not found")) -> 0.05 | M72: =B72*K72 -> 324 | N72: =IFERROR(VLOOKUP(D72, Product_Category!A:B, 2, FALSE), "Uncategorized") -> MCC | O72: =K72*1000 -> 6480 | P72: =L72*O72 -> 324 | Q72: 2023 | R72: =IFERROR(VLOOKUP(G72,'SOURCE COMPANY'!A:B, 2, FALSE), "") -> SDM AGENCIES | S72: =IFERROR(VLOOKUP(H72,'CUSTOMER NAME'!A:B, 2, FALSE), "") -> ALIVE PHARMA
A73: Nepal | B73: 100 | C73: KGS | D73: CCS IP | E73: 250 | F73: INR | G73: SUDARSHAN TRADING | H73: ALIVE PHARMA | I73: =I72 -> October | J73: =IF(F73="USD", E73, E73 * IFERROR(VLOOKUP(F73, EXCHANGE_RATE!A:B, 2, FALSE), "Currency not found")) -> 3 | K73: =ROUNDUP(J73,2) -> 3 | L73: =IF(C73="MTS", B73, B73 * IFERROR(VLOOKUP(C73, 'QTY_CONVERSIONS '!A:B, 2, FALSE), "Units not found")) -> 0.1 | M73: =B73*K73 -> 300 | N73: =IFERROR(VLOOKUP(D73, Product_Category!A:B, 2, FALSE), "Uncategorized") -> CROSCARMELLOSE SODIUM | O73: =K73*1000 -> 3000 | P73: =L73*O73 -> 300 | Q73: 2023 | R73: =IFERROR(VLOOKUP(G73,'SOURCE COMPANY'!A:B, 2, FALSE), "") -> SUDARSHAN TRADING | S73: =IFERROR(VLOOKUP(H73,'CUSTOMER NAME'!A:B, 2, FALSE), "") -> ALIVE PHARMA
A74: MALAYSIA | B74: 50 | C74: KGS | D74: MAGNESIUM STEARATE IP | E74: 29.5 | F74: USD | G74: SUDARSHAN TRADING | H74: ALIVE PHARMA | I74: =I73 -> October | J74: =IF(F74="USD", E74, E74 * IFERROR(VLOOKUP(F74, EXCHANGE_RATE!A:B, 2, FALSE), "Currency not found")) -> 29.5 | K74: =ROUNDUP(J74,2) -> 29.5 | L74: =IF(C74="MTS", B74, B74 * IFERROR(VLOOKUP(C74, 'QTY_CONVERSIONS '!A:B, 2, FALSE), "Units not found")) -> 0.05 | M74: =B74*K74 -> 1475 | N74: =IFERROR(VLOOKUP(D74, Product_Category!A:B, 2, FALSE), "Uncategorized") -> MAGNESIUM STEARATE | O74: =K74*1000 -> 29500 | P74: =L74*O74 -> 1475 | Q74: 2023 | R74: =IFERROR(VLOOKUP(G74,'SOURCE COMPANY'!A:B, 2, FALSE), "") -> SUDARSHAN TRADING | S74: =IFERROR(VLOOKUP(H74,'CUSTOMER NAME'!A:B, 2, FALSE), "") -> ALIVE PHARMA
A75: Nepal | B75: 200 | C75: KGS | D75: MCCP PH 102 | E75: 1.94 | F75: USD | G75: SUDARSHAN TRADING | H75: ALIVE PHARMA | I75: September | J75: =IF(F75="USD", E75, E75 * IFERROR(VLOOKUP(F75, EXCHANGE_RATE!A:B, 2, FALSE), "Currency not found")) -> 1.94 | K75: =ROUNDUP(J75,2) -> 1.94 | L75: =IF(C75="MTS", B75, B75 * IFERROR(VLOOKUP(C75, 'QTY_CONVERSIONS '!A:B, 2, FALSE), "Units not found")) -> 0.2 | M75: =B75*K75 -> 388 | N75: =IFERROR(VLOOKUP(D75, Product_Category!A:B, 2, FALSE), "Uncategorized") -> MCC | O75: =K75*1000 -> 1940 | P75: =L75*O75 -> 388 | Q75: 2023 | R75: =IFERROR(VLOOKUP(G75,'SOURCE COMPANY'!A:B, 2, FALSE), "") -> SUDARSHAN TRADING | S75: =IFERROR(VLOOKUP(H75,'CUSTOMER NAME'!A:B, 2, FALSE), "") -> ALIVE PHARMA
A76: Hungary | B76: 56.7 | C76: KGS | D76: MAGNESIUM STEARATE | E76: 7.95996 | F76: USD | G76: SUN PHARMA | H76: ALKALOIDA | I76: August | J76: =IF(F76="USD", E76, E76 * IFERROR(VLOOKUP(F76, EXCHANGE_RATE!A:B, 2, FALSE), "Currency not found")) -> 7.95996 | K76: =ROUNDUP(J76,2) -> 7.96 | L76: =IF(C76="MTS", B76, B76 * IFERROR(VLOOKUP(C76, 'QTY_CONVERSIONS '!A:B, 2, FALSE), "Units not found")) -> 0.0567 | M76: =B76*K76 -> 451.332 | N76: =IFERROR(VLOOKUP(D76, Product_Category!A:B, 2, FALSE), "Uncategorized") -> MAGNESIUM STEARATE | O76: =K76*1000 -> 7960 | P76: =L76*O76 -> 451.332 | Q76: 2023 | R76: =IFERROR(VLOOKUP(G76,'SOURCE COMPANY'!A:B, 2, FALSE), "") -> SUN PHARMA | S76: =IFERROR(VLOOKUP(H76,'CUSTOMER NAME'!A:B, 2, FALSE), "") -> ALKALOIDA
A77: Hungary | B77: 640 | C77: KGS | D77: MCC | E77: 4.83 | F77: USD | G77: SUN PHARMA | H77: ALKALOIDA | I77: August | J77: =IF(F77="USD", E77, E77 * IFERROR(VLOOKUP(F77, EXCHANGE_RATE!A:B, 2, FALSE), "Currency not found")) -> 4.83 | K77: =ROUNDUP(J77,2) -> 4.83 | L77: =IF(C77="MTS", B77, B77 * IFERROR(VLOOKUP(C77, 'QTY_CONVERSIONS '!A:B, 2, FALSE), "Units not found")) -> 0.64 | M77: =B77*K77 -> 3091.2 | N77: =IFERROR(VLOOKUP(D77, Product_Category!A:B, 2, FALSE), "Uncategorized") -> MCC | O77: =K77*1000 -> 4830 | P77: =L77*O77 -> 3091.2 | Q77: 2023 | R77: =IFERROR(VLOOKUP(G77,'SOURCE COMPANY'!A:B, 2, FALSE), "") -> SUN PHARMA | S77: =IFERROR(VLOOKUP(H77,'CUSTOMER NAME'!A:B, 2, FALSE), "") -> ALKALOIDA
A78: Hungary | B78: 50 | C78: KGS | D78: SSG | E78: 16.34 | F78: USD | G78: SUN PHARMA | H78: ALKALOIDA | I78: =I77 -> August | J78: =IF(F78="USD", E78, E78 * IFERROR(VLOOKUP(F78, EXCHANGE_RATE!A:B, 2, FALSE), "Currency not found")) -> 16.34 | K78: =ROUNDUP(J78,2) -> 16.34 | L78: =IF(C78="MTS", B78, B78 * IFERROR(VLOOKUP(C78, 'QTY_CONVERSIONS '!A:B, 2, FALSE), "Units not found")) -> 0.05 | M78: =B78*K78 -> 817 | N78: =IFERROR(VLOOKUP(D78, Product_Category!A:B, 2, FALSE), "Uncategorized") -> SSG | O78: =K78*1000 -> 16340 | P78: =L78*O78 -> 817 | Q78: 2023 | R78: =IFERROR(VLOOKUP(G78,'SOURCE COMPANY'!A:B, 2, FALSE), "") -> SUN PHARMA | S78: =IFERROR(VLOOKUP(H78,'CUSTOMER NAME'!A:B, 2, FALSE), "") -> ALKALOIDA
A79: Hungary | B79: 300 | C79: KGS | D79: SODIUM CCM | E79: 32 | F79: USD | G79: SUN PHARMA | H79: ALKALOIDA | I79: October | J79: =IF(F79="USD", E79, E79 * IFERROR(VLOOKUP(F79, EXCHANGE_RATE!A:B, 2, FALSE), "Currency not found")) -> 32 | K79: =ROUNDUP(J79,2) -> 32 | L79: =IF(C79="MTS", B79, B79 * IFERROR(VLOOKUP(C79, 'QTY_CONVERSIONS '!A:B, 2, FALSE), "Units not found")) -> 0.3 | M79: =B79*K79 -> 9600 | N79: =IFERROR(VLOOKUP(D79, Product_Category!A:B, 2, FALSE), "Uncategorized") -> CROSCARMELLOSE SODIUM | O79: =K79*1000 -> 32000 | P79: =L79*O79 -> 9600 | Q79: 2023 | R79: =IFERROR(VLOOKUP(G79,'SOURCE COMPANY'!A:B, 2, FALSE), "") -> SUN PHARMA | S79: =IFERROR(VLOOKUP(H79,'CUSTOMER NAME'!A:B, 2, FALSE), "") -> ALKALOIDA
A80: Hungary | B80: 500 | C80: KGS | D80: SODIUM CCM | E80: 32 | F80: USD | G80: SUN PHARMA | H80: ALKALOIDA | I80: October | J80: =IF(F80="USD", E80, E80 * IFERROR(VLOOKUP(F80, EXCHANGE_RATE!A:B, 2, FALSE), "Currency not found")) -> 32 | K80: =ROUNDUP(J80,2) -> 32 | L80: =IF(C80="MTS", B80, B80 * IFERROR(VLOOKUP(C80, 'QTY_CONVERSIONS '!A:B, 2, FALSE), "Units not found")) -> 0.5 | M80: =B80*K80 -> 16000 | N80: =IFERROR(VLOOKUP(D80, Product_Category!A:B, 2, FALSE), "Uncategorized") -> CROSCARMELLOSE SODIUM | O80: =K80*1000 -> 32000 | P80: =L80*O80 -> 16000 | Q80: 2023 | R80: =IFERROR(VLOOKUP(G80,'SOURCE COMPANY'!A:B, 2, FALSE), "") -> SUN PHARMA | S80: =IFERROR(VLOOKUP(H80,'CUSTOMER NAME'!A:B, 2, FALSE), "") -> ALKALOIDA
A81: Hungary | B81: 56.7 | C81: KGS | D81: Magnesium Stearate | E81: 35.77 | F81: USD | G81: SUN PHARMA | H81: ALKALOIDA | I81: September | J81: =IF(F81="USD", E81, E81 * IFERROR(VLOOKUP(F81, EXCHANGE_RATE!A:B, 2, FALSE), "Currency not found")) -> 35.77 | K81: =ROUNDUP(J81,2) -> 35.77 | L81: =IF(C81="MTS", B81, B81 * IFERROR(VLOOKUP(C81, 'QTY_CONVERSIONS '!A:B, 2, FALSE), "Units not found")) -> 0.0567 | M81: =B81*K81 -> 2028.159 | N81: =IFERROR(VLOOKUP(D81, Product_Category!A:B, 2, FALSE), "Uncategorized") -> MAGNESIUM STEARATE | O81: =K81*1000 -> 35770 | P81: =L81*O81 -> 2028.159 | Q81: 2023 | R81: =IFERROR(VLOOKUP(G81,'SOURCE COMPANY'!A:B, 2, FALSE), "") -> SUN PHARMA | S81: =IFERROR(VLOOKUP(H81,'CUSTOMER NAME'!A:B, 2, FALSE), "") -> ALKALOIDA
A82: Nepal | B82: 200 | C82: KGS | D82: MCC | E82: =350*0.012 -> 4.2 | F82: USD | G82: EMBELLISH PHARMA | H82: ALLIANCE PHARMA | I82: December | J82: =IF(F82="USD", E82, E82 * IFERROR(VLOOKUP(F82, EXCHANGE_RATE!A:B, 2, FALSE), "Currency not found")) -> 4.2 | K82: =ROUNDUP(J82,2) -> 4.2 | L82: =IF(C82="MTS", B82, B82 * IFERROR(VLOOKUP(C82, 'QTY_CONVERSIONS '!A:B, 2, FALSE), "Units not found")) -> 0.2 | M82: =B82*K82 -> 840 | N82: =IFERROR(VLOOKUP(D82, Product_Category!A:B, 2, FALSE), "Uncategorized") -> MCC | O82: =K82*1000 -> 4200 | P82: =L82*O82 -> 840 | Q82: 2023 | R82: =IFERROR(VLOOKUP(G82,'SOURCE COMPANY'!A:B, 2, FALSE), "") -> EMBELLISH PHARMA | S82: =IFERROR(VLOOKUP(H82,'CUSTOMER NAME'!A:B, 2, FALSE), "") -> ALLIANCE PHARMA
A83: Nepal | B83: 125 | C83: KGS | D83: MCC | E83: 4.22 | F83: USD | G83: EMBELLISH PHARMA | H83: ALLIANCE PHARMA | I83: October | J83: =IF(F83="USD", E83, E83 * IFERROR(VLOOKUP(F83, EXCHANGE_RATE!A:B, 2, FALSE), "Currency not found")) -> 4.22 | K83: =ROUNDUP(J83,2) -> 4.22 | L83: =IF(C83="MTS", B83, B83 * IFERROR(VLOOKUP(C83, 'QTY_CONVERSIONS '!A:B, 2, FALSE), "Units not found")) -> 0.125 | M83: =B83*K83 -> 527.5 | N83: =IFERROR(VLOOKUP(D83, Product_Category!A:B, 2, FALSE), "Uncategorized") -> MCC | O83: =K83*1000 -> 4220 | P83: =L83*O83 -> 527.5 | Q83: 2023 | R83: =IFERROR(VLOOKUP(G83,'SOURCE COMPANY'!A:B, 2, FALSE), "") -> EMBELLISH PHARMA | S83: =IFERROR(VLOOKUP(H83,'CUSTOMER NAME'!A:B, 2, FALSE), "") -> ALLIANCE PHARMA
A84: Nepal | B84: 100 | C84: KGS | D84: CCS | E84: 220 | F84: INR | G84: PINGAKSH PHARMA | H84: ALLIANCE PHARMA | I84: =I83 -> October | J84: =IF(F84="USD", E84, E84 * IFERROR(VLOOKUP(F84, EXCHANGE_RATE!A:B, 2, FALSE), "Currency not found")) -> 2.64 | K84: =ROUNDUP(J84,2) -> 2.64 | L84: =IF(C84="MTS", B84, B84 * IFERROR(VLOOKUP(C84, 'QTY_CONVERSIONS '!A:B, 2, FALSE), "Units not found")) -> 0.1 | M84: =B84*K84 -> 264 | N84: =IFERROR(VLOOKUP(D84, Product_Category!A:B, 2, FALSE), "Uncategorized") -> CROSCARMELLOSE SODIUM | O84: =K84*1000 -> 2640 | P84: =L84*O84 -> 264 | Q84: 2023 | R84: =IFERROR(VLOOKUP(G84,'SOURCE COMPANY'!A:B, 2, FALSE), "") -> PINGAKSH PHARMA | S84: =IFERROR(VLOOKUP(H84,'CUSTOMER NAME'!A:B, 2, FALSE), "") -> ALLIANCE PHARMA
A85: Nepal | B85: 50 | C85: KGS | D85: MAGNESIUM STEARATE IP | E85: 220 | F85: INR | G85: PINGAKSH PHARMA | H85: ALLIANCE PHARMA | I85: =I84 -> October | J85: =IF(F85="USD", E85, E85 * IFERROR(VLOOKUP(F85, EXCHANGE_RATE!A:B, 2, FALSE), "Currency not found")) -> 2.64 | K85: =ROUNDUP(J85,2) -> 2.64 | L85: =IF(C85="MTS", B85, B85 * IFERROR(VLOOKUP(C85, 'QTY_CONVERSIONS '!A:B, 2, FALSE), "Units not found")) -> 0.05 | M85: =B85*K85 -> 132 | N85: =IFERROR(VLOOKUP(D85, Product_Category!A:B, 2, FALSE), "Uncategorized") -> MAGNESIUM STEARATE | O85: =K85*1000 -> 2640 | P85: =L85*O85 -> 132 | Q85: 2023 | R85: =IFERROR(VLOOKUP(G85,'SOURCE COMPANY'!A:B, 2, FALSE), "") -> PINGAKSH PHARMA | S85: =IFERROR(VLOOKUP(H85,'CUSTOMER NAME'!A:B, 2, FALSE), "") -> ALLIANCE PHARMA
A86: Nepal | B86: 500 | C86: KGS | D86: MCC IP | E86: 166 | F86: INR | G86: PINGAKSH PHARMA | H86: ALLIANCE PHARMA | I86: =I85 -> October | J86: =IF(F86="USD", E86, E86 * IFERROR(VLOOKUP(F86, EXCHANGE_RATE!A:B, 2, FALSE), "Currency not found")) -> 1.992 | K86: =ROUNDUP(J86,2) -> 2 | L86: =IF(C86="MTS", B86, B86 * IFERROR(VLOOKUP(C86, 'QTY_CONVERSIONS '!A:B, 2, FALSE), "Units not found")) -> 0.5 | M86: =B86*K86 -> 1000 | N86: =IFERROR(VLOOKUP(D86, Product_Category!A:B, 2, FALSE), "Uncategorized") -> MCC | O86: =K86*1000 -> 2000 | P86: =L86*O86 -> 1000 | Q86: 2023 | R86: =IFERROR(VLOOKUP(G86,'SOURCE COMPANY'!A:B, 2, FALSE), "") -> PINGAKSH PHARMA | S86: =IFERROR(VLOOKUP(H86,'CUSTOMER NAME'!A:B, 2, FALSE), "") -> ALLIANCE PHARMA
A87: Australia | B87: 9000 | C87: KGS | D87: FLOCEL 101 | E87: 2.4 | F87: USD | G87: JRS PHARMA | H87: ALPHA PHARM | I87: December | J87: =IF(F87="USD", E87, E87 * IFERROR(VLOOKUP(F87, EXCHANGE_RATE!A:B, 2, FALSE), "Currency not found")) -> 2.4 | K87: =ROUNDUP(J87,2) -> 2.4 | L87: =IF(C87="MTS", B87, B87 * IFERROR(VLOOKUP(C87, 'QTY_CONVERSIONS '!A:B, 2, FALSE), "Units not found")) -> 9 | M87: =B87*K87 -> 21600 | N87: =IFERROR(VLOOKUP(D87, Product_Category!A:B, 2, FALSE), "Uncategorized") -> MCC | O87: =K87*1000 -> 2400 | P87: =L87*O87 -> 21600 | Q87: 2023 | R87: =IFERROR(VLOOKUP(G87,'SOURCE COMPANY'!A:B, 2, FALSE), "") -> JRS PHARMA | S87: =IFERROR(VLOOKUP(H87,'CUSTOMER NAME'!A:B, 2, FALSE), "") -> ALPHA PHARM
A88: Australia | B88: 1500 | C88: KGS | D88: FLOCEL 101 | E88: 5 | F88: USD | G88: JRS PHARMA | H88: ALPHA PHARM | I88: October | J88: =IF(F88="USD", E88, E88 * IFERROR(VLOOKUP(F88, EXCHANGE_RATE!A:B, 2, FALSE), "Currency not found")) -> 5 | K88: =ROUNDUP(J88,2) -> 5 | L88: =IF(C88="MTS", B88, B88 * IFERROR(VLOOKUP(C88, 'QTY_CONVERSIONS '!A:B, 2, FALSE), "Units not found")) -> 1.5 | M88: =B88*K88 -> 7500 | N88: =IFERROR(VLOOKUP(D88, Product_Category!A:B, 2, FALSE), "Uncategorized") -> MCC | O88: =K88*1000 -> 5000 | P88: =L88*O88 -> 7500 | Q88: 2023 | R88: =IFERROR(VLOOKUP(G88,'SOURCE COMPANY'!A:B, 2, FALSE), "") -> JRS PHARMA | S88: =IFERROR(VLOOKUP(H88,'CUSTOMER NAME'!A:B, 2, FALSE), "") -> ALPHA PHARM
A89: Australia | B89: 1500 | C89: KGS | D89: FLOCEL 102 | E89: 2 | F89: USD | G89: JRS PHARMA | H89: ALPHA PHARM | I89: September | J89: =IF(F89="USD", E89, E89 * IFERROR(VLOOKUP(F89, EXCHANGE_RATE!A:B, 2, FALSE), "Currency not found")) -> 2 | K89: =ROUNDUP(J89,2) -> 2 | L89: =IF(C89="MTS", B89, B89 * IFERROR(VLOOKUP(C89, 'QTY_CONVERSIONS '!A:B, 2, FALSE), "Units not found")) -> 1.5 | M89: =B89*K89 -> 3000 | N89: =IFERROR(VLOOKUP(D89, Product_Category!A:B, 2, FALSE), "Uncategorized") -> MCC | O89: =K89*1000 -> 2000 | P89: =L89*O89 -> 3000 | Q89: 2023 | R89: =IFERROR(VLOOKUP(G89,'SOURCE COMPANY'!A:B, 2, FALSE), "") -> JRS PHARMA | S89: =IFERROR(VLOOKUP(H89,'CUSTOMER NAME'!A:B, 2, FALSE), "") -> ALPHA PHARM
A90: Australia | B90: 500 | C90: KGS | D90: FLOCEL 102 | E90: 2 | F90: USD | G90: JRS PHARMA | H90: ALPHA PHARM | I90: September | J90: =IF(F90="USD", E90, E90 * IFERROR(VLOOKUP(F90, EXCHANGE_RATE!A:B, 2, FALSE), "Currency not found")) -> 2 | K90: =ROUNDUP(J90,2) -> 2 | L90: =IF(C90="MTS", B90, B90 * IFERROR(VLOOKUP(C90, 'QTY_CONVERSIONS '!A:B, 2, FALSE), "Units not found")) -> 0.5 | M90: =B90*K90 -> 1000 | N90: =IFERROR(VLOOKUP(D90, Product_Category!A:B, 2, FALSE), "Uncategorized") -> MCC | O90: =K90*1000 -> 2000 | P90: =L90*O90 -> 1000 | Q90: 2023 | R90: =IFERROR(VLOOKUP(G90,'SOURCE COMPANY'!A:B, 2, FALSE), "") -> JRS PHARMA | S90: =IFERROR(VLOOKUP(H90,'CUSTOMER NAME'!A:B, 2, FALSE), "") -> ALPHA PHARM
A91: Australia | B91: 100 | C91: KGS | D91: CCS VIVASOL | E91: 8.6698266 | F91: USD | G91: JRS PHARMA | H91: ALPHA PHARM | I91: =I90 -> September | J91: =IF(F91="USD", E91, E91 * IFERROR(VLOOKUP(F91, EXCHANGE_RATE!A:B, 2, FALSE), "Currency not found")) -> 8.6698266 | K91: =ROUNDUP(J91,2) -> 8.67 | L91: =IF(C91="MTS", B91, B91 * IFERROR(VLOOKUP(C91, 'QTY_CONVERSIONS '!A:B, 2, FALSE), "Units not found")) -> 0.1 | M91: =B91*K91 -> 867 | N91: =IFERROR(VLOOKUP(D91, Product_Category!A:B, 2, FALSE), "Uncategorized") -> CROSCARMELLOSE SODIUM | O91: =K91*1000 -> 8670 | P91: =L91*O91 -> 867 | Q91: 2023 | R91: =IFERROR(VLOOKUP(G91,'SOURCE COMPANY'!A:B, 2, FALSE), "") -> JRS PHARMA | S91: =IFERROR(VLOOKUP(H91,'CUSTOMER NAME'!A:B, 2, FALSE), "") -> ALPHA PHARM
A92: Australia | B92: 100 | C92: KGS | D92: MCCP FLOCEL | E92: 3.0299394 | F92: USD | G92: JRS PHARMA | H92: ALPHA PHARM | I92: =I91 -> September | J92: =IF(F92="USD", E92, E92 * IFERROR(VLOOKUP(F92, EXCHANGE_RATE!A:B, 2, FALSE), "Currency not found")) -> 3.0299394 | K92: =ROUNDUP(J92,2) -> 3.03 | L92: =IF(C92="MTS", B92, B92 * IFERROR(VLOOKUP(C92, 'QTY_CONVERSIONS '!A:B, 2, FALSE), "Units not found")) -> 0.1 | M92: =B92*K92 -> 303 | N92: =IFERROR(VLOOKUP(D92, Product_Category!A:B, 2, FALSE), "Uncategorized") -> MCC | O92: =K92*1000 -> 3030 | P92: =L92*O92 -> 303 | Q92: 2023 | R92: =IFERROR(VLOOKUP(G92,'SOURCE COMPANY'!A:B, 2, FALSE), "") -> JRS PHARMA | S92: =IFERROR(VLOOKUP(H92,'CUSTOMER NAME'!A:B, 2, FALSE), "") -> ALPHA PHARM
A93: Australia | B93: 9500 | C93: KGS | D93: MCCP FLOCEL | E93: 2.1199576 | F93: USD | G93: JRS PHARMA | H93: ALPHA PHARM | I93: =I92 -> September | J93: =IF(F93="USD", E93, E93 * IFERROR(VLOOKUP(F93, EXCHANGE_RATE!A:B, 2, FALSE), "Currency not found")) -> 2.1199576 | K93: =ROUNDUP(J93,2) -> 2.12 | L93: =IF(C93="MTS", B93, B93 * IFERROR(VLOOKUP(C93, 'QTY_CONVERSIONS '!A:B, 2, FALSE), "Units not found")) -> 9.5 | M93: =B93*K93 -> 20140 | N93: =IFERROR(VLOOKUP(D93, Product_Category!A:B, 2, FALSE), "Uncategorized") -> MCC | O93: =K93*1000 -> 2120 | P93: =L93*O93 -> 20140 | Q93: 2023 | R93: =IFERROR(VLOOKUP(G93,'SOURCE COMPANY'!A:B, 2, FALSE), "") -> JRS PHARMA | S93: =IFERROR(VLOOKUP(H93,'CUSTOMER NAME'!A:B, 2, FALSE), "") -> ALPHA PHARM
A94: Australia | B94: 100 | C94: KGS | D94: MCCP FLOCEL | E94: 2.1199576 | F94: USD | G94: JRS PHARMA | H94: ALPHA PHARM | I94: =I93 -> September | J94: =IF(F94="USD", E94, E94 * IFERROR(VLOOKUP(F94, EXCHANGE_RATE!A:B, 2, FALSE), "Currency not found")) -> 2.1199576 | K94: =ROUNDUP(J94,2) -> 2.12 | L94: =IF(C94="MTS", B94, B94 * IFERROR(VLOOKUP(C94, 'QTY_CONVERSIONS '!A:B, 2, FALSE), "Units not found")) -> 0.1 | M94: =B94*K94 -> 212 | N94: =IFERROR(VLOOKUP(D94, Product_Category!A:B, 2, FALSE), "Uncategorized") -> MCC | O94: =K94*1000 -> 2120 | P94: =L94*O94 -> 212 | Q94: 2023 | R94: =IFERROR(VLOOKUP(G94,'SOURCE COMPANY'!A:B, 2, FALSE), "") -> JRS PHARMA | S94: =IFERROR(VLOOKUP(H94,'CUSTOMER NAME'!A:B, 2, FALSE), "") -> ALPHA PHARM
A95: Australia | B95: 100 | C95: KGS | D95: MCCP FLOCEL | E95: 2.49995 | F95: USD | G95: JRS PHARMA | H95: ALPHA PHARM | I95: =I94 -> September | J95: =IF(F95="USD", E95, E95 * IFERROR(VLOOKUP(F95, EXCHANGE_RATE!A:B, 2, FALSE), "Currency not found")) -> 2.49995 | K95: =ROUNDUP(J95,2) -> 2.5 | L95: =IF(C95="MTS", B95, B95 * IFERROR(VLOOKUP(C95, 'QTY_CONVERSIONS '!A:B, 2, FALSE), "Units not found")) -> 0.1 | M95: =B95*K95 -> 250 | N95: =IFERROR(VLOOKUP(D95, Product_Category!A:B, 2, FALSE), "Uncategorized") -> MCC | O95: =K95*1000 -> 2500 | P95: =L95*O95 -> 250 | Q95: 2023 | R95: =IFERROR(VLOOKUP(G95,'SOURCE COMPANY'!A:B, 2, FALSE), "") -> JRS PHARMA | S95: =IFERROR(VLOOKUP(H95,'CUSTOMER NAME'!A:B, 2, FALSE), "") -> ALPHA PHARM
A96: Australia | B96: 20000 | C96: KGS | D96: MCC FLOCEL 102 | E96: 1.92 | F96: USD | G96: JRS PHARMA | H96: ALPHA PHARM | I96: =I95 -> September | J96: =IF(F96="USD", E96, E96 * IFERROR(VLOOKUP(F96, EXCHANGE_RATE!A:B, 2, FALSE), "Currency not found")) -> 1.92 | K96: =ROUNDUP(J96,2) -> 1.92 | L96: =IF(C96="MTS", B96, B96 * IFERROR(VLOOKUP(C96, 'QTY_CONVERSIONS '!A:B, 2, FALSE), "Units not found")) -> 20 | M96: =B96*K96 -> 38400 | N96: =IFERROR(VLOOKUP(D96, Product_Category!A:B, 2, FALSE), "Uncategorized") -> MCC | O96: =K96*1000 -> 1920 | P96: =L96*O96 -> 38400 | Q96: 2023 | R96: =IFERROR(VLOOKUP(G96,'SOURCE COMPANY'!A:B, 2, FALSE), "") -> JRS PHARMA | S96: =IFERROR(VLOOKUP(H96,'CUSTOMER NAME'!A:B, 2, FALSE), "") -> ALPHA PHARM
A97: Algeria | B97: 20000 | C97: KGS | D97: PHARMACEL (R) 101 | E97: 2.95 | F97: EUR | G97: DFE PHARMA | H97: ALSOCHEM SARL | I97: December | J97: =IF(F97="USD", E97, E97 * IFERROR(VLOOKUP(F97, EXCHANGE_RATE!A:B, 2, FALSE), "Currency not found")) -> 3.1565 | K97: =ROUNDUP(J97,2) -> 3.16 | L97: =IF(C97="MTS", B97, B97 * IFERROR(VLOOKUP(C97, 'QTY_CONVERSIONS '!A:B, 2, FALSE), "Units not found")) -> 20 | M97: =B97*K97 -> 63200 | N97: =IFERROR(VLOOKUP(D97, Product_Category!A:B, 2, FALSE), "Uncategorized") -> MCC | O97: =K97*1000 -> 3160 | P97: =L97*O97 -> 63200 | Q97: 2023 | R97: =IFERROR(VLOOKUP(G97,'SOURCE COMPANY'!A:B, 2, FALSE), "") -> DFE PHARMA | S97: =IFERROR(VLOOKUP(H97,'CUSTOMER NAME'!A:B, 2, FALSE), "") -> ALSOCHEM SARL
A98: Algeria | B98: 8000 | C98: KGS | D98: PHARMACEL (R) SMCC 90 | E98: 3.36 | F98: EUR | G98: DFE PHARMA | H98: ALSOCHEM SARL | I98: December | J98: =IF(F98="USD", E98, E98 * IFERROR(VLOOKUP(F98, EXCHANGE_RATE!A:B, 2, FALSE), "Currency not found")) -> 3.5952 | K98: =ROUNDUP(J98,2) -> 3.6 | L98: =IF(C98="MTS", B98, B98 * IFERROR(VLOOKUP(C98, 'QTY_CONVERSIONS '!A:B, 2, FALSE), "Units not found")) -> 8 | M98: =B98*K98 -> 28800 | N98: =IFERROR(VLOOKUP(D98, Product_Category!A:B, 2, FALSE), "Uncategorized") -> SMCC | O98: =K98*1000 -> 3600 | P98: =L98*O98 -> 28800 | Q98: 2023 | R98: =IFERROR(VLOOKUP(G98,'SOURCE COMPANY'!A:B, 2, FALSE), "") -> DFE PHARMA | S98: =IFERROR(VLOOKUP(H98,'CUSTOMER NAME'!A:B, 2, FALSE), "") -> ALSOCHEM SARL
A99: Algeria | B99: 44000 | C99: KGS | D99: PHARMACEL (R) 102 | E99: 2.95 | F99: EUR | G99: DFE PHARMA | H99: ALSOCHEM SARL | I99: December | J99: =IF(F99="USD", E99, E99 * IFERROR(VLOOKUP(F99, EXCHANGE_RATE!A:B, 2, FALSE), "Currency not found")) -> 3.1565 | K99: =ROUNDUP(J99,2) -> 3.16 | L99: =IF(C99="MTS", B99, B99 * IFERROR(VLOOKUP(C99, 'QTY_CONVERSIONS '!A:B, 2, FALSE), "Units not found")) -> 44 | M99: =B99*K99 -> 139040 | N99: =IFERROR(VLOOKUP(D99, Product_Category!A:B, 2, FALSE), "Uncategorized") -> MCC | O99: =K99*1000 -> 3160 | P99: =L99*O99 -> 139040 | Q99: 2023 | R99: =IFERROR(VLOOKUP(G99,'SOURCE COMPANY'!A:B, 2, FALSE), "") -> DFE PHARMA | S99: =IFERROR(VLOOKUP(H99,'CUSTOMER NAME'!A:B, 2, FALSE), "") -> ALSOCHEM SARL
A100: Algeria | B100: 8000 | C100: KGS | D100: PHARMACEL (R) 112 | E100: 3.49 | F100: EUR | G100: DFE PHARMA | H100: ALSOCHEM SARL | I100: December | J100: =IF(F100="USD", E100, E100 * IFERROR(VLOOKUP(F100, EXCHANGE_RATE!A:B, 2, FALSE), "Currency not found")) -> 3.7343 | K100: =ROUNDUP(J100,2) -> 3.74 | L100: =IF(C100="MTS", B100, B100 * IFERROR(VLOOKUP(C100, 'QTY_CONVERSIONS '!A:B, 2, FALSE), "Units not found")) -> 8 | M100: =B100*K100 -> 29920 | N100: =IFERROR(VLOOKUP(D100, Product_Category!A:B, 2, FALSE), "Uncategorized") -> MCC | O100: =K100*1000 -> 3740 | P100: =L100*O100 -> 29920 | Q100: 2023 | R100: =IFERROR(VLOOKUP(G100,'SOURCE COMPANY'!A:B, 2, FALSE), "") -> DFE PHARMA | S100: =IFERROR(VLOOKUP(H100,'CUSTOMER NAME'!A:B, 2, FALSE), "") -> ALSOCHEM SARL
A101: Algeria | B101: 9000 | C101: KGS | D101: PHARMACEL SMCC 90 | E101: 2.6099478 | F101: EUR | G101: DFE PHARMA | H101: ALSOCHEM SARL | I101: Feb | J101: =IF(F101="USD", E101, E101 * IFERROR(VLOOKUP(F101, EXCHANGE_RATE!A:B, 2, FALSE), "Currency not found")) -> 2.7926441 | K101: =ROUNDUP(J101,2) -> 2.8 | L101: =IF(C101="MTS", B101, B101 * IFERROR(VLOOKUP(C101, 'QTY_CONVERSIONS '!A:B, 2, FALSE), "Units not found")) -> 9 | M101: =B101*K101 -> 25200 | N101: =IFERROR(VLOOKUP(D101, Product_Category!A:B, 2, FALSE), "Uncategorized") -> MCC | O101: =K101*1000 -> 2800 | P101: =L101*O101 -> 25200 | Q101: 2023 | R101: =IFERROR(VLOOKUP(G101,'SOURCE COMPANY'!A:B, 2, FALSE), "") -> DFE PHARMA | S101: =IFERROR(VLOOKUP(H101,'CUSTOMER NAME'!A:B, 2, FALSE), "") -> ALSOCHEM SARL
A102: Algeria | B102: 10000 | C102: KGS | D102: MCC PHARMACEL 101 | E102: 2.6699466 | F102: EUR | G102: DFE PHARMA | H102: ALSOCHEM SARL | I102: =I101 -> Feb | J102: =IF(F102="USD", E102, E102 * IFERROR(VLOOKUP(F102, EXCHANGE_RATE!A:B, 2, FALSE), "Currency not found")) -> 2.8568429 | K102: =ROUNDUP(J102,2) -> 2.86 | L102: =IF(C102="MTS", B102, B102 * IFERROR(VLOOKUP(C102, 'QTY_CONVERSIONS '!A:B, 2, FALSE), "Units not found")) -> 10 | M102: =B102*K102 -> 28600 | N102: =IFERROR(VLOOKUP(D102, Product_Category!A:B, 2, FALSE), "Uncategorized") -> MCC | O102: =K102*1000 -> 2860 | P102: =L102*O102 -> 28600 | Q102: 2023 | R102: =IFERROR(VLOOKUP(G102,'SOURCE COMPANY'!A:B, 2, FALSE), "") -> DFE PHARMA | S102: =IFERROR(VLOOKUP(H102,'CUSTOMER NAME'!A:B, 2, FALSE), "") -> ALSOCHEM SARL
A103: Algeria | B103: 1000 | C103: KGS | D103: MCC PHARMACEL 102 | E103: 3.2599348 | F103: EUR | G103: DFE PHARMA | H103: ALSOCHEM SARL | I103: =I102 -> Feb | J103: =IF(F103="USD", E103, E103 * IFERROR(VLOOKUP(F103, EXCHANGE_RATE!A:B, 2, FALSE), "Currency not found")) -> 3.4881302 | K103: =ROUNDUP(J103,2) -> 3.49 | L103: =IF(C103="MTS", B103, B103 * IFERROR(VLOOKUP(C103, 'QTY_CONVERSIONS '!A:B, 2, FALSE), "Units not found")) -> 1 | M103: =B103*K103 -> 3490 | N103: =IFERROR(VLOOKUP(D103, Product_Category!A:B, 2, FALSE), "Uncategorized") -> MCC | O103: =K103*1000 -> 3490 | P103: =L103*O103 -> 3490 | Q103: 2023 | R103: =IFERROR(VLOOKUP(G103,'SOURCE COMPANY'!A:B, 2, FALSE), "") -> DFE PHARMA | S103: =IFERROR(VLOOKUP(H103,'CUSTOMER NAME'!A:B, 2, FALSE), "") -> ALSOCHEM SARL
A104: Algeria | B104: 4000 | C104: KGS | D104: PHARMACELR 112 MCC | E104: 3.47 | F104: EUR | G104: DFE PHARMA | H104: ALSOCHEM SARL | I104: June | J104: =IF(F104="USD", E104, E104 * IFERROR(VLOOKUP(F104, EXCHANGE_RATE!A:B, 2, FALSE), "Currency not found")) -> 3.7129 | K104: =ROUNDUP(J104,2) -> 3.72 | L104: =IF(C104="MTS", B104, B104 * IFERROR(VLOOKUP(C104, 'QTY_CONVERSIONS '!A:B, 2, FALSE), "Units not found")) -> 4 | M104: =B104*K104 -> 14880 | N104: =IFERROR(VLOOKUP(D104, Product_Category!A:B, 2, FALSE), "Uncategorized") -> MCC | O104: =K104*1000 -> 3720 | P104: =L104*O104 -> 14880 | Q104: 2023 | R104: =IFERROR(VLOOKUP(G104,'SOURCE COMPANY'!A:B, 2, FALSE), "") -> DFE PHARMA | S104: =IFERROR(VLOOKUP(H104,'CUSTOMER NAME'!A:B, 2, FALSE), "") -> ALSOCHEM SARL
A105: Algeria | B105: 15000 | C105: KGS | D105: PHARMACELTM 101 MCC | E105: 2.91 | F105: EUR | G105: DFE PHARMA | H105: ALSOCHEM SARL | I105: =I104 -> June | J105: =IF(F105="USD", E105, E105 * IFERROR(VLOOKUP(F105, EXCHANGE_RATE!A:B, 2, FALSE), "Currency not found")) -> 3.1137 | K105: =ROUNDUP(J105,2) -> 3.12 | L105: =IF(C105="MTS", B105, B105 * IFERROR(VLOOKUP(C105, 'QTY_CONVERSIONS '!A:B, 2, FALSE), "Units not found")) -> 15 | M105: =B105*K105 -> 46800 | N105: =IFERROR(VLOOKUP(D105, Product_Category!A:B, 2, FALSE), "Uncategorized") -> MCC | O105: =K105*1000 -> 3120 | P105: =L105*O105 -> 46800 | Q105: 2023 | R105: =IFERROR(VLOOKUP(G105,'SOURCE COMPANY'!A:B, 2, FALSE), "") -> DFE PHARMA | S105: =IFERROR(VLOOKUP(H105,'CUSTOMER NAME'!A:B, 2, FALSE), "") -> ALSOCHEM SARL
A106: Algeria | B106: 39000 | C106: KGS | D106: PHARMACELTM 102 MCC | E106: 2.91 | F106: EUR | G106: DFE PHARMA | H106: ALSOCHEM SARL | I106: =I105 -> June | J106: =IF(F106="USD", E106, E106 * IFERROR(VLOOKUP(F106, EXCHANGE_RATE!A:B, 2, FALSE), "Currency not found")) -> 3.1137 | K106: =ROUNDUP(J106,2) -> 3.12 | L106: =IF(C106="MTS", B106, B106 * IFERROR(VLOOKUP(C106, 'QTY_CONVERSIONS '!A:B, 2, FALSE), "Units not found")) -> 39 | M106: =B106*K106 -> 121680 | N106: =IFERROR(VLOOKUP(D106, Product_Category!A:B, 2, FALSE), "Uncategorized") -> MCC | O106: =K106*1000 -> 3120 | P106: =L106*O106 -> 121680 | Q106: 2023 | R106: =IFERROR(VLOOKUP(G106,'SOURCE COMPANY'!A:B, 2, FALSE), "") -> DFE PHARMA | S106: =IFERROR(VLOOKUP(H106,'CUSTOMER NAME'!A:B, 2, FALSE), "") -> ALSOCHEM SARL
A107: Algeria | B107: 10000 | C107: KGS | D107: PHARMACELTM 101 | E107: 2.86 | F107: EUR | G107: DFE PHARMA | H107: ALSOCHEM SARL | I107: September | J107: =IF(F107="USD", E107, E107 * IFERROR(VLOOKUP(F107, EXCHANGE_RATE!A:B, 2, FALSE), "Currency not found")) -> 3.0602 | K107: =ROUNDUP(J107,2) -> 3.07 | L107: =IF(C107="MTS", B107, B107 * IFERROR(VLOOKUP(C107, 'QTY_CONVERSIONS '!A:B, 2, FALSE), "Units not found")) -> 10 | M107: =B107*K107 -> 30700 | N107: =IFERROR(VLOOKUP(D107, Product_Category!A:B, 2, FALSE), "Uncategorized") -> MCC | O107: =K107*1000 -> 3070 | P107: =L107*O107 -> 30700 | Q107: 2023 | R107: =IFERROR(VLOOKUP(G107,'SOURCE COMPANY'!A:B, 2, FALSE), "") -> DFE PHARMA | S107: =IFERROR(VLOOKUP(H107,'CUSTOMER NAME'!A:B, 2, FALSE), "") -> ALSOCHEM SARL
A108: Algeria | B108: 17000 | C108: KGS | D108: PHARMACELTM 102 | E108: 2.85 | F108: EUR | G108: DFE PHARMA | H108: ALSOCHEM SARL | I108: September | J108: =IF(F108="USD", E108, E108 * IFERROR(VLOOKUP(F108, EXCHANGE_RATE!A:B, 2, FALSE), "Currency not found")) -> 3.0495 | K108: =ROUNDUP(J108,2) -> 3.05 | L108: =IF(C108="MTS", B108, B108 * IFERROR(VLOOKUP(C108, 'QTY_CONVERSIONS '!A:B, 2, FALSE), "Units not found")) -> 17 | M108: =B108*K108 -> 51850 | N108: =IFERROR(VLOOKUP(D108, Product_Category!A:B, 2, FALSE), "Uncategorized") -> MCC | O108: =K108*1000 -> 3050 | P108: =L108*O108 -> 51850 | Q108: 2023 | R108: =IFERROR(VLOOKUP(G108,'SOURCE COMPANY'!A:B, 2, FALSE), "") -> DFE PHARMA | S108: =IFERROR(VLOOKUP(H108,'CUSTOMER NAME'!A:B, 2, FALSE), "") -> ALSOCHEM SARL
...

Sheet Product_Category
A1: Product Name | B1: Category
A2: MCCP ACECEL 102 (90M) USP | B2: MCC
A3: MICROCEL MCC-101 | B3: MCC
A4: MICROCEL MCC-102 | B4: MCC
A5: MICROCEL MCC-200 | B5: MCC
A6: SODIUM CMC | B6: CMC
A7: CELLULOSE ETHER-SODIUM CMC | B7: CMC
A8: GRINDSTED CELLULOSE GUM SODIUM CMC | B8: CMC
A9: SODIUM CMC USP | B9: CMC
A10: CMC | B10: CMC
A11: PROSOLV SMCC 50 | B11: MCC
A12: FINNFIX 10 - SODIUM CMC | B12: CMC
... A1075: MICROCEL MC-101 MCC | B1075: MCC
A1076: MICROCEL MC-101 SCOPE MCC | B1076: =B1075 -> MCC
A1077: MICROCEL MC-102 SCOPE MCC | B1077: =B1076 -> MCC
A1078: MCC MICROCEL 112 | B1078: =B1077 -> MCC
A1079: PROSOLV SMCC 51 | B1079: =B1078 -> MCC
A1080: PROSOLV SMCC 52 | B1080: =B1079 -> MCC
A1081: PROSOLV SMCC 53 | B1081: =B1080 -> MCC
A1082: PROSOLV SMCC HD 90 | B1082: =B1081 -> MCC
A1083: FINNFIX 150 SODIUM CMC | B1083: CMC
A1084: CEKOL 700 SODIUM CMC | B1084: =B1083 -> CMC
A1085: BLANOSE SODIUM CMC- PH | B1085: =B1084 -> CMC
A1086: BLANOSE SODIUM CMC 7HF PH | B1086: =B1085 -> CMC
A1087: BLANOSE TM SODIUM CMC | B1087: =B1086 -> CMC
A1088: VIVAPUR CS 450 S MCC | B1088: MCC
A1089: VIVAPUR MCC SPHERES 350 | B1089: MCC SPHERES
A1090: VIVAPUR 102 V-102-NF MCC | B1090: =B1088 -> MCC
A1091: VIVAPUR 101 MCC | B1091: MCC
A1092: EMCOCEL 90 M-MCC NFPH.EUR JP | B1092: =B1090 -> MCC
A1093: PARTECK CCS Ph.Eur.JPNF | B1093: CROSCARMELLOSE SODIUM
A1094: AVICEL PH-101 MCC NFPH EUR JP | B1094: MCC
A1095: AVICEL PH-102 MCC NF PH EUR JP | B1095: MCC
A1096: AVICEL PH-112 LN MCC NF PH EUR JP | B1096: MCC
A1097: AVICEL R PH-101 - MCC NF PH.EUR.JP | B1097: MCC
A1098: AVICEL R PH-102 - MCC NF PH. EUR.JP | B1098: MCC
A1099: AVICEL PH-105 MCC NFPH EUR JP | B1099: MCC
A1100: AVICEL PH-200 LM MCC USP NF EP JP | B1100: MCC
A1101: AVICEL PH-302 MCC NF PH. EUR. JP | B1101: MCC
A1102: AVICEL RC-591 MCC/SODIUM CMC NFPH.EUR.JP | B1102: MCC
A1103: AVICEL SMCC 50 NF PH EUR JP | B1103: MCC
A1104: AVICELR PH-101 LN MCC NFPH.EUR.JP | B1104: MCC
... A1130: MCC PH-112 BP/USP | B1130: MCC
A1131: TABCELL MCC PH-1 | B1131: =B1130 -> MCC
A1132: SSG EXPLOTAB USP | B1132: SSG
A1133: MCCP ACECEL 102 | B1133: =B1131 -> MCC
A1134: MCCP USP ACECEL 102 | B1134: MCC
A1135: MCC BP RQ102 | B1135: =B1133 -> MCC
A1136: MCC AND GUAR GUM | B1136: =B1134 -> MCC
A1137: Mg STERATE LIGAMED-MF-2-V | B1137: MAGNESIUM STEARATE
A1138: CCS AC-DI-SOL USP/NF | B1138: CROSCARMELLOSE SODIUM
A1139: MCC AVICEL PH101 USP/NF | B1139: MCC
A1140: ROQUETTE MG STEARATE LS USP/NF,EP, JP | B1140: MAGNESIUM STEARATE
A1141: AVICEL SMCC 90 | B1141: MCC
A1142: MCC ACCEL - 102 D | B1142: MCC
A1143: MCC ACCEL 102 | B1143: MCC
A1144: MG STEARATE IP/BP/EP/USP | B1144: MAGNESIUM STEARATE
A1145: TABLUBE MG STERATE BP | B1145: MAGNESIUM STEARATE
A1146: MCC AND SODIUM CMC HICEL MCG 591 USP/BP | B1146: CMC
A1147: MCC CHEMICEL PH-112 | B1147: MCC
A1148: MCC CHEMICEL PH-102 | B1148: =B1147 -> MCC
A1149: MCC CHEMICEL PH-302 | B1149: =B1148 -> MCC
A1150: MCC CHEMICEL PH-101 | B1150: =B1149 -> MCC
A1151: MCC USPNF CEOLUS | B1151: =B1150 -> MCC
A1152: MG STEARATE USPNF | B1152: MAGNESIUM STEARATE
A1153: MICCEL-102 MCC EP | B1153: MCC
A1154: TABCELL MCC -USP | B1154: =B1153 -> MCC
A1155: MAGNESIUM STEARATE EP/USP | B1155: MAGNESIUM STEARATE
A1156: SPRAY DRIED TABCELL MCC | B1156: =B1154 -> MCC
A1157: MG STEARATE USP/BP/EP | B1157: MAGNESIUM STEARATE
A1158: MCC RQ 200 | B1158: =B1156 -> MCC
A1159: MCC RQ 101 | B1159: MCC
A1160: MCC BP/USP NF | B1160: =B1158 -> MCC
A1161: MCC BP G-101 | B1161: =B1159 -> MCC
A1162: CCS VIVASOL GF PH.EUR, JP- NF | B1162: CROSCARMELLOSE SODIUM
A1163: TABLUBE MG STERATE USP/NF | B1163: MAGNESIUM STEARATE
A1164: MCC NF AVICEL P | B1164: MCC
A1165: MCC AMCELL 101 BP | B1165: =B1164 -> MCC
A1166: MCC FR-CELL 101 | B1166: =B1165 -> MCC
A1167: MCC FR-CELL 102 | B1167: =B1166 -> MCC
A1168: MCC FR-CELL 112 | B1168: =B1167 -> MCC
A1169: MCC FR-CELL 200 | B1169: =B1168 -> MCC
A1170: CCS AC-DI-SOL | B1170: CROSCARMELLOSE SODIUM
A1171: MG STEARATE PH.EUR | B1171: MAGNESIUM STEARATE
A1172: MCC 101 HiC | B1172: =B1169 -> MCC
A1173: MCC 102 HiCe | B1173: MCC
A1174: MCC pH- 112 BP | B1174: MCC
A1175: MCC ACCEL N 102 | B1175: =B1172 -> MCC
A1176: CMC SODIUM BLANOSE | B1176: CMC
A1177: MCC 103 | B1177: MCC
A1178: MCC 104 | B1178: MCC
A1179: TABLUBE MG STEARATE IP | B1179: MAGNESIUM STEARATE
A1180: MCC IP ACCEL N | B1180: MCC
A1181: MCCP-101 SPRAY DRIED | B1181: MCC
A1182: MCCP-102 IP/BP | B1182: MCC
A1183: CCSM USP | B1183: CROSCARMELLOSE SODIUM
A1184: MCC PHARMACEL R101 | B1184: =B1182 -> MCC
A1185: MCC PHARMACEL R102 | B1185: MCC
A1186: PHARMACELR SMCC 90 | B1186: =B1184 -> MCC
A1187: MCC PHARMACEL R112 | B1187: =B1185 -> MCC
...

Sheet EXCHANGE_RATE
A1: Currency | B1: EXCHANGE RATE TO USD
A2: INR | B2: 0.012
A3: EUR | B3: 1.07
A4: CNY | B4: 0.14
A5: JPY | B5: 0.0067
A6: RUR | B6: 0.01
A7: AUD | B7: 0.64
A8: GBP | B8: 1.27
A9: THB | B9: 0.027
A10: AED | B10: 0.27
A11: ZAR | B11: 0.053

Sheet QTY_CONVERSIONS 
A1: Units | B1: Coversions
A2: GMS | B2: 1e-06
A3: KGS | B3: 0.001
A4: PCS | B4: 0.2
A5: LTR | B5: 0.001

Sheet SOURCE COMPANY
A1: SOURCE COMPANY | B1: SOURCE_COMPANY_FINAL
A2: 3F INDUSTRIES | B2: 3F INDUSTRIES
A3: 4S LOGISTIC | B3: 4S LOGISTIC
A4: 5TH FLOOR, B-505, PLOT NO. B-4/5, C | B4: 5TH FLOOR, B-505, PLOT NO. B-4/5, C
A5: A R ENTERPRISE | B5: A R ENTERPRISE
A6: AADI OVERSEAS | B6: AADI OVERSEAS
A7: AADIVIGHNESH CHEM | B7: AADIVIGHNESH CHEM
A8: AALAKSHYA PHARMA | B8: AALAKSHYA PHARMA
A9: ACCENT | B9: ACCENT
A10: ADITYA IMPEX | B10: ADITYA IMPEX
A11: Advanced Enzyme Tech | B11: Advanced Enzyme Tech
A12: Afiq Pharma | B12: Afiq Pharma
... A454: ZYMETH PHARMA | B454: ZYMETH PHARMA

Sheet CUSTOMER NAME
A1: CUSTOMER NAME | B1: CUSTOMER_NAME_FINAL
A2: 5 N T T | B2: 5 N T T
A3: A B C S MEXICO | B3: A B C S MEXICO
A4: A M SWEDISH | B4: A M SWEDISH
A5: AADEE REMEDIES | B5: AADEE REMEDIES
A6: ABSA BANK | B6: ABSA BANK
A7: ACCESS PHARMA | B7: ACCESS PHARMA
A8: ACCORD PHARMA | B8: ACCORD PHARMA
A9: ACE FORTUNE | B9: ACE FORTUNE
A10: ACE HEALTHCARE (PVT) LTD | B10: ACE HEALTHCARE (PVT) LTD
A11: ACI HEALTHCARE | B11: ACI HEALTHCARE
A12: ADCHEM INTERNATIONAL | B12: ADCHEM INTERNATIONAL
... A1081: ZISKA PHARMA | B1081: ZISKA PHARMA

Sheet Importer Name
A1: IMPORTER NAME | B1: IMPORTER NAME_FINAL
A2: SIGACHI INDUSTRIES | B2: SIGACHI INDUSTRIES
A3: AZELIS (INDIA) | B3: AZELIS (INDIA)
A4: Nipra Hydro | B4: Nipra Hydro
A5: BENTEC ORGANO | B5: BENTEC ORGANO
A6: PERRY TRADING | B6: PERRY TRADING
A7: PRACHIN CHEMICAL | B7: PRACHIN CHEMICAL
A8: INGREDION INDIA | B8: INGREDION INDIA
A9: DAFFODIL PHARMA | B9: DAFFODIL PHARMA
A10: DANISCO (INDIA) | B10: DANISCO (INDIA)
A11: MERIDIAN POLYMERS | B11: MERIDIAN POLYMERS
A12: COLGATE-PALMOLIVE | B12: COLGATE-PALMOLIVE
... A380: Dr. Reddy's Labs | B380: Dr. Reddy's Labs

Sheet Supplier name 
A1: SUPPLIER NAME | B1: SUPPLIER NAME_FINAL
A2: RAVENSWOOD | B2: RAVENSWOOD
A3: ITACEL FARMO | B3: ITACEL FARMO
A4: ANQIU EAGLE | B4: ANQIU EAGLE
A5: CHANGSHU WEALTHY | B5: CHANGSHU WEALTHY
A6: CHONGQING LIHONG | B6: CHONGQING LIHONG
A7: JIANGSU GUOTAI | B7: JIANGSU GUOTAI
A8: JIANGSU WEIKEM | B8: JIANGSU WEIKEM
A9: JINING FORTUNE | B9: JINING FORTUNE
A10: KERAY CHEM | B10: KERAY CHEM
A11: M/S. JOIN GOAL | B11: M/S. JOIN GOAL
A12: SHANGHAI SHENGUANG | B12: SHANGHAI SHENGUANG
... A322: AK-PA Tekstil Ihract Pazarlama A.S | B322: AK-PA Tekstil Ihract Pazarlama A.S
